Workbook

Sheet POS_فاکتور
A1: CHAAM
A3: ───────────FJ COD───────────
A4: شماره فاکتور | B4: INV-0279 | D4: تاریخ | E4: 1405/07/19 | F4: شیفت | G4: full
A5: کد پرسنل | C5: =IFERROR(INDEX(اطلاعات_پرسنل!$D$4:$D$63,MATCH(B5,اطلاعات_پرسنل!$A$4:$A$63,0)),"کد یافت نشد") -> فروشگاه | F5: روش پرداخت | G5: کارت
A6: عضویت | D6: کانال | E6: حضوري | F6: پرداخت شده | G6: 0 | I6: chaam
A7: ─────اطلاعات شما─────
A8: نام | D8: نام خانوادگی | F8: شماره تماس
A9: روز تولد | C9: ماه | E9: یادداشت
A10: ──────────────────────────
A11: # | B11: SKU | C11: بارکد | D11: نام محصول | E11: تعداد | F11: قیمت واحد | G11: تخفیف | H11: جمع ردیف
A12: 1 | D12: =IF(B12<>"",IFERROR(INDEX(کاتالوگ_محصولات!$C$4:$C$303,MATCH(B12,کاتالوگ_محصولات!$A$4:$A$303,0)),""),IF(C12<>"",IFERROR(INDEX(کاتالوگ_محصولات!$C$4:$C$303,MATCH(C12,کاتالوگ_محصولات!$B$4:$B$303,0)),IFERROR(INDEX(کاتالوگ_محصولات!$C$4:$C$303,MATCH(C12,کاتالوگ_محصولات!$C$4:$C$303,0)),"")),"")) | E12: 0 | F12: =IF(B12<>"",IFERROR(INDEX(کاتالوگ_محصولات!$H$4:$H$303,MATCH(B12,کاتالوگ_محصولات!$A$4:$A$303,0)),0),IF(C12<>"",IFERROR(INDEX(کاتالوگ_محصولات!$H$4:$H$303,MATCH(C12,کاتالوگ_محصولات!$B$4:$B$303,0)),IFERROR(INDEX(کاتالوگ_محصولات!$H$4:$H$303,MATCH(C12,کاتالوگ_محصولات!$C$4:$C$303,0)),0)),0)) -> 0 | G12: 0 | H12: =MAX(0,E12*F12-G12) -> 0
A13: 2 | D13: =IF(B13<>"",IFERROR(INDEX(کاتالوگ_محصولات!$C$4:$C$303,MATCH(B13,کاتالوگ_محصولات!$A$4:$A$303,0)),""),IF(C13<>"",IFERROR(INDEX(کاتالوگ_محصولات!$C$4:$C$303,MATCH(C13,کاتالوگ_محصولات!$B$4:$B$303,0)),IFERROR(INDEX(کاتالوگ_محصولات!$C$4:$C$303,MATCH(C13,کاتالوگ_محصولات!$C$4:$C$303,0)),"")),"")) | E13: 0 | F13: =IF(B13<>"",IFERROR(INDEX(کاتالوگ_محصولات!$H$4:$H$303,MATCH(B13,کاتالوگ_محصولات!$A$4:$A$303,0)),0),IF(C13<>"",IFERROR(INDEX(کاتالوگ_محصولات!$H$4:$H$303,MATCH(C13,کاتالوگ_محصولات!$B$4:$B$303,0)),IFERROR(INDEX(کاتالوگ_محصولات!$H$4:$H$303,MATCH(C13,کاتالوگ_محصولات!$C$4:$C$303,0)),0)),0)) -> 0 | G13: 0 | H13: =MAX(0,E13*F13-G13) -> 0
A14: 3 | D14: =IF(B14<>"",IFERROR(INDEX(کاتالوگ_محصولات!$C$4:$C$303,MATCH(B14,کاتالوگ_محصولات!$A$4:$A$303,0)),""),IF(C14<>"",IFERROR(INDEX(کاتالوگ_محصولات!$C$4:$C$303,MATCH(C14,کاتالوگ_محصولات!$B$4:$B$303,0)),IFERROR(INDEX(کاتالوگ_محصولات!$C$4:$C$303,MATCH(C14,کاتالوگ_محصولات!$C$4:$C$303,0)),"")),"")) | E14: 0 | F14: =IF(B14<>"",IFERROR(INDEX(کاتالوگ_محصولات!$H$4:$H$303,MATCH(B14,کاتالوگ_محصولات!$A$4:$A$303,0)),0),IF(C14<>"",IFERROR(INDEX(کاتالوگ_محصولات!$H$4:$H$303,MATCH(C14,کاتالوگ_محصولات!$B$4:$B$303,0)),IFERROR(INDEX(کاتالوگ_محصولات!$H$4:$H$303,MATCH(C14,کاتالوگ_محصولات!$C$4:$C$303,0)),0)),0)) -> 0 | G14: 0 | H14: =MAX(0,E14*F14-G14) -> 0
A15: 4 | D15: =IF(B15<>"",IFERROR(INDEX(کاتالوگ_محصولات!$C$4:$C$303,MATCH(B15,کاتالوگ_محصولات!$A$4:$A$303,0)),""),IF(C15<>"",IFERROR(INDEX(کاتالوگ_محصولات!$C$4:$C$303,MATCH(C15,کاتالوگ_محصولات!$B$4:$B$303,0)),IFERROR(INDEX(کاتالوگ_محصولات!$C$4:$C$303,MATCH(C15,کاتالوگ_محصولات!$C$4:$C$303,0)),"")),"")) | E15: 0 | F15: =IF(B15<>"",IFERROR(INDEX(کاتالوگ_محصولات!$H$4:$H$303,MATCH(B15,کاتالوگ_محصولات!$A$4:$A$303,0)),0),IF(C15<>"",IFERROR(INDEX(کاتالوگ_محصولات!$H$4:$H$303,MATCH(C15,کاتالوگ_محصولات!$B$4:$B$303,0)),IFERROR(INDEX(کاتالوگ_محصولات!$H$4:$H$303,MATCH(C15,کاتالوگ_محصولات!$C$4:$C$303,0)),0)),0)) -> 0 | G15: 0 | H15: =MAX(0,E15*F15-G15) -> 0
A16: 5 | D16: =IF(B16<>"",IFERROR(INDEX(کاتالوگ_محصولات!$C$4:$C$303,MATCH(B16,کاتالوگ_محصولات!$A$4:$A$303,0)),""),IF(C16<>"",IFERROR(INDEX(کاتالوگ_محصولات!$C$4:$C$303,MATCH(C16,کاتالوگ_محصولات!$B$4:$B$303,0)),IFERROR(INDEX(کاتالوگ_محصولات!$C$4:$C$303,MATCH(C16,کاتالوگ_محصولات!$C$4:$C$303,0)),"")),"")) | E16: 0 | F16: =IF(B16<>"",IFERROR(INDEX(کاتالوگ_محصولات!$H$4:$H$303,MATCH(B16,کاتالوگ_محصولات!$A$4:$A$303,0)),0),IF(C16<>"",IFERROR(INDEX(کاتالوگ_محصولات!$H$4:$H$303,MATCH(C16,کاتالوگ_محصولات!$B$4:$B$303,0)),IFERROR(INDEX(کاتالوگ_محصولات!$H$4:$H$303,MATCH(C16,کاتالوگ_محصولات!$C$4:$C$303,0)),0)),0)) -> 0 | G16: 0 | H16: =MAX(0,E16*F16-G16) -> 0
A17: 6 | D17: =IF(B17<>"",IFERROR(INDEX(کاتالوگ_محصولات!$C$4:$C$303,MATCH(B17,کاتالوگ_محصولات!$A$4:$A$303,0)),""),IF(C17<>"",IFERROR(INDEX(کاتالوگ_محصولات!$C$4:$C$303,MATCH(C17,کاتالوگ_محصولات!$B$4:$B$303,0)),IFERROR(INDEX(کاتالوگ_محصولات!$C$4:$C$303,MATCH(C17,کاتالوگ_محصولات!$C$4:$C$303,0)),"")),"")) | E17: 0 | F17: =IF(B17<>"",IFERROR(INDEX(کاتالوگ_محصولات!$H$4:$H$303,MATCH(B17,کاتالوگ_محصولات!$A$4:$A$303,0)),0),IF(C17<>"",IFERROR(INDEX(کاتالوگ_محصولات!$H$4:$H$303,MATCH(C17,کاتالوگ_محصولات!$B$4:$B$303,0)),IFERROR(INDEX(کاتالوگ_محصولات!$H$4:$H$303,MATCH(C17,کاتالوگ_محصولات!$C$4:$C$303,0)),0)),0)) -> 0 | G17: 0 | H17: =MAX(0,E17*F17-G17) -> 0
A18: 7 | D18: =IF(B18<>"",IFERROR(INDEX(کاتالوگ_محصولات!$C$4:$C$303,MATCH(B18,کاتالوگ_محصولات!$A$4:$A$303,0)),""),IF(C18<>"",IFERROR(INDEX(کاتالوگ_محصولات!$C$4:$C$303,MATCH(C18,کاتالوگ_محصولات!$B$4:$B$303,0)),IFERROR(INDEX(کاتالوگ_محصولات!$C$4:$C$303,MATCH(C18,کاتالوگ_محصولات!$C$4:$C$303,0)),"")),"")) | E18: 0 | F18: =IF(B18<>"",IFERROR(INDEX(کاتالوگ_محصولات!$H$4:$H$303,MATCH(B18,کاتالوگ_محصولات!$A$4:$A$303,0)),0),IF(C18<>"",IFERROR(INDEX(کاتالوگ_محصولات!$H$4:$H$303,MATCH(C18,کاتالوگ_محصولات!$B$4:$B$303,0)),IFERROR(INDEX(کاتالوگ_محصولات!$H$4:$H$303,MATCH(C18,کاتالوگ_محصولات!$C$4:$C$303,0)),0)),0)) -> 0 | G18: 0 | H18: =MAX(0,E18*F18-G18) -> 0
A19: 8 | D19: =IF(B19<>"",IFERROR(INDEX(کاتالوگ_محصولات!$C$4:$C$303,MATCH(B19,کاتالوگ_محصولات!$A$4:$A$303,0)),""),IF(C19<>"",IFERROR(INDEX(کاتالوگ_محصولات!$C$4:$C$303,MATCH(C19,کاتالوگ_محصولات!$B$4:$B$303,0)),IFERROR(INDEX(کاتالوگ_محصولات!$C$4:$C$303,MATCH(C19,کاتالوگ_محصولات!$C$4:$C$303,0)),"")),"")) | E19: 0 | F19: =IF(B19<>"",IFERROR(INDEX(کاتالوگ_محصولات!$H$4:$H$303,MATCH(B19,کاتالوگ_محصولات!$A$4:$A$303,0)),0),IF(C19<>"",IFERROR(INDEX(کاتالوگ_محصولات!$H$4:$H$303,MATCH(C19,کاتالوگ_محصولات!$B$4:$B$303,0)),IFERROR(INDEX(کاتالوگ_محصولات!$H$4:$H$303,MATCH(C19,کاتالوگ_محصولات!$C$4:$C$303,0)),0)),0)) -> 0 | G19: 0 | H19: =MAX(0,E19*F19-G19) -> 0
A20: 9 | D20: =IF(B20<>"",IFERROR(INDEX(کاتالوگ_محصولات!$C$4:$C$303,MATCH(B20,کاتالوگ_محصولات!$A$4:$A$303,0)),""),IF(C20<>"",IFERROR(INDEX(کاتالوگ_محصولات!$C$4:$C$303,MATCH(C20,کاتالوگ_محصولات!$B$4:$B$303,0)),IFERROR(INDEX(کاتالوگ_محصولات!$C$4:$C$303,MATCH(C20,کاتالوگ_محصولات!$C$4:$C$303,0)),"")),"")) | E20: 0 | F20: =IF(B20<>"",IFERROR(INDEX(کاتالوگ_محصولات!$H$4:$H$303,MATCH(B20,کاتالوگ_محصولات!$A$4:$A$303,0)),0),IF(C20<>"",IFERROR(INDEX(کاتالوگ_محصولات!$H$4:$H$303,MATCH(C20,کاتالوگ_محصولات!$B$4:$B$303,0)),IFERROR(INDEX(کاتالوگ_محصولات!$H$4:$H$303,MATCH(C20,کاتالوگ_محصولات!$C$4:$C$303,0)),0)),0)) -> 0 | G20: 0 | H20: =MAX(0,E20*F20-G20) -> 0
A21: 10 | D21: =IF(B21<>"",IFERROR(INDEX(کاتالوگ_محصولات!$C$4:$C$303,MATCH(B21,کاتالوگ_محصولات!$A$4:$A$303,0)),""),IF(C21<>"",IFERROR(INDEX(کاتالوگ_محصولات!$C$4:$C$303,MATCH(C21,کاتالوگ_محصولات!$B$4:$B$303,0)),IFERROR(INDEX(کاتالوگ_محصولات!$C$4:$C$303,MATCH(C21,کاتالوگ_محصولات!$C$4:$C$303,0)),"")),"")) | E21: 0 | F21: =IF(B21<>"",IFERROR(INDEX(کاتالوگ_محصولات!$H$4:$H$303,MATCH(B21,کاتالوگ_محصولات!$A$4:$A$303,0)),0),IF(C21<>"",IFERROR(INDEX(کاتالوگ_محصولات!$H$4:$H$303,MATCH(C21,کاتالوگ_محصولات!$B$4:$B$303,0)),IFERROR(INDEX(کاتالوگ_محصولات!$H$4:$H$303,MATCH(C21,کاتالوگ_محصولات!$C$4:$C$303,0)),0)),0)) -> 0 | G21: 0 | H21: =MAX(0,E21*F21-G21) -> 0
A22: ─────────────────────
A23: جمع قبل از تخفیف | E23: =SUMPRODUCT(E12:E21,F12:F21) -> 0
A24: تخفیف کل | E24: =SUM(G12:G21) -> 0
A25: مبلغ نهایی | E25: =MAX(0,E23-E24) -> 0
A26: تعداد اقلام | E26: =SUM(E12:E21) -> 0
A27: مانده (دریافتی - مبلغ) | E27: =IFERROR(G6-E25,0) -> 0
A29: 💛چام مدِ نجیب و امروزی زنانه💛
A30: insta: chaamofficial | chaamofficial.ir
A32: ▶ دکمه «ثبت فاکتور» را بزنید | Button «RegisterInvoice»
A33: 📋 بعد از ثبت، فاکتور پاک و شماره +۱ می‌شود | داده در «لاگ_فاکتور» ذخیره می‌شود

Sheet لاگ_فاکتور
A1: لاگ فاکتور
A2: شماره فاکتور Inv_No | B2: تاریخ Date | C2: کد پرسنل Staff_ID | D2: نام پرسنل Staff | E2: شیفت Shift | F2: روش پرداخت Payment | G2: نوع مشتری Cust_Type | H2: کانال Channel | I2: SKU | J2: بارکد/نام ورودی Product_Input | K2: نام کامل محصول Product_Name | L2: تعداد Qty | M2: قیمت واحد Unit_Price | N2: تخفیف Discount | O2: جمع ردیف Line_Total | P2: نام مشتری Cust_First | Q2: نام خانوادگی Cust_Last | R2: شماره تماس Phone | S2: روز تولد Birth_Day | T2: ماه تولد Birth_Month | U2: یادداشت Notes | V2: پرچم فاکتور | W2: فروش ناخالص ردیف | X2: کلید مشتری | Y2: مشتری جدید | Z2: فاکتور تکراری | AA2: مبلغ فاکتور | AB2: اقلام فاکتور | AC2: بهای تمام‌شده | AD2: حاشیه سود | AE2: ماه گزارش
A3: INV-0200 | B3: 1405/07/01 | C3: 0 | D3: فروشگاه | E3: full | F3: کارت | G3: جدید | H3: کانال | J3: کیف 4148 | K3: کیف 4148 | L3: 1 | M3: 2000000 | N3: 0 | O3: 2000000 | U3: خرید خانم صانعی | V3: =IF(A3="",0,IF(COUNTIF($A$3:A3,A3)=1,1,0)) -> 1 | W3: =IF(A3="",0,L3*M3) -> 2000000 | X3: =IF(R3<>"",R3,IF(AND(P3<>"",Q3<>""),P3&"|"&Q3,"")) | Y3: =IF(X3="",0,IF(COUNTIF($X$3:X3,X3)=1,1,0)) -> 0 | Z3: =IF(V3<>1,0,IF(X3="",0,IF(COUNTIF($X$2:X2,X3)>0,1,0))) -> 0 | AA3: =IF(V3=1,SUMIF($A$3:$A$1622,A3,$O$3:$O$1622),0) -> 2000000 | AB3: =IF(V3=1,SUMIF($A$3:$A$1622,A3,$L$3:$L$1622),0) -> 1 | AC3: =IF(I3="",0,L3*IFERROR(INDEX(کاتالوگ_محصولات!$G$4:$G$303,MATCH(I3,کاتالوگ_محصولات!$A$4:$A$303,0)),0)) -> 0 | AD3: =IF(A3="",0,O3-AC3) -> 2000000 | AE3: =IF(B3="","",LEFT(B3,7)) -> 1405/07
A4: INV-0201 | B4: 1405/07/02 | C4: 2 | D4: ماحی حمیدپور | E4: PM | F4: کارت | G4: جدید | H4: کانال | J4: شومیز لینن سونای سرمه ای 2 | K4: شومیز لینن سونای سرمه ای 2 | L4: 1 | M4: 1350000 | N4: 0 | O4: 1350000 | P4: نوشین | Q4: ایرانپور | R4: 9352269323 | S4: 14 | T4: 1360/01 | U4: پیوست فاکتور 195 | V4: =IF(A4="",0,IF(COUNTIF($A$3:A4,A4)=1,1,0)) -> 1 | W4: =IF(A4="",0,L4*M4) -> 1350000 | X4: =IF(R4<>"",R4,IF(AND(P4<>"",Q4<>""),P4&"|"&Q4,"")) -> 9352269323 | Y4: =IF(X4="",0,IF(COUNTIF($X$3:X4,X4)=1,1,0)) -> 1 | Z4: =IF(V4<>1,0,IF(X4="",0,IF(COUNTIF($X$3:X3,X4)>0,1,0))) -> 0 | AA4: =IF(V4=1,SUMIF($A$3:$A$1622,A4,$O$3:$O$1622),0) -> 1350000 | AB4: =IF(V4=1,SUMIF($A$3:$A$1622,A4,$L$3:$L$1622),0) -> 1 | AC4: =IF(I4="",0,L4*IFERROR(INDEX(کاتالوگ_محصولات!$G$4:$G$303,MATCH(I4,کاتالوگ_محصولات!$A$4:$A$303,0)),0)) -> 0 | AD4: =IF(A4="",0,O4-AC4) -> 1350000 | AE4: =IF(B4="","",LEFT(B4,7)) -> 1405/07
A5: INV-0202 | B5: 1405/07/02 | C5: 0 | D5: فروشگاه | E5: full | F5: کارت | G5: جدید | H5: کانال | J5: شومیز دریا کرم سایز1 | K5: شومیز دریا کرم سایز1 | L5: 1 | M5: 1980000 | N5: 0 | O5: 1980000 | P5: ساره | Q5: قدیانی | R5: 9129419189 | S5: 26 | T5: 1367/08 | V5: =IF(A5="",0,IF(COUNTIF($A$3:A5,A5)=1,1,0)) -> 1 | W5: =IF(A5="",0,L5*M5) -> 1980000 | X5: =IF(R5<>"",R5,IF(AND(P5<>"",Q5<>""),P5&"|"&Q5,"")) -> 9129419189 | Y5: =IF(X5="",0,IF(COUNTIF($X$3:X5,X5)=1,1,0)) -> 1 | Z5: =IF(V5<>1,0,IF(X5="",0,IF(COUNTIF($X$3:X4,X5)>0,1,0))) -> 0 | AA5: =IF(V5=1,SUMIF($A$3:$A$1622,A5,$O$3:$O$1622),0) -> 3960000 | AB5: =IF(V5=1,SUMIF($A$3:$A$1622,A5,$L$3:$L$1622),0) -> 2 | AC5: =IF(I5="",0,L5*IFERROR(INDEX(کاتالوگ_محصولات!$G$4:$G$303,MATCH(I5,کاتالوگ_محصولات!$A$4:$A$303,0)),0)) -> 0 | AD5: =IF(A5="",0,O5-AC5) -> 1980000 | AE5: =IF(B5="","",LEFT(B5,7)) -> 1405/07
A6: INV-0202 | B6: 1405/07/02 | C6: 0 | D6: فروشگاه | E6: full | F6: کارت | G6: جدید | H6: کانال | J6: شومیز دریا صورتی سایز1 | K6: شومیز دریا صورتی سایز1 | L6: 1 | M6: 1980000 | N6: 0 | O6: 1980000 | P6: ساره | Q6: قدیانی | R6: 9129419189 | S6: 26 | T6: 1367/08 | V6: =IF(A6="",0,IF(COUNTIF($A$3:A6,A6)=1,1,0)) -> 0 | W6: =IF(A6="",0,L6*M6) -> 1980000 | X6: =IF(R6<>"",R6,IF(AND(P6<>"",Q6<>""),P6&"|"&Q6,"")) -> 9129419189 | Y6: =IF(X6="",0,IF(COUNTIF($X$3:X6,X6)=1,1,0)) -> 0 | Z6: =IF(V6<>1,0,IF(X6="",0,IF(COUNTIF($X$3:X5,X6)>0,1,0))) -> 0 | AA6: =IF(V6=1,SUMIF($A$3:$A$1622,A6,$O$3:$O$1622),0) -> 0 | AB6: =IF(V6=1,SUMIF($A$3:$A$1622,A6,$L$3:$L$1622),0) -> 0 | AC6: =IF(I6="",0,L6*IFERROR(INDEX(کاتالوگ_محصولات!$G$4:$G$303,MATCH(I6,کاتالوگ_محصولات!$A$4:$A$303,0)),0)) -> 0 | AD6: =IF(A6="",0,O6-AC6) -> 1980000 | AE6: =IF(B6="","",LEFT(B6,7)) -> 1405/07
A7: INV-0203 | B7: 1405/07/02 | C7: 2 | D7: ماحی حمیدپور | E7: PM | F7: کارت | G7: جدید | H7: کانال | J7: شومیز ویولا سرخابی سایز1 | K7: شومیز ویولا سرخابی سایز1 | L7: 1 | M7: 2086000 | N7: 0 | O7: 2086000 | P7: دینا | Q7: پیمایی | R7: 9123871328 | S7: 24 | T7: 9 | V7: =IF(A7="",0,IF(COUNTIF($A$3:A7,A7)=1,1,0)) -> 1 | W7: =IF(A7="",0,L7*M7) -> 2086000 | X7: =IF(R7<>"",R7,IF(AND(P7<>"",Q7<>""),P7&"|"&Q7,"")) -> 9123871328 | Y7: =IF(X7="",0,IF(COUNTIF($X$3:X7,X7)=1,1,0)) -> 1 | Z7: =IF(V7<>1,0,IF(X7="",0,IF(COUNTIF($X$3:X6,X7)>0,1,0))) -> 0 | AA7: =IF(V7=1,SUMIF($A$3:$A$1622,A7,$O$3:$O$1622),0) -> 2086000 | AB7: =IF(V7=1,SUMIF($A$3:$A$1622,A7,$L$3:$L$1622),0) -> 1 | AC7: =IF(I7="",0,L7*IFERROR(INDEX(کاتالوگ_محصولات!$G$4:$G$303,MATCH(I7,کاتالوگ_محصولات!$A$4:$A$303,0)),0)) -> 0 | AD7: =IF(A7="",0,O7-AC7) -> 2086000 | AE7: =IF(B7="","",LEFT(B7,7)) -> 1405/07
A8: INV-0204 | B8: 1405/07/02 | C8: 2 | D8: ماحی حمیدپور | E8: PM | F8: کارت | G8: جدید | H8: کانال | J8: شومیز تایملس مشکی فری | K8: شومیز تایملس مشکی فری | L8: 1 | M8: 2200000 | N8: 0 | O8: 2200000 | P8: میترا | Q8: حشمتی | R8: 9194452406 | V8: =IF(A8="",0,IF(COUNTIF($A$3:A8,A8)=1,1,0)) -> 1 | W8: =IF(A8="",0,L8*M8) -> 2200000 | X8: =IF(R8<>"",R8,IF(AND(P8<>"",Q8<>""),P8&"|"&Q8,"")) -> 9194452406 | Y8: =IF(X8="",0,IF(COUNTIF($X$3:X8,X8)=1,1,0)) -> 1 | Z8: =IF(V8<>1,0,IF(X8="",0,IF(COUNTIF($X$3:X7,X8)>0,1,0))) -> 0 | AA8: =IF(V8=1,SUMIF($A$3:$A$1622,A8,$O$3:$O$1622),0) -> 2200000 | AB8: =IF(V8=1,SUMIF($A$3:$A$1622,A8,$L$3:$L$1622),0) -> 1 | AC8: =IF(I8="",0,L8*IFERROR(INDEX(کاتالوگ_محصولات!$G$4:$G$303,MATCH(I8,کاتالوگ_محصولات!$A$4:$A$303,0)),0)) -> 0 | AD8: =IF(A8="",0,O8-AC8) -> 2200000 | AE8: =IF(B8="","",LEFT(B8,7)) -> 1405/07
A9: INV-0205 | B9: 1405/07/03 | C9: 2 | D9: ماحی حمیدپور | E9: full | F9: اسنپ پی | G9: جدید | H9: کانال | J9: کت سبز | K9: کت سبز | L9: 1 | M9: 1800000 | N9: 0 | O9: 1800000 | P9: سمیرا | Q9: باجلان | R9: 9383159588 | S9: 2 | T9: 8 | U9: آپ سل 15 میلیونی | V9: =IF(A9="",0,IF(COUNTIF($A$3:A9,A9)=1,1,0)) -> 1 | W9: =IF(A9="",0,L9*M9) -> 1800000 | X9: =IF(R9<>"",R9,IF(AND(P9<>"",Q9<>""),P9&"|"&Q9,"")) -> 9383159588 | Y9: =IF(X9="",0,IF(COUNTIF($X$3:X9,X9)=1,1,0)) -> 1 | Z9: =IF(V9<>1,0,IF(X9="",0,IF(COUNTIF($X$3:X8,X9)>0,1,0))) -> 0 | AA9: =IF(V9=1,SUMIF($A$3:$A$1622,A9,$O$3:$O$1622),0) -> 13750000 | AB9: =IF(V9=1,SUMIF($A$3:$A$1622,A9,$L$3:$L$1622),0) -> 4 | AC9: =IF(I9="",0,L9*IFERROR(INDEX(کاتالوگ_محصولات!$G$4:$G$303,MATCH(I9,کاتالوگ_محصولات!$A$4:$A$303,0)),0)) -> 0 | AD9: =IF(A9="",0,O9-AC9) -> 1800000 | AE9: =IF(B9="","",LEFT(B9,7)) -> 1405/07
A10: INV-0205 | B10: 1405/07/03 | C10: 2 | D10: ماحی حمیدپور | E10: full | F10: اسنپ پی | G10: جدید | H10: کانال | J10: کت ژاکارد صورتی 1 | K10: کت ژاکارد صورتی 1 | L10: 1 | M10: 3850000 | N10: 0 | O10: 3850000 | P10: سمیرا | Q10: باجلان | R10: 9383159588 | S10: 2 | T10: 8 | V10: =IF(A10="",0,IF(COUNTIF($A$3:A10,A10)=1,1,0)) -> 0 | W10: =IF(A10="",0,L10*M10) -> 3850000 | X10: =IF(R10<>"",R10,IF(AND(P10<>"",Q10<>""),P10&"|"&Q10,"")) -> 9383159588 | Y10: =IF(X10="",0,IF(COUNTIF($X$3:X10,X10)=1,1,0)) -> 0 | Z10: =IF(V10<>1,0,IF(X10="",0,IF(COUNTIF($X$3:X9,X10)>0,1,0))) -> 0 | AA10: =IF(V10=1,SUMIF($A$3:$A$1622,A10,$O$3:$O$1622),0) -> 0 | AB10: =IF(V10=1,SUMIF($A$3:$A$1622,A10,$L$3:$L$1622),0) -> 0 | AC10: =IF(I10="",0,L10*IFERROR(INDEX(کاتالوگ_محصولات!$G$4:$G$303,MATCH(I10,کاتالوگ_محصولات!$A$4:$A$303,0)),0)) -> 0 | AD10: =IF(A10="",0,O10-AC10) -> 3850000 | AE10: =IF(B10="","",LEFT(B10,7)) -> 1405/07
A11: INV-0205 | B11: 1405/07/03 | C11: 2 | D11: ماحی حمیدپور | E11: full | F11: اسنپ پی | G11: جدید | H11: کانال | J11: کت ژاکارد ابی سایز 1 | K11: کت ژاکارد ابی سایز 1 | L11: 1 | M11: 3850000 | N11: 0 | O11: 3850000 | P11: سمیرا | Q11: باجلان | R11: 9383159588 | S11: 2 | T11: 8 | V11: =IF(A11="",0,IF(COUNTIF($A$3:A11,A11)=1,1,0)) -> 0 | W11: =IF(A11="",0,L11*M11) -> 3850000 | X11: =IF(R11<>"",R11,IF(AND(P11<>"",Q11<>""),P11&"|"&Q11,"")) -> 9383159588 | Y11: =IF(X11="",0,IF(COUNTIF($X$3:X11,X11)=1,1,0)) -> 0 | Z11: =IF(V11<>1,0,IF(X11="",0,IF(COUNTIF($X$3:X10,X11)>0,1,0))) -> 0 | AA11: =IF(V11=1,SUMIF($A$3:$A$1622,A11,$O$3:$O$1622),0) -> 0 | AB11: =IF(V11=1,SUMIF($A$3:$A$1622,A11,$L$3:$L$1622),0) -> 0 | AC11: =IF(I11="",0,L11*IFERROR(INDEX(کاتالوگ_محصولات!$G$4:$G$303,MATCH(I11,کاتالوگ_محصولات!$A$4:$A$303,0)),0)) -> 0 | AD11: =IF(A11="",0,O11-AC11) -> 3850000 | AE11: =IF(B11="","",LEFT(B11,7)) -> 1405/07
A12: INV-0205 | B12: 1405/07/03 | C12: 2 | D12: ماحی حمیدپور | E12: full | F12: اسنپ پی | G12: جدید | H12: کانال | J12: کت شنل سایز1 | K12: کت شنل سایز1 | L12: 1 | M12: 4250000 | N12: 0 | O12: 4250000 | P12: سمیرا | Q12: باجلان | R12: 9383159588 | S12: 2 | T12: 8 | V12: =IF(A12="",0,IF(COUNTIF($A$3:A12,A12)=1,1,0)) -> 0 | W12: =IF(A12="",0,L12*M12) -> 4250000 | X12: =IF(R12<>"",R12,IF(AND(P12<>"",Q12<>""),P12&"|"&Q12,"")) -> 9383159588 | Y12: =IF(X12="",0,IF(COUNTIF($X$3:X12,X12)=1,1,0)) -> 0 | Z12: =IF(V12<>1,0,IF(X12="",0,IF(COUNTIF($X$3:X11,X12)>0,1,0))) -> 0 | AA12: =IF(V12=1,SUMIF($A$3:$A$1622,A12,$O$3:$O$1622),0) -> 0 | AB12: =IF(V12=1,SUMIF($A$3:$A$1622,A12,$L$3:$L$1622),0) -> 0 | AC12: =IF(I12="",0,L12*IFERROR(INDEX(کاتالوگ_محصولات!$G$4:$G$303,MATCH(I12,کاتالوگ_محصولات!$A$4:$A$303,0)),0)) -> 0 | AD12: =IF(A12="",0,O12-AC12) -> 4250000 | AE12: =IF(B12="","",LEFT(B12,7)) -> 1405/07
A13: INV-0206 | B13: 1405/07/03 | C13: 2 | D13: ماحی حمیدپور | E13: full | F13: کارت | G13: جدید | H13: کانال | J13: کیف سرمه ای 4095 | K13: کیف سرمه ای 4095 | L13: 1 | M13: 2680000 | N13: 0 | O13: 2680000 | P13: نرگس | Q13: رامشک | R13: 9126998490 | S13: 29 | T13: 8 | V13: =IF(A13="",0,IF(COUNTIF($A$3:A13,A13)=1,1,0)) -> 1 | W13: =IF(A13="",0,L13*M13) -> 2680000 | X13: =IF(R13<>"",R13,IF(AND(P13<>"",Q13<>""),P13&"|"&Q13,"")) -> 9126998490 | Y13: =IF(X13="",0,IF(COUNTIF($X$3:X13,X13)=1,1,0)) -> 1 | Z13: =IF(V13<>1,0,IF(X13="",0,IF(COUNTIF($X$3:X12,X13)>0,1,0))) -> 0 | AA13: =IF(V13=1,SUMIF($A$3:$A$1622,A13,$O$3:$O$1622),0) -> 8440000 | AB13: =IF(V13=1,SUMIF($A$3:$A$1622,A13,$L$3:$L$1622),0) -> 3 | AC13: =IF(I13="",0,L13*IFERROR(INDEX(کاتالوگ_محصولات!$G$4:$G$303,MATCH(I13,کاتالوگ_محصولات!$A$4:$A$303,0)),0)) -> 0 | AD13: =IF(A13="",0,O13-AC13) -> 2680000 | AE13: =IF(B13="","",LEFT(B13,7)) -> 1405/07
A14: INV-0206 | B14: 1405/07/03 | C14: 2 | D14: ماحی حمیدپور | E14: full | F14: کارت | G14: جدید | H14: کانال | J14: شومیز دریا صورتی سایز1 | K14: شومیز دریا صورتی سایز1 | L14: 1 | M14: 1980000 | N14: 0 | O14: 1980000 | P14: نرگس | Q14: رامشک | R14: 9126998490 | S14: 29 | T14: 8 | V14: =IF(A14="",0,IF(COUNTIF($A$3:A14,A14)=1,1,0)) -> 0 | W14: =IF(A14="",0,L14*M14) -> 1980000 | X14: =IF(R14<>"",R14,IF(AND(P14<>"",Q14<>""),P14&"|"&Q14,"")) -> 9126998490 | Y14: =IF(X14="",0,IF(COUNTIF($X$3:X14,X14)=1,1,0)) -> 0 | Z14: =IF(V14<>1,0,IF(X14="",0,IF(COUNTIF($X$3:X13,X14)>0,1,0))) -> 0 | AA14: =IF(V14=1,SUMIF($A$3:$A$1622,A14,$O$3:$O$1622),0) -> 0 | AB14: =IF(V14=1,SUMIF($A$3:$A$1622,A14,$L$3:$L$1622),0) -> 0 | AC14: =IF(I14="",0,L14*IFERROR(INDEX(کاتالوگ_محصولات!$G$4:$G$303,MATCH(I14,کاتالوگ_محصولات!$A$4:$A$303,0)),0)) -> 0 | AD14: =IF(A14="",0,O14-AC14) -> 1980000 | AE14: =IF(B14="","",LEFT(B14,7)) -> 1405/07
A15: INV-0206 | B15: 1405/07/03 | C15: 2 | D15: ماحی حمیدپور | E15: full | F15: کارت | G15: جدید | H15: کانال | J15: شلوار بوتکات سرمه ای40 | K15: شلوار بوتکات سرمه ای40 | L15: 1 | M15: 3780000 | N15: 0 | O15: 3780000 | P15: نرگس | Q15: رامشک | R15: 9126998490 | S15: 29 | T15: 8 | V15: =IF(A15="",0,IF(COUNTIF($A$3:A15,A15)=1,1,0)) -> 0 | W15: =IF(A15="",0,L15*M15) -> 3780000 | X15: =IF(R15<>"",R15,IF(AND(P15<>"",Q15<>""),P15&"|"&Q15,"")) -> 9126998490 | Y15: =IF(X15="",0,IF(COUNTIF($X$3:X15,X15)=1,1,0)) -> 0 | Z15: =IF(V15<>1,0,IF(X15="",0,IF(COUNTIF($X$3:X14,X15)>0,1,0))) -> 0 | AA15: =IF(V15=1,SUMIF($A$3:$A$1622,A15,$O$3:$O$1622),0) -> 0 | AB15: =IF(V15=1,SUMIF($A$3:$A$1622,A15,$L$3:$L$1622),0) -> 0 | AC15: =IF(I15="",0,L15*IFERROR(INDEX(کاتالوگ_محصولات!$G$4:$G$303,MATCH(I15,کاتالوگ_محصولات!$A$4:$A$303,0)),0)) -> 0 | AD15: =IF(A15="",0,O15-AC15) -> 3780000 | AE15: =IF(B15="","",LEFT(B15,7)) -> 1405/07
A16: INV-0207 | B16: 1405/07/03 | C16: 2 | D16: ماحی حمیدپور | E16: full | F16: کارت | G16: جدید | H16: کانال | J16: کت سبز | K16: کت سبز | L16: 1 | M16: 1800000 | N16: 0 | O16: 1800000 | Q16: باقری | R16: 9123637907 | S16: 1 | T16: 1344/01 | V16: =IF(A16="",0,IF(COUNTIF($A$3:A16,A16)=1,1,0)) -> 1 | W16: =IF(A16="",0,L16*M16) -> 1800000 | X16: =IF(R16<>"",R16,IF(AND(P16<>"",Q16<>""),P16&"|"&Q16,"")) -> 9123637907 | Y16: =IF(X16="",0,IF(COUNTIF($X$3:X16,X16)=1,1,0)) -> 1 | Z16: =IF(V16<>1,0,IF(X16="",0,IF(COUNTIF($X$3:X15,X16)>0,1,0))) -> 0 | AA16: =IF(V16=1,SUMIF($A$3:$A$1622,A16,$O$3:$O$1622),0) -> 8860000 | AB16: =IF(V16=1,SUMIF($A$3:$A$1622,A16,$L$3:$L$1622),0) -> 3 | AC16: =IF(I16="",0,L16*IFERROR(INDEX(کاتالوگ_محصولات!$G$4:$G$303,MATCH(I16,کاتالوگ_محصولات!$A$4:$A$303,0)),0)) -> 0 | AD16: =IF(A16="",0,O16-AC16) -> 1800000 | AE16: =IF(B16="","",LEFT(B16,7)) -> 1405/07
A17: INV-0207 | B17: 1405/07/03 | C17: 2 | D17: ماحی حمیدپور | E17: full | F17: کارت | G17: جدید | H17: کانال | J17: شلوار بوتکات سرمه ای48 | K17: شلوار بوتکات سرمه ای48 | L17: 1 | M17: 3780000 | N17: 0 | O17: 3780000 | Q17: باقری | R17: 9123637907 | S17: 1 | T17: 1344/01 | V17: =IF(A17="",0,IF(COUNTIF($A$3:A17,A17)=1,1,0)) -> 0 | W17: =IF(A17="",0,L17*M17) -> 3780000 | X17: =IF(R17<>"",R17,IF(AND(P17<>"",Q17<>""),P17&"|"&Q17,"")) -> 9123637907 | Y17: =IF(X17="",0,IF(COUNTIF($X$3:X17,X17)=1,1,0)) -> 0 | Z17: =IF(V17<>1,0,IF(X17="",0,IF(COUNTIF($X$3:X16,X17)>0,1,0))) -> 0 | AA17: =IF(V17=1,SUMIF($A$3:$A$1622,A17,$O$3:$O$1622),0) -> 0 | AB17: =IF(V17=1,SUMIF($A$3:$A$1622,A17,$L$3:$L$1622),0) -> 0 | AC17: =IF(I17="",0,L17*IFERROR(INDEX(کاتالوگ_محصولات!$G$4:$G$303,MATCH(I17,کاتالوگ_محصولات!$A$4:$A$303,0)),0)) -> 0 | AD17: =IF(A17="",0,O17-AC17) -> 3780000 | AE17: =IF(B17="","",LEFT(B17,7)) -> 1405/07
A18: INV-0207 | B18: 1405/07/03 | C18: 2 | D18: ماحی حمیدپور | E18: full | F18: کارت | G18: جدید | H18: کانال | J18: شومیز ساتن چری سرمه ای2 | K18: شومیز ساتن چری سرمه ای2 | L18: 1 | M18: 3280000 | N18: 0 | O18: 3280000 | Q18: باقری | R18: 9123637907 | S18: 1 | T18: 1344/01 | V18: =IF(A18="",0,IF(COUNTIF($A$3:A18,A18)=1,1,0)) -> 0 | W18: =IF(A18="",0,L18*M18) -> 3280000 | X18: =IF(R18<>"",R18,IF(AND(P18<>"",Q18<>""),P18&"|"&Q18,"")) -> 9123637907 | Y18: =IF(X18="",0,IF(COUNTIF($X$3:X18,X18)=1,1,0)) -> 0 | Z18: =IF(V18<>1,0,IF(X18="",0,IF(COUNTIF($X$3:X17,X18)>0,1,0))) -> 0 | AA18: =IF(V18=1,SUMIF($A$3:$A$1622,A18,$O$3:$O$1622),0) -> 0 | AB18: =IF(V18=1,SUMIF($A$3:$A$1622,A18,$L$3:$L$1622),0) -> 0 | AC18: =IF(I18="",0,L18*IFERROR(INDEX(کاتالوگ_محصولات!$G$4:$G$303,MATCH(I18,کاتالوگ_محصولات!$A$4:$A$303,0)),0)) -> 0 | AD18: =IF(A18="",0,O18-AC18) -> 3280000 | AE18: =IF(B18="","",LEFT(B18,7)) -> 1405/07
A19: INV-0208 | B19: 1405/07/03 | C19: 2 | D19: ماحی حمیدپور | E19: full | F19: اسنپ پی | G19: جدید | H19: کانال | J19: کت ژاکارد طوسی | K19: کت ژاکارد طوسی | L19: 1 | M19: 3290000 | N19: 0 | O19: 3290000 | P19: مهران | R19: 9121242431 | S19: 7 | T19: 1 | V19: =IF(A19="",0,IF(COUNTIF($A$3:A19,A19)=1,1,0)) -> 1 | W19: =IF(A19="",0,L19*M19) -> 3290000 | X19: =IF(R19<>"",R19,IF(AND(P19<>"",Q19<>""),P19&"|"&Q19,"")) -> 9121242431 | Y19: =IF(X19="",0,IF(COUNTIF($X$3:X19,X19)=1,1,0)) -> 1 | Z19: =IF(V19<>1,0,IF(X19="",0,IF(COUNTIF($X$3:X18,X19)>0,1,0))) -> 0 | AA19: =IF(V19=1,SUMIF($A$3:$A$1622,A19,$O$3:$O$1622),0) -> 7670000 | AB19: =IF(V19=1,SUMIF($A$3:$A$1622,A19,$L$3:$L$1622),0) -> 3 | AC19: =IF(I19="",0,L19*IFERROR(INDEX(کاتالوگ_محصولات!$G$4:$G$303,MATCH(I19,کاتالوگ_محصولات!$A$4:$A$303,0)),0)) -> 0 | AD19: =IF(A19="",0,O19-AC19) -> 3290000 | AE19: =IF(B19="","",LEFT(B19,7)) -> 1405/07
A20: INV-0208 | B20: 1405/07/03 | C20: 2 | D20: ماحی حمیدپور | E20: full | F20: اسنپ پی | G20: جدید | H20: کانال | J20: وست بیژو آبی نفتی فری | K20: وست بیژو آبی نفتی فری | L20: 1 | M20: 3200000 | N20: 0 | O20: 3200000 | P20: مهران | R20: 9121242431 | S20: 7 | T20: 1 | V20: =IF(A20="",0,IF(COUNTIF($A$3:A20,A20)=1,1,0)) -> 0 | W20: =IF(A20="",0,L20*M20) -> 3200000 | X20: =IF(R20<>"",R20,IF(AND(P20<>"",Q20<>""),P20&"|"&Q20,"")) -> 9121242431 | Y20: =IF(X20="",0,IF(COUNTIF($X$3:X20,X20)=1,1,0)) -> 0 | Z20: =IF(V20<>1,0,IF(X20="",0,IF(COUNTIF($X$3:X19,X20)>0,1,0))) -> 0 | AA20: =IF(V20=1,SUMIF($A$3:$A$1622,A20,$O$3:$O$1622),0) -> 0 | AB20: =IF(V20=1,SUMIF($A$3:$A$1622,A20,$L$3:$L$1622),0) -> 0 | AC20: =IF(I20="",0,L20*IFERROR(INDEX(کاتالوگ_محصولات!$G$4:$G$303,MATCH(I20,کاتالوگ_محصولات!$A$4:$A$303,0)),0)) -> 0 | AD20: =IF(A20="",0,O20-AC20) -> 3200000 | AE20: =IF(B20="","",LEFT(B20,7)) -> 1405/07
A21: INV-0208 | B21: 1405/07/03 | C21: 2 | D21: ماحی حمیدپور | E21: full | F21: اسنپ پی | G21: جدید | H21: کانال | J21: شلوار بیژو آبی نفتی فری | K21: شلوار بیژو آبی نفتی فری | L21: 1 | M21: 1180000 | N21: 0 | O21: 1180000 | P21: مهران | R21: 9121242431 | S21: 7 | T21: 1 | V21: =IF(A21="",0,IF(COUNTIF($A$3:A21,A21)=1,1,0)) -> 0 | W21: =IF(A21="",0,L21*M21) -> 1180000 | X21: =IF(R21<>"",R21,IF(AND(P21<>"",Q21<>""),P21&"|"&Q21,"")) -> 9121242431 | Y21: =IF(X21="",0,IF(COUNTIF($X$3:X21,X21)=1,1,0)) -> 0 | Z21: =IF(V21<>1,0,IF(X21="",0,IF(COUNTIF($X$3:X20,X21)>0,1,0))) -> 0 | AA21: =IF(V21=1,SUMIF($A$3:$A$1622,A21,$O$3:$O$1622),0) -> 0 | AB21: =IF(V21=1,SUMIF($A$3:$A$1622,A21,$L$3:$L$1622),0) -> 0 | AC21: =IF(I21="",0,L21*IFERROR(INDEX(کاتالوگ_محصولات!$G$4:$G$303,MATCH(I21,کاتالوگ_محصولات!$A$4:$A$303,0)),0)) -> 0 | AD21: =IF(A21="",0,O21-AC21) -> 1180000 | AE21: =IF(B21="","",LEFT(B21,7)) -> 1405/07
A22: INV-0209 | B22: 1405/07/03 | C22: 2 | D22: ماحی حمیدپور | E22: full | F22: اسنپ پی | G22: جدید | H22: کانال | J22: بامبر ژکت سبز | K22: بامبر ژکت سبز | L22: 1 | M22: 6780000 | N22: 0 | O22: 6780000 | P22: مهسا | Q22: سعدی | R22: 9918681529 | V22: =IF(A22="",0,IF(COUNTIF($A$3:A22,A22)=1,1,0)) -> 1 | W22: =IF(A22="",0,L22*M22) -> 6780000 | X22: =IF(R22<>"",R22,IF(AND(P22<>"",Q22<>""),P22&"|"&Q22,"")) -> 9918681529 | Y22: =IF(X22="",0,IF(COUNTIF($X$3:X22,X22)=1,1,0)) -> 1 | Z22: =IF(V22<>1,0,IF(X22="",0,IF(COUNTIF($X$3:X21,X22)>0,1,0))) -> 0 | AA22: =IF(V22=1,SUMIF($A$3:$A$1622,A22,$O$3:$O$1622),0) -> 6780000 | AB22: =IF(V22=1,SUMIF($A$3:$A$1622,A22,$L$3:$L$1622),0) -> 1 | AC22: =IF(I22="",0,L22*IFERROR(INDEX(کاتالوگ_محصولات!$G$4:$G$303,MATCH(I22,کاتالوگ_محصولات!$A$4:$A$303,0)),0)) -> 0 | AD22: =IF(A22="",0,O22-AC22) -> 6780000 | AE22: =IF(B22="","",LEFT(B22,7)) -> 1405/07
A23: INV-0210 | B23: 1405/07/03 | C23: 2 | D23: ماحی حمیدپور | E23: full | F23: دیجی پی -کارت | G23: برگشتی | H23: کانال | J23: شلوار ساتن سبز2 | K23: شلوار ساتن سبز2 | L23: 1 | M23: 1540000 | N23: 0 | O23: 1540000 | P23: پریسا | Q23: حبیبی | R23: 9365161629 | S23: 11 | T23: 1378/07 | U23: دیجی پی3/900/000 | V23: =IF(A23="",0,IF(COUNTIF($A$3:A23,A23)=1,1,0)) -> 1 | W23: =IF(A23="",0,L23*M23) -> 1540000 | X23: =IF(R23<>"",R23,IF(AND(P23<>"",Q23<>""),P23&"|"&Q23,"")) -> 9365161629 | Y23: =IF(X23="",0,IF(COUNTIF($X$3:X23,X23)=1,1,0)) -> 1 | Z23: =IF(V23<>1,0,IF(X23="",0,IF(COUNTIF($X$3:X22,X23)>0,1,0))) -> 0 | AA23: =IF(V23=1,SUMIF($A$3:$A$1622,A23,$O$3:$O$1622),0) -> 6280000 | AB23: =IF(V23=1,SUMIF($A$3:$A$1622,A23,$L$3:$L$1622),0) -> 3 | AC23: =IF(I23="",0,L23*IFERROR(INDEX(کاتالوگ_محصولات!$G$4:$G$303,MATCH(I23,کاتالوگ_محصولات!$A$4:$A$303,0)),0)) -> 0 | AD23: =IF(A23="",0,O23-AC23) -> 1540000 | AE23: =IF(B23="","",LEFT(B23,7)) -> 1405/07
A24: INV-0210 | B24: 1405/07/03 | C24: 2 | D24: ماحی حمیدپور | E24: full | F24: دیجی پی -کارت | G24: برگشتی | H24: کانال | J24: شلوار ساتن سفید2 | K24: شلوار ساتن سفید2 | L24: 1 | M24: 1540000 | N24: 0 | O24: 1540000 | P24: پریسا | Q24: حبیبی | R24: 9365161629 | S24: 11 | T24: 1378/07 | V24: =IF(A24="",0,IF(COUNTIF($A$3:A24,A24)=1,1,0)) -> 0 | W24: =IF(A24="",0,L24*M24) -> 1540000 | X24: =IF(R24<>"",R24,IF(AND(P24<>"",Q24<>""),P24&"|"&Q24,"")) -> 9365161629 | Y24: =IF(X24="",0,IF(COUNTIF($X$3:X24,X24)=1,1,0)) -> 0 | Z24: =IF(V24<>1,0,IF(X24="",0,IF(COUNTIF($X$3:X23,X24)>0,1,0))) -> 0 | AA24: =IF(V24=1,SUMIF($A$3:$A$1622,A24,$O$3:$O$1622),0) -> 0 | AB24: =IF(V24=1,SUMIF($A$3:$A$1622,A24,$L$3:$L$1622),0) -> 0 | AC24: =IF(I24="",0,L24*IFERROR(INDEX(کاتالوگ_محصولات!$G$4:$G$303,MATCH(I24,کاتالوگ_محصولات!$A$4:$A$303,0)),0)) -> 0 | AD24: =IF(A24="",0,O24-AC24) -> 1540000 | AE24: =IF(B24="","",LEFT(B24,7)) -> 1405/07
A25: INV-0210 | B25: 1405/07/03 | C25: 2 | D25: ماحی حمیدپور | E25: full | F25: دیجی پی -کارت | G25: برگشتی | H25: کانال | J25: شومیز مانلی سبز زیتونی 2 | K25: شومیز مانلی سبز زیتونی 2 | L25: 1 | M25: 3200000 | N25: 0 | O25: 3200000 | P25: پریسا | Q25: حبیبی | R25: 9365161629 | S25: 11 | T25: 1378/07 | V25: =IF(A25="",0,IF(COUNTIF($A$3:A25,A25)=1,1,0)) -> 0 | W25: =IF(A25="",0,L25*M25) -> 3200000 | X25: =IF(R25<>"",R25,IF(AND(P25<>"",Q25<>""),P25&"|"&Q25,"")) -> 9365161629 | Y25: =IF(X25="",0,IF(COUNTIF($X$3:X25,X25)=1,1,0)) -> 0 | Z25: =IF(V25<>1,0,IF(X25="",0,IF(COUNTIF($X$3:X24,X25)>0,1,0))) -> 0 | AA25: =IF(V25=1,SUMIF($A$3:$A$1622,A25,$O$3:$O$1622),0) -> 0 | AB25: =IF(V25=1,SUMIF($A$3:$A$1622,A25,$L$3:$L$1622),0) -> 0 | AC25: =IF(I25="",0,L25*IFERROR(INDEX(کاتالوگ_محصولات!$G$4:$G$303,MATCH(I25,کاتالوگ_محصولات!$A$4:$A$303,0)),0)) -> 0 | AD25: =IF(A25="",0,O25-AC25) -> 3200000 | AE25: =IF(B25="","",LEFT(B25,7)) -> 1405/07
A26: INV-0211 | B26: 1405/07/03 | C26: 2 | D26: ماحی حمیدپور | E26: full | F26: کارت | G26: جدید | H26: کانال | J26: بامبر ژکت سبز | K26: بامبر ژکت سبز | L26: 1 | M26: 6780000 | N26: 0 | O26: 6780000 | P26: امیر | Q26: شماعی | R26: 909630096 | V26: =IF(A26="",0,IF(COUNTIF($A$3:A26,A26)=1,1,0)) -> 1 | W26: =IF(A26="",0,L26*M26) -> 6780000 | X26: =IF(R26<>"",R26,IF(AND(P26<>"",Q26<>""),P26&"|"&Q26,"")) -> 909630096 | Y26: =IF(X26="",0,IF(COUNTIF($X$3:X26,X26)=1,1,0)) -> 1 | Z26: =IF(V26<>1,0,IF(X26="",0,IF(COUNTIF($X$3:X25,X26)>0,1,0))) -> 0 | AA26: =IF(V26=1,SUMIF($A$3:$A$1622,A26,$O$3:$O$1622),0) -> 6780000 | AB26: =IF(V26=1,SUMIF($A$3:$A$1622,A26,$L$3:$L$1622),0) -> 1 | AC26: =IF(I26="",0,L26*IFERROR(INDEX(کاتالوگ_محصولات!$G$4:$G$303,MATCH(I26,کاتالوگ_محصولات!$A$4:$A$303,0)),0)) -> 0 | AD26: =IF(A26="",0,O26-AC26) -> 6780000 | AE26: =IF(B26="","",LEFT(B26,7)) -> 1405/07
A27: INV-0212 | B27: 1405/07/03 | C27: 1 | D27: دریا کریمی | E27: PM | F27: اسنپ پی | G27: چدید | H27: کانال | J27: وست کرمی سایز 1 | K27: وست کرمی سایز 1 | L27: 1 | M27: 1800000 | N27: 0 | O27: 1800000 | P27: ستایش | Q27: رضازاده | R27: 9120292707 | S27: 22 | T27: 1380/06 | U27: آپ سل 15 میلیونی | V27: =IF(A27="",0,IF(COUNTIF($A$3:A27,A27)=1,1,0)) -> 1 | W27: =IF(A27="",0,L27*M27) -> 1800000 | X27: =IF(R27<>"",R27,IF(AND(P27<>"",Q27<>""),P27&"|"&Q27,"")) -> 9120292707 | Y27: =IF(X27="",0,IF(COUNTIF($X$3:X27,X27)=1,1,0)) -> 1 | Z27: =IF(V27<>1,0,IF(X27="",0,IF(COUNTIF($X$3:X26,X27)>0,1,0))) -> 0 | AA27: =IF(V27=1,SUMIF($A$3:$A$1622,A27,$O$3:$O$1622),0) -> 15190000 | AB27: =IF(V27=1,SUMIF($A$3:$A$1622,A27,$L$3:$L$1622),0) -> 6 | AC27: =IF(I27="",0,L27*IFERROR(INDEX(کاتالوگ_محصولات!$G$4:$G$303,MATCH(I27,کاتالوگ_محصولات!$A$4:$A$303,0)),0)) -> 0 | AD27: =IF(A27="",0,O27-AC27) -> 1800000 | AE27: =IF(B27="","",LEFT(B27,7)) -> 1405/07
A28: INV-0212 | B28: 1405/07/03 | C28: 1 | D28: دریا کریمی | E28: PM | F28: اسنپ پی | G28: چدید | H28: کانال | J28: دامن لیدی مشکی فری | K28: دامن لیدی مشکی فری | L28: 1 | M28: 2950000 | N28: 0 | O28: 2950000 | P28: ستایش | Q28: رضازاده | R28: 9120292707 | S28: 22 | T28: 1380/06 | V28: =IF(A28="",0,IF(COUNTIF($A$3:A28,A28)=1,1,0)) -> 0 | W28: =IF(A28="",0,L28*M28) -> 2950000 | X28: =IF(R28<>"",R28,IF(AND(P28<>"",Q28<>""),P28&"|"&Q28,"")) -> 9120292707 | Y28: =IF(X28="",0,IF(COUNTIF($X$3:X28,X28)=1,1,0)) -> 0 | Z28: =IF(V28<>1,0,IF(X28="",0,IF(COUNTIF($X$3:X27,X28)>0,1,0))) -> 0 | AA28: =IF(V28=1,SUMIF($A$3:$A$1622,A28,$O$3:$O$1622),0) -> 0 | AB28: =IF(V28=1,SUMIF($A$3:$A$1622,A28,$L$3:$L$1622),0) -> 0 | AC28: =IF(I28="",0,L28*IFERROR(INDEX(کاتالوگ_محصولات!$G$4:$G$303,MATCH(I28,کاتالوگ_محصولات!$A$4:$A$303,0)),0)) -> 0 | AD28: =IF(A28="",0,O28-AC28) -> 2950000 | AE28: =IF(B28="","",LEFT(B28,7)) -> 1405/07
A29: INV-0212 | B29: 1405/07/03 | C29: 1 | D29: دریا کریمی | E29: PM | F29: اسنپ پی | G29: چدید | H29: کانال | J29: شومیز مانلی کرم2 | K29: شومیز مانلی کرم2 | L29: 1 | M29: 3200000 | N29: 0 | O29: 3200000 | P29: ستایش | Q29: رضازاده | R29: 9120292707 | S29: 22 | T29: 1380/06 | V29: =IF(A29="",0,IF(COUNTIF($A$3:A29,A29)=1,1,0)) -> 0 | W29: =IF(A29="",0,L29*M29) -> 3200000 | X29: =IF(R29<>"",R29,IF(AND(P29<>"",Q29<>""),P29&"|"&Q29,"")) -> 9120292707 | Y29: =IF(X29="",0,IF(COUNTIF($X$3:X29,X29)=1,1,0)) -> 0 | Z29: =IF(V29<>1,0,IF(X29="",0,IF(COUNTIF($X$3:X28,X29)>0,1,0))) -> 0 | AA29: =IF(V29=1,SUMIF($A$3:$A$1622,A29,$O$3:$O$1622),0) -> 0 | AB29: =IF(V29=1,SUMIF($A$3:$A$1622,A29,$L$3:$L$1622),0) -> 0 | AC29: =IF(I29="",0,L29*IFERROR(INDEX(کاتالوگ_محصولات!$G$4:$G$303,MATCH(I29,کاتالوگ_محصولات!$A$4:$A$303,0)),0)) -> 0 | AD29: =IF(A29="",0,O29-AC29) -> 3200000 | AE29: =IF(B29="","",LEFT(B29,7)) -> 1405/07
A30: INV-0212 | B30: 1405/07/03 | C30: 1 | D30: دریا کریمی | E30: PM | F30: اسنپ پی | G30: چدید | H30: کانال | J30: بافت یقه ایستاده کرم | K30: بافت یقه ایستاده کرم | L30: 1 | M30: 2180000 | N30: 0 | O30: 2180000 | P30: ستایش | Q30: رضازاده | R30: 9120292707 | S30: 22 | T30: 1380/06 | V30: =IF(A30="",0,IF(COUNTIF($A$3:A30,A30)=1,1,0)) -> 0 | W30: =IF(A30="",0,L30*M30) -> 2180000 | X30: =IF(R30<>"",R30,IF(AND(P30<>"",Q30<>""),P30&"|"&Q30,"")) -> 9120292707 | Y30: =IF(X30="",0,IF(COUNTIF($X$3:X30,X30)=1,1,0)) -> 0 | Z30: =IF(V30<>1,0,IF(X30="",0,IF(COUNTIF($X$3:X29,X30)>0,1,0))) -> 0 | AA30: =IF(V30=1,SUMIF($A$3:$A$1622,A30,$O$3:$O$1622),0) -> 0 | AB30: =IF(V30=1,SUMIF($A$3:$A$1622,A30,$L$3:$L$1622),0) -> 0 | AC30: =IF(I30="",0,L30*IFERROR(INDEX(کاتالوگ_محصولات!$G$4:$G$303,MATCH(I30,کاتالوگ_محصولات!$A$4:$A$303,0)),0)) -> 0 | AD30: =IF(A30="",0,O30-AC30) -> 2180000 | AE30: =IF(B30="","",LEFT(B30,7)) -> 1405/07
A31: INV-0212 | B31: 1405/07/03 | C31: 1 | D31: دریا کریمی | E31: PM | F31: اسنپ پی | G31: چدید | H31: کانال | J31: بافت یقه ایستاده مشکی | K31: بافت یقه ایستاده مشکی | L31: 1 | M31: 2180000 | N31: 0 | O31: 2180000 | P31: ستایش | Q31: رضازاده | R31: 9120292707 | S31: 22 | T31: 1380/06 | V31: =IF(A31="",0,IF(COUNTIF($A$3:A31,A31)=1,1,0)) -> 0 | W31: =IF(A31="",0,L31*M31) -> 2180000 | X31: =IF(R31<>"",R31,IF(AND(P31<>"",Q31<>""),P31&"|"&Q31,"")) -> 9120292707 | Y31: =IF(X31="",0,IF(COUNTIF($X$3:X31,X31)=1,1,0)) -> 0 | Z31: =IF(V31<>1,0,IF(X31="",0,IF(COUNTIF($X$3:X30,X31)>0,1,0))) -> 0 | AA31: =IF(V31=1,SUMIF($A$3:$A$1622,A31,$O$3:$O$1622),0) -> 0 | AB31: =IF(V31=1,SUMIF($A$3:$A$1622,A31,$L$3:$L$1622),0) -> 0 | AC31: =IF(I31="",0,L31*IFERROR(INDEX(کاتالوگ_محصولات!$G$4:$G$303,MATCH(I31,کاتالوگ_محصولات!$A$4:$A$303,0)),0)) -> 0 | AD31: =IF(A31="",0,O31-AC31) -> 2180000 | AE31: =IF(B31="","",LEFT(B31,7)) -> 1405/07
A32: INV-0212 | B32: 1405/07/03 | C32: 1 | D32: دریا کریمی | E32: PM | F32: اسنپ پی | G32: چدید | H32: کانال | J32: کیف کرم قهوه ای 4194 | K32: کیف کرم قهوه ای 4194 | L32: 1 | M32: 2880000 | N32: 0 | O32: 2880000 | P32: ستایش | Q32: رضازاده | R32: 9120292707 | S32: 22 | T32: 1380/06 | V32: =IF(A32="",0,IF(COUNTIF($A$3:A32,A32)=1,1,0)) -> 0 | W32: =IF(A32="",0,L32*M32) -> 2880000 | X32: =IF(R32<>"",R32,IF(AND(P32<>"",Q32<>""),P32&"|"&Q32,"")) -> 9120292707 | Y32: =IF(X32="",0,IF(COUNTIF($X$3:X32,X32)=1,1,0)) -> 0 | Z32: =IF(V32<>1,0,IF(X32="",0,IF(COUNTIF($X$3:X31,X32)>0,1,0))) -> 0 | AA32: =IF(V32=1,SUMIF($A$3:$A$1622,A32,$O$3:$O$1622),0) -> 0 | AB32: =IF(V32=1,SUMIF($A$3:$A$1622,A32,$L$3:$L$1622),0) -> 0 | AC32: =IF(I32="",0,L32*IFERROR(INDEX(کاتالوگ_محصولات!$G$4:$G$303,MATCH(I32,کاتالوگ_محصولات!$A$4:$A$303,0)),0)) -> 0 | AD32: =IF(A32="",0,O32-AC32) -> 2880000 | AE32: =IF(B32="","",LEFT(B32,7)) -> 1405/07
A33: INV-0213 | B33: 1405/07/03 | C33: 1 | D33: دریا کریمی | E33: PM | F33: کارت | G33: جدید | H33: کانال | J33: تاپ بند ماکارون | K33: تاپ بند ماکارون | L33: 1 | M33: 928000 | N33: 0 | O33: 928000 | Q33: اعتمادی | R33: 9026666570 | S33: 25 | T33: 1370/11 | V33: =IF(A33="",0,IF(COUNTIF($A$3:A33,A33)=1,1,0)) -> 1 | W33: =IF(A33="",0,L33*M33) -> 928000 | X33: =IF(R33<>"",R33,IF(AND(P33<>"",Q33<>""),P33&"|"&Q33,"")) -> 9026666570 | Y33: =IF(X33="",0,IF(COUNTIF($X$3:X33,X33)=1,1,0)) -> 1 | Z33: =IF(V33<>1,0,IF(X33="",0,IF(COUNTIF($X$3:X32,X33)>0,1,0))) -> 0 | AA33: =IF(V33=1,SUMIF($A$3:$A$1622,A33,$O$3:$O$1622),0) -> 928000 | AB33: =IF(V33=1,SUMIF($A$3:$A$1622,A33,$L$3:$L$1622),0) -> 1 | AC33: =IF(I33="",0,L33*IFERROR(INDEX(کاتالوگ_محصولات!$G$4:$G$303,MATCH(I33,کاتالوگ_محصولات!$A$4:$A$303,0)),0)) -> 0 | AD33: =IF(A33="",0,O33-AC33) -> 928000 | AE33: =IF(B33="","",LEFT(B33,7)) -> 1405/07
A34: INV-0214 | B34: 1405/07/04 | C34: 1 | D34: دریا کریمی | E34: pm | F34: کارت | G34: برگشتی | H34: کانال | J34: شومیز لینن سونای سرمه ای 1 | K34: شومیز لینن سونای سرمه ای 1 | L34: 1 | M34: 3380000 | N34: 0 | O34: 3380000 | P34: شیما | Q34: سعیدی | R34: 9124934558 | S34: 27 | T34: 1 | U34: مشتری برگشتی | V34: =IF(A34="",0,IF(COUNTIF($A$3:A34,A34)=1,1,0)) -> 1 | W34: =IF(A34="",0,L34*M34) -> 3380000 | X34: =IF(R34<>"",R34,IF(AND(P34<>"",Q34<>""),P34&"|"&Q34,"")) -> 9124934558 | Y34: =IF(X34="",0,IF(COUNTIF($X$3:X34,X34)=1,1,0)) -> 1 | Z34: =IF(V34<>1,0,IF(X34="",0,IF(COUNTIF($X$3:X33,X34)>0,1,0))) -> 0 | AA34: =IF(V34=1,SUMIF($A$3:$A$1622,A34,$O$3:$O$1622),0) -> 3380000 | AB34: =IF(V34=1,SUMIF($A$3:$A$1622,A34,$L$3:$L$1622),0) -> 1 | AC34: =IF(I34="",0,L34*IFERROR(INDEX(کاتالوگ_محصولات!$G$4:$G$303,MATCH(I34,کاتالوگ_محصولات!$A$4:$A$303,0)),0)) -> 0 | AD34: =IF(A34="",0,O34-AC34) -> 3380000 | AE34: =IF(B34="","",LEFT(B34,7)) -> 1405/07
A35: INV-0215 | B35: 1405/07/04 | C35: 1 | D35: دریا کریمی | E35: _PM_ | F35: کارت | G35: جدید | H35: کانال | J35: شلوار مانا کله غازی2 | K35: شلوار مانا کله غازی2 | L35: 1 | M35: 1680000 | N35: 0 | O35: 1680000 | P35: خانم | Q35: فرزان پور | R35: 9148931108 | S35: 28 | T35: 6 | V35: =IF(A35="",0,IF(COUNTIF($A$3:A35,A35)=1,1,0)) -> 1 | W35: =IF(A35="",0,L35*M35) -> 1680000 | X35: =IF(R35<>"",R35,IF(AND(P35<>"",Q35<>""),P35&"|"&Q35,"")) -> 9148931108 | Y35: =IF(X35="",0,IF(COUNTIF($X$3:X35,X35)=1,1,0)) -> 1 | Z35: =IF(V35<>1,0,IF(X35="",0,IF(COUNTIF($X$3:X34,X35)>0,1,0))) -> 0 | AA35: =IF(V35=1,SUMIF($A$3:$A$1622,A35,$O$3:$O$1622),0) -> 3000000 | AB35: =IF(V35=1,SUMIF($A$3:$A$1622,A35,$L$3:$L$1622),0) -> 2 | AC35: =IF(I35="",0,L35*IFERROR(INDEX(کاتالوگ_محصولات!$G$4:$G$303,MATCH(I35,کاتالوگ_محصولات!$A$4:$A$303,0)),0)) -> 0 | AD35: =IF(A35="",0,O35-AC35) -> 1680000 | AE35: =IF(B35="","",LEFT(B35,7)) -> 1405/07
A36: INV-0215 | B36: 1405/07/04 | C36: 1 | D36: دریا کریمی | E36: _PM_ | F36: کارت | G36: جدید | H36: کانال | J36: شومیز تایملس سبز فری | K36: شومیز تایملس سبز فری | L36: 1 | M36: 1320000 | N36: 0 | O36: 1320000 | P36: خانم | Q36: فرزان پور | R36: 9148931108 | S36: 28 | T36: 6 | V36: =IF(A36="",0,IF(COUNTIF($A$3:A36,A36)=1,1,0)) -> 0 | W36: =IF(A36="",0,L36*M36) -> 1320000 | X36: =IF(R36<>"",R36,IF(AND(P36<>"",Q36<>""),P36&"|"&Q36,"")) -> 9148931108 | Y36: =IF(X36="",0,IF(COUNTIF($X$3:X36,X36)=1,1,0)) -> 0 | Z36: =IF(V36<>1,0,IF(X36="",0,IF(COUNTIF($X$3:X35,X36)>0,1,0))) -> 0 | AA36: =IF(V36=1,SUMIF($A$3:$A$1622,A36,$O$3:$O$1622),0) -> 0 | AB36: =IF(V36=1,SUMIF($A$3:$A$1622,A36,$L$3:$L$1622),0) -> 0 | AC36: =IF(I36="",0,L36*IFERROR(INDEX(کاتالوگ_محصولات!$G$4:$G$303,MATCH(I36,کاتالوگ_محصولات!$A$4:$A$303,0)),0)) -> 0 | AD36: =IF(A36="",0,O36-AC36) -> 1320000 | AE36: =IF(B36="","",LEFT(B36,7)) -> 1405/07
A37: INV-0216 | B37: 1405/07/04 | C37: 1 | D37: دریا کریمی | E37: _PM_ | F37: کارت | H37: کانال | J37: شومیز حراجی گیپور ابی | K37: شومیز حراجی گیپور ابی | L37: 2 | M37: 1080000 | N37: 0 | O37: 2160000 | V37: =IF(A37="",0,IF(COUNTIF($A$3:A37,A37)=1,1,0)) -> 1 | W37: =IF(A37="",0,L37*M37) -> 2160000 | X37: =IF(R37<>"",R37,IF(AND(P37<>"",Q37<>""),P37&"|"&Q37,"")) | Y37: =IF(X37="",0,IF(COUNTIF($X$3:X37,X37)=1,1,0)) -> 0 | Z37: =IF(V37<>1,0,IF(X37="",0,IF(COUNTIF($X$3:X36,X37)>0,1,0))) -> 0 | AA37: =IF(V37=1,SUMIF($A$3:$A$1622,A37,$O$3:$O$1622),0) -> 2160000 | AB37: =IF(V37=1,SUMIF($A$3:$A$1622,A37,$L$3:$L$1622),0) -> 2 | AC37: =IF(I37="",0,L37*IFERROR(INDEX(کاتالوگ_محصولات!$G$4:$G$303,MATCH(I37,کاتالوگ_محصولات!$A$4:$A$303,0)),0)) -> 0 | AD37: =IF(A37="",0,O37-AC37) -> 2160000 | AE37: =IF(B37="","",LEFT(B37,7)) -> 1405/07
A38: INV-0217 | B38: 1405/07/04 | C38: 1 | D38: دریا کریمی | E38: _PM | F38: کارت | H38: کانال | J38: شومیز زبرا | K38: شومیز زبرا | L38: 1 | M38: 1680000 | N38: 0 | O38: 1680000 | P38: خانم | Q38: عنبری | R38: 9169513733 | S38: 2 | T38: 46031 | V38: =IF(A38="",0,IF(COUNTIF($A$3:A38,A38)=1,1,0)) -> 1 | W38: =IF(A38="",0,L38*M38) -> 1680000 | X38: =IF(R38<>"",R38,IF(AND(P38<>"",Q38<>""),P38&"|"&Q38,"")) -> 9169513733 | Y38: =IF(X38="",0,IF(COUNTIF($X$3:X38,X38)=1,1,0)) -> 1 | Z38: =IF(V38<>1,0,IF(X38="",0,IF(COUNTIF($X$3:X37,X38)>0,1,0))) -> 0 | AA38: =IF(V38=1,SUMIF($A$3:$A$1622,A38,$O$3:$O$1622),0) -> 1680000 | AB38: =IF(V38=1,SUMIF($A$3:$A$1622,A38,$L$3:$L$1622),0) -> 1 | AC38: =IF(I38="",0,L38*IFERROR(INDEX(کاتالوگ_محصولات!$G$4:$G$303,MATCH(I38,کاتالوگ_محصولات!$A$4:$A$303,0)),0)) -> 0 | AD38: =IF(A38="",0,O38-AC38) -> 1680000 | AE38: =IF(B38="","",LEFT(B38,7)) -> 1405/07
A39: INV-0218 | B39: 1405/07/04 | C39: 2 | D39: ماحی حمیدپور | F39: 5اسنپ1400پوز 2770کارت ب کارت | H39: کانال | J39: شومیز لیو سفید سایز1 | K39: شومیز لیو سفید سایز1 | L39: 1 | M39: 2630000 | N39: 0 | O39: 2630000 | P39: خانم | Q39: باقری | R39: 9932692491 | S39: 5 | T39: 8 | U39: ادامه فاکتور 161 | V39: =IF(A39="",0,IF(COUNTIF($A$3:A39,A39)=1,1,0)) -> 1 | W39: =IF(A39="",0,L39*M39) -> 2630000 | X39: =IF(R39<>"",R39,IF(AND(P39<>"",Q39<>""),P39&"|"&Q39,"")) -> 9932692491 | Y39: =IF(X39="",0,IF(COUNTIF($X$3:X39,X39)=1,1,0)) -> 1 | Z39: =IF(V39<>1,0,IF(X39="",0,IF(COUNTIF($X$3:X38,X39)>0,1,0))) -> 0 | AA39: =IF(V39=1,SUMIF($A$3:$A$1622,A39,$O$3:$O$1622),0) -> 4170000 | AB39: =IF(V39=1,SUMIF($A$3:$A$1622,A39,$L$3:$L$1622),0) -> 2 | AC39: =IF(I39="",0,L39*IFERROR(INDEX(کاتالوگ_محصولات!$G$4:$G$303,MATCH(I39,کاتالوگ_محصولات!$A$4:$A$303,0)),0)) -> 0 | AD39: =IF(A39="",0,O39-AC39) -> 2630000 | AE39: =IF(B39="","",LEFT(B39,7)) -> 1405/07
A40: INV-0218 | B40: 1405/07/04 | C40: 2 | D40: ماحی حمیدپور | F40: 5اسنپ1400پوز 2770کارت ب کارت | H40: کانال | J40: شلوار ساتن سبز2 | K40: شلوار ساتن سبز2 | L40: 1 | M40: 1540000 | N40: 0 | O40: 1540000 | P40: خانم | Q40: باقری | R40: 9932692491 | S40: 5 | T40: 8 | V40: =IF(A40="",0,IF(COUNTIF($A$3:A40,A40)=1,1,0)) -> 0 | W40: =IF(A40="",0,L40*M40) -> 1540000 | X40: =IF(R40<>"",R40,IF(AND(P40<>"",Q40<>""),P40&"|"&Q40,"")) -> 9932692491 | Y40: =IF(X40="",0,IF(COUNTIF($X$3:X40,X40)=1,1,0)) -> 0 | Z40: =IF(V40<>1,0,IF(X40="",0,IF(COUNTIF($X$3:X39,X40)>0,1,0))) -> 0 | AA40: =IF(V40=1,SUMIF($A$3:$A$1622,A40,$O$3:$O$1622),0) -> 0 | AB40: =IF(V40=1,SUMIF($A$3:$A$1622,A40,$L$3:$L$1622),0) -> 0 | AC40: =IF(I40="",0,L40*IFERROR(INDEX(کاتالوگ_محصولات!$G$4:$G$303,MATCH(I40,کاتالوگ_محصولات!$A$4:$A$303,0)),0)) -> 0 | AD40: =IF(A40="",0,O40-AC40) -> 1540000 | AE40: =IF(B40="","",LEFT(B40,7)) -> 1405/07
A41: INV-0219 | B41: 1405/07/04 | C41: 1 | D41: دریا کریمی | E41: _PM_ | F41: کارت | G41: جدید | H41: کانال | J41: کیف سفید 2669 | K41: کیف سفید 2669 | L41: 1 | M41: 2880000 | N41: 0 | O41: 2880000 | P41: خانم | Q41: رحیم زاده | R41: 9902242621 | S41: 25 | T41: 4 | V41: =IF(A41="",0,IF(COUNTIF($A$3:A41,A41)=1,1,0)) -> 1 | W41: =IF(A41="",0,L41*M41) -> 2880000 | X41: =IF(R41<>"",R41,IF(AND(P41<>"",Q41<>""),P41&"|"&Q41,"")) -> 9902242621 | Y41: =IF(X41="",0,IF(COUNTIF($X$3:X41,X41)=1,1,0)) -> 1 | Z41: =IF(V41<>1,0,IF(X41="",0,IF(COUNTIF($X$3:X40,X41)>0,1,0))) -> 0 | AA41: =IF(V41=1,SUMIF($A$3:$A$1622,A41,$O$3:$O$1622),0) -> 2880000 | AB41: =IF(V41=1,SUMIF($A$3:$A$1622,A41,$L$3:$L$1622),0) -> 1 | AC41: =IF(I41="",0,L41*IFERROR(INDEX(کاتالوگ_محصولات!$G$4:$G$303,MATCH(I41,کاتالوگ_محصولات!$A$4:$A$303,0)),0)) -> 0 | AD41: =IF(A41="",0,O41-AC41) -> 2880000 | AE41: =IF(B41="","",LEFT(B41,7)) -> 1405/07
A42: INV-0220 | B42: 1405/07/04 | C42: 1 | D42: دریا کریمی | E42: pm | F42: کارت | H42: کانال | J42: کیف 2792 کرم | K42: کیف 2792 کرم | L42: 1 | M42: 2880000 | N42: 0 | O42: 2880000 | V42: =IF(A42="",0,IF(COUNTIF($A$3:A42,A42)=1,1,0)) -> 1 | W42: =IF(A42="",0,L42*M42) -> 2880000 | X42: =IF(R42<>"",R42,IF(AND(P42<>"",Q42<>""),P42&"|"&Q42,"")) | Y42: =IF(X42="",0,IF(COUNTIF($X$3:X42,X42)=1,1,0)) -> 0 | Z42: =IF(V42<>1,0,IF(X42="",0,IF(COUNTIF($X$3:X41,X42)>0,1,0))) -> 0 | AA42: =IF(V42=1,SUMIF($A$3:$A$1622,A42,$O$3:$O$1622),0) -> 5760000 | AB42: =IF(V42=1,SUMIF($A$3:$A$1622,A42,$L$3:$L$1622),0) -> 2 | AC42: =IF(I42="",0,L42*IFERROR(INDEX(کاتالوگ_محصولات!$G$4:$G$303,MATCH(I42,کاتالوگ_محصولات!$A$4:$A$303,0)),0)) -> 0 | AD42: =IF(A42="",0,O42-AC42) -> 2880000 | AE42: =IF(B42="","",LEFT(B42,7)) -> 1405/07
A43: INV-0220 | B43: 1405/07/04 | C43: 1 | D43: دریا کریمی | E43: pm | F43: کارت | H43: کانال | J43: کیف 2792 قهوه ای | K43: کیف 2792 قهوه ای | L43: 1 | M43: 2880000 | N43: 0 | O43: 2880000 | V43: =IF(A43="",0,IF(COUNTIF($A$3:A43,A43)=1,1,0)) -> 0 | W43: =IF(A43="",0,L43*M43) -> 2880000 | X43: =IF(R43<>"",R43,IF(AND(P43<>"",Q43<>""),P43&"|"&Q43,"")) | Y43: =IF(X43="",0,IF(COUNTIF($X$3:X43,X43)=1,1,0)) -> 0 | Z43: =IF(V43<>1,0,IF(X43="",0,IF(COUNTIF($X$3:X42,X43)>0,1,0))) -> 0 | AA43: =IF(V43=1,SUMIF($A$3:$A$1622,A43,$O$3:$O$1622),0) -> 0 | AB43: =IF(V43=1,SUMIF($A$3:$A$1622,A43,$L$3:$L$1622),0) -> 0 | AC43: =IF(I43="",0,L43*IFERROR(INDEX(کاتالوگ_محصولات!$G$4:$G$303,MATCH(I43,کاتالوگ_محصولات!$A$4:$A$303,0)),0)) -> 0 | AD43: =IF(A43="",0,O43-AC43) -> 2880000 | AE43: =IF(B43="","",LEFT(B43,7)) -> 1405/07
A44: INV-0221 | B44: 1405/07/05 | C44: 1 | D44: دریا کریمی | E44: pm | F44: کارت | G44: جدید | H44: کانال | J44: لوفر قهوه ای 38 | K44: لوفر قهوه ای 38 | L44: 1 | M44: 3780000 | N44: 0 | O44: 3780000 | P44: خانم | Q44: عبدللهی | R44: 9126041731 | S44: 31 | T44: 6 | V44: =IF(A44="",0,IF(COUNTIF($A$3:A44,A44)=1,1,0)) -> 1 | W44: =IF(A44="",0,L44*M44) -> 3780000 | X44: =IF(R44<>"",R44,IF(AND(P44<>"",Q44<>""),P44&"|"&Q44,"")) -> 9126041731 | Y44: =IF(X44="",0,IF(COUNTIF($X$3:X44,X44)=1,1,0)) -> 1 | Z44: =IF(V44<>1,0,IF(X44="",0,IF(COUNTIF($X$3:X43,X44)>0,1,0))) -> 0 | AA44: =IF(V44=1,SUMIF($A$3:$A$1622,A44,$O$3:$O$1622),0) -> 3780000 | AB44: =IF(V44=1,SUMIF($A$3:$A$1622,A44,$L$3:$L$1622),0) -> 1 | AC44: =IF(I44="",0,L44*IFERROR(INDEX(کاتالوگ_محصولات!$G$4:$G$303,MATCH(I44,کاتالوگ_محصولات!$A$4:$A$303,0)),0)) -> 0 | AD44: =IF(A44="",0,O44-AC44) -> 3780000 | AE44: =IF(B44="","",LEFT(B44,7)) -> 1405/07
A45: INV-0222 | B45: 1405/07/05 | C45: 1 | D45: دریا کریمی | E45: pm | F45: کارت | G45: جدید | H45: کانال | J45: کیف 2792 | K45: کیف 2792 | L45: 1 | M45: 2800000 | N45: 0 | O45: 2800000 | Q45: نوروزیان | R45: 9122774607 | S45: 16 | T45: 1 | U45: اپ سل 10 میلیونی | V45: =IF(A45="",0,IF(COUNTIF($A$3:A45,A45)=1,1,0)) -> 1 | W45: =IF(A45="",0,L45*M45) -> 2800000 | X45: =IF(R45<>"",R45,IF(AND(P45<>"",Q45<>""),P45&"|"&Q45,"")) -> 9122774607 | Y45: =IF(X45="",0,IF(COUNTIF($X$3:X45,X45)=1,1,0)) -> 1 | Z45: =IF(V45<>1,0,IF(X45="",0,IF(COUNTIF($X$3:X44,X45)>0,1,0))) -> 0 | AA45: =IF(V45=1,SUMIF($A$3:$A$1622,A45,$O$3:$O$1622),0) -> 14460000 | AB45: =IF(V45=1,SUMIF($A$3:$A$1622,A45,$L$3:$L$1622),0) -> 3 | AC45: =IF(I45="",0,L45*IFERROR(INDEX(کاتالوگ_محصولات!$G$4:$G$303,MATCH(I45,کاتالوگ_محصولات!$A$4:$A$303,0)),0)) -> 0 | AD45: =IF(A45="",0,O45-AC45) -> 2800000 | AE45: =IF(B45="","",LEFT(B45,7)) -> 1405/07
A46: INV-0222 | B46: 1405/07/05 | C46: 1 | D46: دریا کریمی | E46: pm | F46: کارت | G46: جدید | H46: کانال | J46: صندل 40 مشکی | K46: صندل 40 مشکی | L46: 1 | M46: 2880000 | N46: 0 | O46: 2880000 | Q46: نوروزیان | R46: 9122774607 | S46: 16 | T46: 1 | V46: =IF(A46="",0,IF(COUNTIF($A$3:A46,A46)=1,1,0)) -> 0 | W46: =IF(A46="",0,L46*M46) -> 2880000 | X46: =IF(R46<>"",R46,IF(AND(P46<>"",Q46<>""),P46&"|"&Q46,"")) -> 9122774607 | Y46: =IF(X46="",0,IF(COUNTIF($X$3:X46,X46)=1,1,0)) -> 0 | Z46: =IF(V46<>1,0,IF(X46="",0,IF(COUNTIF($X$3:X45,X46)>0,1,0))) -> 0 | AA46: =IF(V46=1,SUMIF($A$3:$A$1622,A46,$O$3:$O$1622),0) -> 0 | AB46: =IF(V46=1,SUMIF($A$3:$A$1622,A46,$L$3:$L$1622),0) -> 0 | AC46: =IF(I46="",0,L46*IFERROR(INDEX(کاتالوگ_محصولات!$G$4:$G$303,MATCH(I46,کاتالوگ_محصولات!$A$4:$A$303,0)),0)) -> 0 | AD46: =IF(A46="",0,O46-AC46) -> 2880000 | AE46: =IF(B46="","",LEFT(B46,7)) -> 1405/07
A47: INV-0222 | B47: 1405/07/05 | C47: 1 | D47: دریا کریمی | E47: pm | F47: کارت | G47: جدید | H47: کانال | J47: بارونی ماهور سرمه ای2 | K47: بارونی ماهور سرمه ای2 | L47: 1 | M47: 8780000 | N47: 0 | O47: 8780000 | Q47: نوروزیان | R47: 9122774607 | S47: 16 | T47: 1 | V47: =IF(A47="",0,IF(COUNTIF($A$3:A47,A47)=1,1,0)) -> 0 | W47: =IF(A47="",0,L47*M47) -> 8780000 | X47: =IF(R47<>"",R47,IF(AND(P47<>"",Q47<>""),P47&"|"&Q47,"")) -> 9122774607 | Y47: =IF(X47="",0,IF(COUNTIF($X$3:X47,X47)=1,1,0)) -> 0 | Z47: =IF(V47<>1,0,IF(X47="",0,IF(COUNTIF($X$3:X46,X47)>0,1,0))) -> 0 | AA47: =IF(V47=1,SUMIF($A$3:$A$1622,A47,$O$3:$O$1622),0) -> 0 | AB47: =IF(V47=1,SUMIF($A$3:$A$1622,A47,$L$3:$L$1622),0) -> 0 | AC47: =IF(I47="",0,L47*IFERROR(INDEX(کاتالوگ_محصولات!$G$4:$G$303,MATCH(I47,کاتالوگ_محصولات!$A$4:$A$303,0)),0)) -> 0 | AD47: =IF(A47="",0,O47-AC47) -> 8780000 | AE47: =IF(B47="","",LEFT(B47,7)) -> 1405/07
A48: INV-0223 | B48: 1405/07/06 | C48: 0 | D48: فروشگاه | E48: full | F48: اسنپ پی | G48: جدید | H48: کانال | J48: شلوار کاترین مشکی 2 | K48: شلوار کاترین مشکی 2 | L48: 1 | M48: 4580000 | N48: 0 | O48: 4580000 | P48: نرگس | Q48: حق مرادی | R48: 9129301401 | S48: 8 | T48: 1369/08 | V48: =IF(A48="",0,IF(COUNTIF($A$3:A48,A48)=1,1,0)) -> 1 | W48: =IF(A48="",0,L48*M48) -> 4580000 | X48: =IF(R48<>"",R48,IF(AND(P48<>"",Q48<>""),P48&"|"&Q48,"")) -> 9129301401 | Y48: =IF(X48="",0,IF(COUNTIF($X$3:X48,X48)=1,1,0)) -> 1 | Z48: =IF(V48<>1,0,IF(X48="",0,IF(COUNTIF($X$3:X47,X48)>0,1,0))) -> 0 | AA48: =IF(V48=1,SUMIF($A$3:$A$1622,A48,$O$3:$O$1622),0) -> 4580000 | AB48: =IF(V48=1,SUMIF($A$3:$A$1622,A48,$L$3:$L$1622),0) -> 1 | AC48: =IF(I48="",0,L48*IFERROR(INDEX(کاتالوگ_محصولات!$G$4:$G$303,MATCH(I48,کاتالوگ_محصولات!$A$4:$A$303,0)),0)) -> 0 | AD48: =IF(A48="",0,O48-AC48) -> 4580000 | AE48: =IF(B48="","",LEFT(B48,7)) -> 1405/07
A49: INV-0224 | B49: 1405/07/06 | C49: 2 | D49: ماحی حمیدپور | E49: PM | F49: کارت | G49: جدید | H49: کانال | J49: کت یقه عروسکی قهوه ای سایز 2 | K49: کت یقه عروسکی قهوه ای سایز 2 | L49: 1 | M49: 6880000 | N49: 0 | O49: 6880000 | V49: =IF(A49="",0,IF(COUNTIF($A$3:A49,A49)=1,1,0)) -> 1 | W49: =IF(A49="",0,L49*M49) -> 6880000 | X49: =IF(R49<>"",R49,IF(AND(P49<>"",Q49<>""),P49&"|"&Q49,"")) | Y49: =IF(X49="",0,IF(COUNTIF($X$3:X49,X49)=1,1,0)) -> 0 | Z49: =IF(V49<>1,0,IF(X49="",0,IF(COUNTIF($X$3:X48,X49)>0,1,0))) -> 0 | AA49: =IF(V49=1,SUMIF($A$3:$A$1622,A49,$O$3:$O$1622),0) -> 6880000 | AB49: =IF(V49=1,SUMIF($A$3:$A$1622,A49,$L$3:$L$1622),0) -> 1 | AC49: =IF(I49="",0,L49*IFERROR(INDEX(کاتالوگ_محصولات!$G$4:$G$303,MATCH(I49,کاتالوگ_محصولات!$A$4:$A$303,0)),0)) -> 0 | AD49: =IF(A49="",0,O49-AC49) -> 6880000 | AE49: =IF(B49="","",LEFT(B49,7)) -> 1405/07
A50: INV-0225 | B50: 1405/07/06 | C50: 2 | D50: ماحی حمیدپور | E50: PM | F50: کارت | G50: جدید | H50: کانال | J50: کت یقه عروسکی سبز سایز 1 | K50: کت یقه عروسکی سبز سایز 1 | L50: 1 | M50: 6880000 | N50: 0 | O50: 6880000 | P50: پوریا | Q50: زنجانی | R50: 9129400456 | S50: 5 | T50: 12 | U50: اپ سل 20 میلیونی | V50: =IF(A50="",0,IF(COUNTIF($A$3:A50,A50)=1,1,0)) -> 1 | W50: =IF(A50="",0,L50*M50) -> 6880000 | X50: =IF(R50<>"",R50,IF(AND(P50<>"",Q50<>""),P50&"|"&Q50,"")) -> 9129400456 | Y50: =IF(X50="",0,IF(COUNTIF($X$3:X50,X50)=1,1,0)) -> 1 | Z50: =IF(V50<>1,0,IF(X50="",0,IF(COUNTIF($X$3:X49,X50)>0,1,0))) -> 0 | AA50: =IF(V50=1,SUMIF($A$3:$A$1622,A50,$O$3:$O$1622),0) -> 19620000 | AB50: =IF(V50=1,SUMIF($A$3:$A$1622,A50,$L$3:$L$1622),0) -> 4 | AC50: =IF(I50="",0,L50*IFERROR(INDEX(کاتالوگ_محصولات!$G$4:$G$303,MATCH(I50,کاتالوگ_محصولات!$A$4:$A$303,0)),0)) -> 0 | AD50: =IF(A50="",0,O50-AC50) -> 6880000 | AE50: =IF(B50="","",LEFT(B50,7)) -> 1405/07
A51: INV-0225 | B51: 1405/07/06 | C51: 2 | D51: ماحی حمیدپور | E51: PM | F51: کارت | G51: جدید | H51: کانال | J51: بامبر ژکت سرمه ای | K51: بامبر ژکت سرمه ای | L51: 1 | M51: 6780000 | N51: 0 | O51: 6780000 | P51: پوریا | Q51: زنجانی | R51: 9129400456 | S51: 5 | T51: 12 | V51: =IF(A51="",0,IF(COUNTIF($A$3:A51,A51)=1,1,0)) -> 0 | W51: =IF(A51="",0,L51*M51) -> 6780000 | X51: =IF(R51<>"",R51,IF(AND(P51<>"",Q51<>""),P51&"|"&Q51,"")) -> 9129400456 | Y51: =IF(X51="",0,IF(COUNTIF($X$3:X51,X51)=1,1,0)) -> 0 | Z51: =IF(V51<>1,0,IF(X51="",0,IF(COUNTIF($X$3:X50,X51)>0,1,0))) -> 0 | AA51: =IF(V51=1,SUMIF($A$3:$A$1622,A51,$O$3:$O$1622),0) -> 0 | AB51: =IF(V51=1,SUMIF($A$3:$A$1622,A51,$L$3:$L$1622),0) -> 0 | AC51: =IF(I51="",0,L51*IFERROR(INDEX(کاتالوگ_محصولات!$G$4:$G$303,MATCH(I51,کاتالوگ_محصولات!$A$4:$A$303,0)),0)) -> 0 | AD51: =IF(A51="",0,O51-AC51) -> 6780000 | AE51: =IF(B51="","",LEFT(B51,7)) -> 1405/07
A52: INV-0225 | B52: 1405/07/06 | C52: 2 | D52: ماحی حمیدپور | E52: PM | F52: کارت | G52: جدید | H52: کانال | J52: شلوار تافی قهوه ای | K52: شلوار تافی قهوه ای | L52: 1 | M52: 3580000 | N52: 0 | O52: 3580000 | P52: پوریا | Q52: زنجانی | R52: 9129400456 | S52: 5 | T52: 12 | V52: =IF(A52="",0,IF(COUNTIF($A$3:A52,A52)=1,1,0)) -> 0 | W52: =IF(A52="",0,L52*M52) -> 3580000 | X52: =IF(R52<>"",R52,IF(AND(P52<>"",Q52<>""),P52&"|"&Q52,"")) -> 9129400456 | Y52: =IF(X52="",0,IF(COUNTIF($X$3:X52,X52)=1,1,0)) -> 0 | Z52: =IF(V52<>1,0,IF(X52="",0,IF(COUNTIF($X$3:X51,X52)>0,1,0))) -> 0 | AA52: =IF(V52=1,SUMIF($A$3:$A$1622,A52,$O$3:$O$1622),0) -> 0 | AB52: =IF(V52=1,SUMIF($A$3:$A$1622,A52,$L$3:$L$1622),0) -> 0 | AC52: =IF(I52="",0,L52*IFERROR(INDEX(کاتالوگ_محصولات!$G$4:$G$303,MATCH(I52,کاتالوگ_محصولات!$A$4:$A$303,0)),0)) -> 0 | AD52: =IF(A52="",0,O52-AC52) -> 3580000 | AE52: =IF(B52="","",LEFT(B52,7)) -> 1405/07
A53: INV-0225 | B53: 1405/07/06 | C53: 2 | D53: ماحی حمیدپور | E53: PM | F53: کارت | G53: جدید | H53: کانال | J53: شلوار بیسیک سفید 1 | K53: شلوار بیسیک سفید 1 | L53: 1 | M53: 2380000 | N53: 0 | O53: 2380000 | P53: پوریا | Q53: زنجانی | R53: 9129400456 | S53: 5 | T53: 12 | V53: =IF(A53="",0,IF(COUNTIF($A$3:A53,A53)=1,1,0)) -> 0 | W53: =IF(A53="",0,L53*M53) -> 2380000 | X53: =IF(R53<>"",R53,IF(AND(P53<>"",Q53<>""),P53&"|"&Q53,"")) -> 9129400456 | Y53: =IF(X53="",0,IF(COUNTIF($X$3:X53,X53)=1,1,0)) -> 0 | Z53: =IF(V53<>1,0,IF(X53="",0,IF(COUNTIF($X$3:X52,X53)>0,1,0))) -> 0 | AA53: =IF(V53=1,SUMIF($A$3:$A$1622,A53,$O$3:$O$1622),0) -> 0 | AB53: =IF(V53=1,SUMIF($A$3:$A$1622,A53,$L$3:$L$1622),0) -> 0 | AC53: =IF(I53="",0,L53*IFERROR(INDEX(کاتالوگ_محصولات!$G$4:$G$303,MATCH(I53,کاتالوگ_محصولات!$A$4:$A$303,0)),0)) -> 0 | AD53: =IF(A53="",0,O53-AC53) -> 2380000 | AE53: =IF(B53="","",LEFT(B53,7)) -> 1405/07
A54: INV-0226 | B54: 1405/07/07 | C54: 0 | D54: فروشگاه | E54: full | F54: کارت | G54: جدید | H54: کانال | J54: کت شنل | K54: کت شنل | L54: 1 | M54: 4250000 | N54: 0 | O54: 4250000 | P54: مریم | Q54: دستوری | R54: 9126713501 | S54: 9 | T54: 1377/05 | V54: =IF(A54="",0,IF(COUNTIF($A$3:A54,A54)=1,1,0)) -> 1 | W54: =IF(A54="",0,L54*M54) -> 4250000 | X54: =IF(R54<>"",R54,IF(AND(P54<>"",Q54<>""),P54&"|"&Q54,"")) -> 9126713501 | Y54: =IF(X54="",0,IF(COUNTIF($X$3:X54,X54)=1,1,0)) -> 1 | Z54: =IF(V54<>1,0,IF(X54="",0,IF(COUNTIF($X$3:X53,X54)>0,1,0))) -> 0 | AA54: =IF(V54=1,SUMIF($A$3:$A$1622,A54,$O$3:$O$1622),0) -> 6900000 | AB54: =IF(V54=1,SUMIF($A$3:$A$1622,A54,$L$3:$L$1622),0) -> 2 | AC54: =IF(I54="",0,L54*IFERROR(INDEX(کاتالوگ_محصولات!$G$4:$G$303,MATCH(I54,کاتالوگ_محصولات!$A$4:$A$303,0)),0)) -> 0 | AD54: =IF(A54="",0,O54-AC54) -> 4250000 | AE54: =IF(B54="","",LEFT(B54,7)) -> 1405/07
A55: INV-0226 | B55: 1405/07/07 | C55: 0 | D55: فروشگاه | E55: full | F55: کارت | G55: جدید | H55: کانال | J55: کت بیژو مشکی فری | K55: کت بیژو مشکی فری | L55: 1 | M55: 2650000 | N55: 0 | O55: 2650000 | P55: مریم | Q55: دستوری | R55: 9126713501 | S55: 9 | T55: 1377/05 | V55: =IF(A55="",0,IF(COUNTIF($A$3:A55,A55)=1,1,0)) -> 0 | W55: =IF(A55="",0,L55*M55) -> 2650000 | X55: =IF(R55<>"",R55,IF(AND(P55<>"",Q55<>""),P55&"|"&Q55,"")) -> 9126713501 | Y55: =IF(X55="",0,IF(COUNTIF($X$3:X55,X55)=1,1,0)) -> 0 | Z55: =IF(V55<>1,0,IF(X55="",0,IF(COUNTIF($X$3:X54,X55)>0,1,0))) -> 0 | AA55: =IF(V55=1,SUMIF($A$3:$A$1622,A55,$O$3:$O$1622),0) -> 0 | AB55: =IF(V55=1,SUMIF($A$3:$A$1622,A55,$L$3:$L$1622),0) -> 0 | AC55: =IF(I55="",0,L55*IFERROR(INDEX(کاتالوگ_محصولات!$G$4:$G$303,MATCH(I55,کاتالوگ_محصولات!$A$4:$A$303,0)),0)) -> 0 | AD55: =IF(A55="",0,O55-AC55) -> 2650000 | AE55: =IF(B55="","",LEFT(B55,7)) -> 1405/07
A56: INV-0227 | B56: 1405/07/07 | C56: 1 | D56: دریا کریمی | E56: pm | F56: کارت | G56: جدید | H56: کانال | J56: کت دیپلمات سرمه ای سایز 2 | K56: کت دیپلمات سرمه ای سایز 2 | L56: 1 | M56: 2580000 | N56: 0 | O56: 2580000 | V56: =IF(A56="",0,IF(COUNTIF($A$3:A56,A56)=1,1,0)) -> 1 | W56: =IF(A56="",0,L56*M56) -> 2580000 | X56: =IF(R56<>"",R56,IF(AND(P56<>"",Q56<>""),P56&"|"&Q56,"")) | Y56: =IF(X56="",0,IF(COUNTIF($X$3:X56,X56)=1,1,0)) -> 0 | Z56: =IF(V56<>1,0,IF(X56="",0,IF(COUNTIF($X$3:X55,X56)>0,1,0))) -> 0 | AA56: =IF(V56=1,SUMIF($A$3:$A$1622,A56,$O$3:$O$1622),0) -> 2580000 | AB56: =IF(V56=1,SUMIF($A$3:$A$1622,A56,$L$3:$L$1622),0) -> 1 | AC56: =IF(I56="",0,L56*IFERROR(INDEX(کاتالوگ_محصولات!$G$4:$G$303,MATCH(I56,کاتالوگ_محصولات!$A$4:$A$303,0)),0)) -> 0 | AD56: =IF(A56="",0,O56-AC56) -> 2580000 | AE56: =IF(B56="","",LEFT(B56,7)) -> 1405/07
A57: INV-0228 | B57: 1405/07/07 | C57: 1 | D57: دریا کریمی | E57: PM | F57: نقد | G57: چدید | H57: کانال | J57: کیف 2792 قهوه ای | K57: کیف 2792 قهوه ای | L57: 1 | M57: 2880000 | N57: 0 | O57: 2880000 | V57: =IF(A57="",0,IF(COUNTIF($A$3:A57,A57)=1,1,0)) -> 1 | W57: =IF(A57="",0,L57*M57) -> 2880000 | X57: =IF(R57<>"",R57,IF(AND(P57<>"",Q57<>""),P57&"|"&Q57,"")) | Y57: =IF(X57="",0,IF(COUNTIF($X$3:X57,X57)=1,1,0)) -> 0 | Z57: =IF(V57<>1,0,IF(X57="",0,IF(COUNTIF($X$3:X56,X57)>0,1,0))) -> 0 | AA57: =IF(V57=1,SUMIF($A$3:$A$1622,A57,$O$3:$O$1622),0) -> 2880000 | AB57: =IF(V57=1,SUMIF($A$3:$A$1622,A57,$L$3:$L$1622),0) -> 1 | AC57: =IF(I57="",0,L57*IFERROR(INDEX(کاتالوگ_محصولات!$G$4:$G$303,MATCH(I57,کاتالوگ_محصولات!$A$4:$A$303,0)),0)) -> 0 | AD57: =IF(A57="",0,O57-AC57) -> 2880000 | AE57: =IF(B57="","",LEFT(B57,7)) -> 1405/07
A58: INV-0229 | B58: 1405/07/08 | C58: 2 | D58: ماحی حمیدپور | E58: pm | F58: اسنپ پی | G58: جدید | H58: کانال | J58: شومیز ساتن بسیک کرمه | K58: شومیز ساتن بسیک کرمه | L58: 1 | M58: 2380000 | N58: 0 | O58: 2380000 | P58: فرهناز | Q58: شکری | R58: 9121599540 | V58: =IF(A58="",0,IF(COUNTIF($A$3:A58,A58)=1,1,0)) -> 1 | W58: =IF(A58="",0,L58*M58) -> 2380000 | X58: =IF(R58<>"",R58,IF(AND(P58<>"",Q58<>""),P58&"|"&Q58,"")) -> 9121599540 | Y58: =IF(X58="",0,IF(COUNTIF($X$3:X58,X58)=1,1,0)) -> 1 | Z58: =IF(V58<>1,0,IF(X58="",0,IF(COUNTIF($X$3:X57,X58)>0,1,0))) -> 0 | AA58: =IF(V58=1,SUMIF($A$3:$A$1622,A58,$O$3:$O$1622),0) -> 5060000 | AB58: =IF(V58=1,SUMIF($A$3:$A$1622,A58,$L$3:$L$1622),0) -> 2 | AC58: =IF(I58="",0,L58*IFERROR(INDEX(کاتالوگ_محصولات!$G$4:$G$303,MATCH(I58,کاتالوگ_محصولات!$A$4:$A$303,0)),0)) -> 0 | AD58: =IF(A58="",0,O58-AC58) -> 2380000 | AE58: =IF(B58="","",LEFT(B58,7)) -> 1405/07
A59: INV-0229 | B59: 1405/07/08 | C59: 2 | D59: ماحی حمیدپور | E59: pm | F59: اسنپ پی | G59: جدید | H59: کانال | J59: کیف 4148 رنگ کرمی | K59: کیف 4148 رنگ کرمی | L59: 1 | M59: 2680000 | N59: 0 | O59: 2680000 | P59: فرهناز | Q59: شکری | R59: 9121599540 | V59: =IF(A59="",0,IF(COUNTIF($A$3:A59,A59)=1,1,0)) -> 0 | W59: =IF(A59="",0,L59*M59) -> 2680000 | X59: =IF(R59<>"",R59,IF(AND(P59<>"",Q59<>""),P59&"|"&Q59,"")) -> 9121599540 | Y59: =IF(X59="",0,IF(COUNTIF($X$3:X59,X59)=1,1,0)) -> 0 | Z59: =IF(V59<>1,0,IF(X59="",0,IF(COUNTIF($X$3:X58,X59)>0,1,0))) -> 0 | AA59: =IF(V59=1,SUMIF($A$3:$A$1622,A59,$O$3:$O$1622),0) -> 0 | AB59: =IF(V59=1,SUMIF($A$3:$A$1622,A59,$L$3:$L$1622),0) -> 0 | AC59: =IF(I59="",0,L59*IFERROR(INDEX(کاتالوگ_محصولات!$G$4:$G$303,MATCH(I59,کاتالوگ_محصولات!$A$4:$A$303,0)),0)) -> 0 | AD59: =IF(A59="",0,O59-AC59) -> 2680000 | AE59: =IF(B59="","",LEFT(B59,7)) -> 1405/07
A60: INV-0230 | B60: 1405/07/08 | C60: 2 | D60: ماحی حمیدپور | E60: PM | F60: کارت | G60: جدید | H60: کانال | J60: کیف 3904 | K60: کیف 3904 | L60: 1 | M60: 2680000 | N60: 0 | O60: 2680000 | P60: ژیلا | Q60: اهدایی | R60: 9166123376 | V60: =IF(A60="",0,IF(COUNTIF($A$3:A60,A60)=1,1,0)) -> 1 | W60: =IF(A60="",0,L60*M60) -> 2680000 | X60: =IF(R60<>"",R60,IF(AND(P60<>"",Q60<>""),P60&"|"&Q60,"")) -> 9166123376 | Y60: =IF(X60="",0,IF(COUNTIF($X$3:X60,X60)=1,1,0)) -> 1 | Z60: =IF(V60<>1,0,IF(X60="",0,IF(COUNTIF($X$3:X59,X60)>0,1,0))) -> 0 | AA60: =IF(V60=1,SUMIF($A$3:$A$1622,A60,$O$3:$O$1622),0) -> 2680000 | AB60: =IF(V60=1,SUMIF($A$3:$A$1622,A60,$L$3:$L$1622),0) -> 1 | AC60: =IF(I60="",0,L60*IFERROR(INDEX(کاتالوگ_محصولات!$G$4:$G$303,MATCH(I60,کاتالوگ_محصولات!$A$4:$A$303,0)),0)) -> 0 | AD60: =IF(A60="",0,O60-AC60) -> 2680000 | AE60: =IF(B60="","",LEFT(B60,7)) -> 1405/07
A61: INV-0231 | B61: 1405/07/08 | C61: 1 | D61: دریا کریمی | E61: PM | F61: کارت | G61: جدید | H61: کانال | J61: شومیز دریا مشکی سایز1 | K61: شومیز دریا مشکی سایز1 | L61: 1 | M61: 2580000 | N61: 0 | O61: 2580000 | P61: خانم | Q61: بهبهانی | R61: 9134032447 | S61: 28 | T61: بهمن | V61: =IF(A61="",0,IF(COUNTIF($A$3:A61,A61)=1,1,0)) -> 1 | W61: =IF(A61="",0,L61*M61) -> 2580000 | X61: =IF(R61<>"",R61,IF(AND(P61<>"",Q61<>""),P61&"|"&Q61,"")) -> 9134032447 | Y61: =IF(X61="",0,IF(COUNTIF($X$3:X61,X61)=1,1,0)) -> 1 | Z61: =IF(V61<>1,0,IF(X61="",0,IF(COUNTIF($X$3:X60,X61)>0,1,0))) -> 0 | AA61: =IF(V61=1,SUMIF($A$3:$A$1622,A61,$O$3:$O$1622),0) -> 2580000 | AB61: =IF(V61=1,SUMIF($A$3:$A$1622,A61,$L$3:$L$1622),0) -> 1 | AC61: =IF(I61="",0,L61*IFERROR(INDEX(کاتالوگ_محصولات!$G$4:$G$303,MATCH(I61,کاتالوگ_محصولات!$A$4:$A$303,0)),0)) -> 0 | AD61: =IF(A61="",0,O61-AC61) -> 2580000 | AE61: =IF(B61="","",LEFT(B61,7)) -> 1405/07
A62: INV-0232 | B62: 1405/07/08 | C62: 1 | D62: دریا کریمی | E62: PM | F62: کارت | H62: کانال | J62: صندل کرم 37 | K62: صندل کرم 37 | L62: 1 | M62: 2890000 | N62: 0 | O62: 2890000 | P62: خانم | Q62: فتحیه | R62: 9302627101 | S62: 1 | T62: 2 | V62: =IF(A62="",0,IF(COUNTIF($A$3:A62,A62)=1,1,0)) -> 1 | W62: =IF(A62="",0,L62*M62) -> 2890000 | X62: =IF(R62<>"",R62,IF(AND(P62<>"",Q62<>""),P62&"|"&Q62,"")) -> 9302627101 | Y62: =IF(X62="",0,IF(COUNTIF($X$3:X62,X62)=1,1,0)) -> 1 | Z62: =IF(V62<>1,0,IF(X62="",0,IF(COUNTIF($X$3:X61,X62)>0,1,0))) -> 0 | AA62: =IF(V62=1,SUMIF($A$3:$A$1622,A62,$O$3:$O$1622),0) -> 2890000 | AB62: =IF(V62=1,SUMIF($A$3:$A$1622,A62,$L$3:$L$1622),0) -> 1 | AC62: =IF(I62="",0,L62*IFERROR(INDEX(کاتالوگ_محصولات!$G$4:$G$303,MATCH(I62,کاتالوگ_محصولات!$A$4:$A$303,0)),0)) -> 0 | AD62: =IF(A62="",0,O62-AC62) -> 2890000 | AE62: =IF(B62="","",LEFT(B62,7)) -> 1405/07
A63: INV-0233 | B63: 1405/07/08 | C63: 1 | D63: دریا کریمی | E63: PM | F63: کارت | G63: مشتری بازگشتی | H63: کانال | J63: کیف سرمه ای 2771 | K63: کیف سرمه ای 2771 | L63: 1 | M63: 1360000 | N63: 0 | O63: 1360000 | P63: خانم | Q63: موسوی | R63: 9132679141 | S63: 13 | T63: 3 | V63: =IF(A63="",0,IF(COUNTIF($A$3:A63,A63)=1,1,0)) -> 1 | W63: =IF(A63="",0,L63*M63) -> 1360000 | X63: =IF(R63<>"",R63,IF(AND(P63<>"",Q63<>""),P63&"|"&Q63,"")) -> 9132679141 | Y63: =IF(X63="",0,IF(COUNTIF($X$3:X63,X63)=1,1,0)) -> 1 | Z63: =IF(V63<>1,0,IF(X63="",0,IF(COUNTIF($X$3:X62,X63)>0,1,0))) -> 0 | AA63: =IF(V63=1,SUMIF($A$3:$A$1622,A63,$O$3:$O$1622),0) -> 4240000 | AB63: =IF(V63=1,SUMIF($A$3:$A$1622,A63,$L$3:$L$1622),0) -> 2 | AC63: =IF(I63="",0,L63*IFERROR(INDEX(کاتالوگ_محصولات!$G$4:$G$303,MATCH(I63,کاتالوگ_محصولات!$A$4:$A$303,0)),0)) -> 0 | AD63: =IF(A63="",0,O63-AC63) -> 1360000 | AE63: =IF(B63="","",LEFT(B63,7)) -> 1405/07
A64: INV-0233 | B64: 1405/07/08 | C64: 1 | D64: دریا کریمی | E64: PM | F64: کارت | G64: مشتری بازگشتی | H64: کانال | J64: کیف 4148 قهوه ای | K64: کیف 4148 قهوه ای | L64: 1 | M64: 2880000 | N64: 0 | O64: 2880000 | P64: خانم | Q64: موسوی | R64: 9132679141 | S64: 13 | T64: 3 | V64: =IF(A64="",0,IF(COUNTIF($A$3:A64,A64)=1,1,0)) -> 0 | W64: =IF(A64="",0,L64*M64) -> 2880000 | X64: =IF(R64<>"",R64,IF(AND(P64<>"",Q64<>""),P64&"|"&Q64,"")) -> 9132679141 | Y64: =IF(X64="",0,IF(COUNTIF($X$3:X64,X64)=1,1,0)) -> 0 | Z64: =IF(V64<>1,0,IF(X64="",0,IF(COUNTIF($X$3:X63,X64)>0,1,0))) -> 0 | AA64: =IF(V64=1,SUMIF($A$3:$A$1622,A64,$O$3:$O$1622),0) -> 0 | AB64: =IF(V64=1,SUMIF($A$3:$A$1622,A64,$L$3:$L$1622),0) -> 0 | AC64: =IF(I64="",0,L64*IFERROR(INDEX(کاتالوگ_محصولات!$G$4:$G$303,MATCH(I64,کاتالوگ_محصولات!$A$4:$A$303,0)),0)) -> 0 | AD64: =IF(A64="",0,O64-AC64) -> 2880000 | AE64: =IF(B64="","",LEFT(B64,7)) -> 1405/07
A65: INV-0234 | B65: 1405/07/09 | C65: 2 | D65: ماحی حمیدپور | E65: full | F65: کارت | G65: جدید | H65: کانال | J65: بارونی ماهور کرمی 1 | K65: بارونی ماهور کرمی 1 | L65: 1 | M65: 8780000 | N65: 0 | O65: 8780000 | P65: زینب | Q65: قربانی | R65: 9338593391 | U65: اپ سل 15میلیونی | V65: =IF(A65="",0,IF(COUNTIF($A$3:A65,A65)=1,1,0)) -> 1 | W65: =IF(A65="",0,L65*M65) -> 8780000 | X65: =IF(R65<>"",R65,IF(AND(P65<>"",Q65<>""),P65&"|"&Q65,"")) -> 9338593391 | Y65: =IF(X65="",0,IF(COUNTIF($X$3:X65,X65)=1,1,0)) -> 1 | Z65: =IF(V65<>1,0,IF(X65="",0,IF(COUNTIF($X$3:X64,X65)>0,1,0))) -> 0 | AA65: =IF(V65=1,SUMIF($A$3:$A$1622,A65,$O$3:$O$1622),0) -> 16820000 | AB65: =IF(V65=1,SUMIF($A$3:$A$1622,A65,$L$3:$L$1622),0) -> 4 | AC65: =IF(I65="",0,L65*IFERROR(INDEX(کاتالوگ_محصولات!$G$4:$G$303,MATCH(I65,کاتالوگ_محصولات!$A$4:$A$303,0)),0)) -> 0 | AD65: =IF(A65="",0,O65-AC65) -> 8780000 | AE65: =IF(B65="","",LEFT(B65,7)) -> 1405/07
A66: INV-0234 | B66: 1405/07/09 | C66: 2 | D66: ماحی حمیدپور | E66: full | F66: کارت | G66: جدید | H66: کانال | J66: شلوار بیژوطوسی روشن فری سایز | K66: شلوار بیژوطوسی روشن فری سایز | L66: 1 | M66: 1680000 | N66: 0 | O66: 1680000 | P66: زینب | Q66: قربانی | R66: 9338593391 | V66: =IF(A66="",0,IF(COUNTIF($A$3:A66,A66)=1,1,0)) -> 0 | W66: =IF(A66="",0,L66*M66) -> 1680000 | X66: =IF(R66<>"",R66,IF(AND(P66<>"",Q66<>""),P66&"|"&Q66,"")) -> 9338593391 | Y66: =IF(X66="",0,IF(COUNTIF($X$3:X66,X66)=1,1,0)) -> 0 | Z66: =IF(V66<>1,0,IF(X66="",0,IF(COUNTIF($X$3:X65,X66)>0,1,0))) -> 0 | AA66: =IF(V66=1,SUMIF($A$3:$A$1622,A66,$O$3:$O$1622),0) -> 0 | AB66: =IF(V66=1,SUMIF($A$3:$A$1622,A66,$L$3:$L$1622),0) -> 0 | AC66: =IF(I66="",0,L66*IFERROR(INDEX(کاتالوگ_محصولات!$G$4:$G$303,MATCH(I66,کاتالوگ_محصولات!$A$4:$A$303,0)),0)) -> 0 | AD66: =IF(A66="",0,O66-AC66) -> 1680000 | AE66: =IF(B66="","",LEFT(B66,7)) -> 1405/07
A67: INV-0234 | B67: 1405/07/09 | C67: 2 | D67: ماحی حمیدپور | E67: full | F67: کارت | G67: جدید | H67: کانال | J67: کت بیژو طوسی روشن فیری | K67: کت بیژو طوسی روشن فیری | L67: 1 | M67: 3780000 | N67: 0 | O67: 3780000 | P67: زینب | Q67: قربانی | R67: 9338593391 | V67: =IF(A67="",0,IF(COUNTIF($A$3:A67,A67)=1,1,0)) -> 0 | W67: =IF(A67="",0,L67*M67) -> 3780000 | X67: =IF(R67<>"",R67,IF(AND(P67<>"",Q67<>""),P67&"|"&Q67,"")) -> 9338593391 | Y67: =IF(X67="",0,IF(COUNTIF($X$3:X67,X67)=1,1,0)) -> 0 | Z67: =IF(V67<>1,0,IF(X67="",0,IF(COUNTIF($X$3:X66,X67)>0,1,0))) -> 0 | AA67: =IF(V67=1,SUMIF($A$3:$A$1622,A67,$O$3:$O$1622),0) -> 0 | AB67: =IF(V67=1,SUMIF($A$3:$A$1622,A67,$L$3:$L$1622),0) -> 0 | AC67: =IF(I67="",0,L67*IFERROR(INDEX(کاتالوگ_محصولات!$G$4:$G$303,MATCH(I67,کاتالوگ_محصولات!$A$4:$A$303,0)),0)) -> 0 | AD67: =IF(A67="",0,O67-AC67) -> 3780000 | AE67: =IF(B67="","",LEFT(B67,7)) -> 1405/07
A68: INV-0234 | B68: 1405/07/09 | C68: 2 | D68: ماحی حمیدپور | E68: full | F68: کارت | G68: جدید | H68: کانال | J68: شومیز دریا صورتی سایز2 | K68: شومیز دریا صورتی سایز2 | L68: 1 | M68: 2580000 | N68: 0 | O68: 2580000 | P68: زینب | Q68: قربانی | R68: 9338593391 | V68: =IF(A68="",0,IF(COUNTIF($A$3:A68,A68)=1,1,0)) -> 0 | W68: =IF(A68="",0,L68*M68) -> 2580000 | X68: =IF(R68<>"",R68,IF(AND(P68<>"",Q68<>""),P68&"|"&Q68,"")) -> 9338593391 | Y68: =IF(X68="",0,IF(COUNTIF($X$3:X68,X68)=1,1,0)) -> 0 | Z68: =IF(V68<>1,0,IF(X68="",0,IF(COUNTIF($X$3:X67,X68)>0,1,0))) -> 0 | AA68: =IF(V68=1,SUMIF($A$3:$A$1622,A68,$O$3:$O$1622),0) -> 0 | AB68: =IF(V68=1,SUMIF($A$3:$A$1622,A68,$L$3:$L$1622),0) -> 0 | AC68: =IF(I68="",0,L68*IFERROR(INDEX(کاتالوگ_محصولات!$G$4:$G$303,MATCH(I68,کاتالوگ_محصولات!$A$4:$A$303,0)),0)) -> 0 | AD68: =IF(A68="",0,O68-AC68) -> 2580000 | AE68: =IF(B68="","",LEFT(B68,7)) -> 1405/07
A69: INV-0235 | B69: 1405/07/09 | C69: 2 | D69: ماحی حمیدپور | E69: full | F69: کارت- اسنپ پی | G69: جدید | H69: کانال | J69: شلوار کاترین قهوه ای1 | K69: شلوار کاترین قهوه ای1 | L69: 1 | M69: 4580000 | N69: 0 | O69: 4580000 | P69: نگار | Q69: شریفی | R69: 9103309983 | S69: 9 | T69: 1383/09 | V69: =IF(A69="",0,IF(COUNTIF($A$3:A69,A69)=1,1,0)) -> 1 | W69: =IF(A69="",0,L69*M69) -> 4580000 | X69: =IF(R69<>"",R69,IF(AND(P69<>"",Q69<>""),P69&"|"&Q69,"")) -> 9103309983 | Y69: =IF(X69="",0,IF(COUNTIF($X$3:X69,X69)=1,1,0)) -> 1 | Z69: =IF(V69<>1,0,IF(X69="",0,IF(COUNTIF($X$3:X68,X69)>0,1,0))) -> 0 | AA69: =IF(V69=1,SUMIF($A$3:$A$1622,A69,$O$3:$O$1622),0) -> 5870000 | AB69: =IF(V69=1,SUMIF($A$3:$A$1622,A69,$L$3:$L$1622),0) -> 2 | AC69: =IF(I69="",0,L69*IFERROR(INDEX(کاتالوگ_محصولات!$G$4:$G$303,MATCH(I69,کاتالوگ_محصولات!$A$4:$A$303,0)),0)) -> 0 | AD69: =IF(A69="",0,O69-AC69) -> 4580000 | AE69: =IF(B69="","",LEFT(B69,7)) -> 1405/07
A70: INV-0235 | B70: 1405/07/09 | C70: 2 | D70: ماحی حمیدپور | E70: full | F70: کارت- اسنپ پی | G70: جدید | H70: کانال | J70: شلوار چین طبقه ای سبز | K70: شلوار چین طبقه ای سبز | L70: 1 | M70: 1290000 | N70: 0 | O70: 1290000 | P70: نگار | Q70: شریفی | R70: 9103309983 | S70: 9 | T70: 1383/09 | V70: =IF(A70="",0,IF(COUNTIF($A$3:A70,A70)=1,1,0)) -> 0 | W70: =IF(A70="",0,L70*M70) -> 1290000 | X70: =IF(R70<>"",R70,IF(AND(P70<>"",Q70<>""),P70&"|"&Q70,"")) -> 9103309983 | Y70: =IF(X70="",0,IF(COUNTIF($X$3:X70,X70)=1,1,0)) -> 0 | Z70: =IF(V70<>1,0,IF(X70="",0,IF(COUNTIF($X$3:X69,X70)>0,1,0))) -> 0 | AA70: =IF(V70=1,SUMIF($A$3:$A$1622,A70,$O$3:$O$1622),0) -> 0 | AB70: =IF(V70=1,SUMIF($A$3:$A$1622,A70,$L$3:$L$1622),0) -> 0 | AC70: =IF(I70="",0,L70*IFERROR(INDEX(کاتالوگ_محصولات!$G$4:$G$303,MATCH(I70,کاتالوگ_محصولات!$A$4:$A$303,0)),0)) -> 0 | AD70: =IF(A70="",0,O70-AC70) -> 1290000 | AE70: =IF(B70="","",LEFT(B70,7)) -> 1405/07
A71: INV-0236 | B71: 1405/07/09 | C71: 2 | D71: ماحی حمیدپور | E71: full | F71: کارت | G71: جدید | H71: کانال | J71: شومیز مانلی قرمز 1 | K71: شومیز مانلی قرمز 1 | L71: 1 | M71: 3450000 | N71: 0 | O71: 3450000 | P71: یوسف | Q71: نصیری | R71: 9126055141 | V71: =IF(A71="",0,IF(COUNTIF($A$3:A71,A71)=1,1,0)) -> 1 | W71: =IF(A71="",0,L71*M71) -> 3450000 | X71: =IF(R71<>"",R71,IF(AND(P71<>"",Q71<>""),P71&"|"&Q71,"")) -> 9126055141 | Y71: =IF(X71="",0,IF(COUNTIF($X$3:X71,X71)=1,1,0)) -> 1 | Z71: =IF(V71<>1,0,IF(X71="",0,IF(COUNTIF($X$3:X70,X71)>0,1,0))) -> 0 | AA71: =IF(V71=1,SUMIF($A$3:$A$1622,A71,$O$3:$O$1622),0) -> 6630000 | AB71: =IF(V71=1,SUMIF($A$3:$A$1622,A71,$L$3:$L$1622),0) -> 2 | AC71: =IF(I71="",0,L71*IFERROR(INDEX(کاتالوگ_محصولات!$G$4:$G$303,MATCH(I71,کاتالوگ_محصولات!$A$4:$A$303,0)),0)) -> 0 | AD71: =IF(A71="",0,O71-AC71) -> 3450000 | AE71: =IF(B71="","",LEFT(B71,7)) -> 1405/07
A72: INV-0236 | B72: 1405/07/09 | C72: 2 | D72: ماحی حمیدپور | E72: full | F72: کارت | G72: جدید | H72: کانال | J72: دامن ساتن قرمز1 | K72: دامن ساتن قرمز1 | L72: 1 | M72: 3180000 | N72: 0 | O72: 3180000 | P72: یوسف | Q72: نصیری | R72: 9126055141 | V72: =IF(A72="",0,IF(COUNTIF($A$3:A72,A72)=1,1,0)) -> 0 | W72: =IF(A72="",0,L72*M72) -> 3180000 | X72: =IF(R72<>"",R72,IF(AND(P72<>"",Q72<>""),P72&"|"&Q72,"")) -> 9126055141 | Y72: =IF(X72="",0,IF(COUNTIF($X$3:X72,X72)=1,1,0)) -> 0 | Z72: =IF(V72<>1,0,IF(X72="",0,IF(COUNTIF($X$3:X71,X72)>0,1,0))) -> 0 | AA72: =IF(V72=1,SUMIF($A$3:$A$1622,A72,$O$3:$O$1622),0) -> 0 | AB72: =IF(V72=1,SUMIF($A$3:$A$1622,A72,$L$3:$L$1622),0) -> 0 | AC72: =IF(I72="",0,L72*IFERROR(INDEX(کاتالوگ_محصولات!$G$4:$G$303,MATCH(I72,کاتالوگ_محصولات!$A$4:$A$303,0)),0)) -> 0 | AD72: =IF(A72="",0,O72-AC72) -> 3180000 | AE72: =IF(B72="","",LEFT(B72,7)) -> 1405/07
A73: INV-0237 | B73: 1405/07/09 | C73: 1 | D73: دریا کریمی | E73: PM | F73: اسنپ پی | G73: جدید | H73: کانال | J73: بامبر دانتل ابی 2 | K73: بامبر دانتل ابی 2 | L73: 1 | M73: 4180000 | N73: 0 | O73: 4180000 | P73: مریم | Q73: اسد الهی | R73: 9174117662 | S73: 6 | T73: 12 | V73: =IF(A73="",0,IF(COUNTIF($A$3:A73,A73)=1,1,0)) -> 1 | W73: =IF(A73="",0,L73*M73) -> 4180000 | X73: =IF(R73<>"",R73,IF(AND(P73<>"",Q73<>""),P73&"|"&Q73,"")) -> 9174117662 | Y73: =IF(X73="",0,IF(COUNTIF($X$3:X73,X73)=1,1,0)) -> 1 | Z73: =IF(V73<>1,0,IF(X73="",0,IF(COUNTIF($X$3:X72,X73)>0,1,0))) -> 0 | AA73: =IF(V73=1,SUMIF($A$3:$A$1622,A73,$O$3:$O$1622),0) -> 4180000 | AB73: =IF(V73=1,SUMIF($A$3:$A$1622,A73,$L$3:$L$1622),0) -> 1 | AC73: =IF(I73="",0,L73*IFERROR(INDEX(کاتالوگ_محصولات!$G$4:$G$303,MATCH(I73,کاتالوگ_محصولات!$A$4:$A$303,0)),0)) -> 0 | AD73: =IF(A73="",0,O73-AC73) -> 4180000 | AE73: =IF(B73="","",LEFT(B73,7)) -> 1405/07
A74: INV-0238 | B74: 1405/07/09 | C74: 1 | D74: دریا کریمی | E74: PM | F74: کارت | G74: جدید | H74: کانال | J74: صندل مشکی39 | K74: صندل مشکی39 | L74: 1 | M74: 2880000 | N74: 0 | O74: 2880000 | P74: ریتا | Q74: جمعه | R74: 9113779465 | S74: 1 | T74: 1366/01 | V74: =IF(A74="",0,IF(COUNTIF($A$3:A74,A74)=1,1,0)) -> 1 | W74: =IF(A74="",0,L74*M74) -> 2880000 | X74: =IF(R74<>"",R74,IF(AND(P74<>"",Q74<>""),P74&"|"&Q74,"")) -> 9113779465 | Y74: =IF(X74="",0,IF(COUNTIF($X$3:X74,X74)=1,1,0)) -> 1 | Z74: =IF(V74<>1,0,IF(X74="",0,IF(COUNTIF($X$3:X73,X74)>0,1,0))) -> 0 | AA74: =IF(V74=1,SUMIF($A$3:$A$1622,A74,$O$3:$O$1622),0) -> 2880000 | AB74: =IF(V74=1,SUMIF($A$3:$A$1622,A74,$L$3:$L$1622),0) -> 1 | AC74: =IF(I74="",0,L74*IFERROR(INDEX(کاتالوگ_محصولات!$G$4:$G$303,MATCH(I74,کاتالوگ_محصولات!$A$4:$A$303,0)),0)) -> 0 | AD74: =IF(A74="",0,O74-AC74) -> 2880000 | AE74: =IF(B74="","",LEFT(B74,7)) -> 1405/07
A75: INV-0239 | B75: 1405/07/09 | C75: 2 | D75: ماحی حمیدپور | E75: full | F75: کارت | G75: جدید | H75: کانال | J75: کت سرمه ای دیپلمات2 | K75: کت سرمه ای دیپلمات2 | L75: 1 | M75: 2580000 | N75: 0 | O75: 2580000 | P75: وحیده | Q75: ملک | R75: 9359311885 | S75: 6 | T75: 1373/06 | V75: =IF(A75="",0,IF(COUNTIF($A$3:A75,A75)=1,1,0)) -> 1 | W75: =IF(A75="",0,L75*M75) -> 2580000 | X75: =IF(R75<>"",R75,IF(AND(P75<>"",Q75<>""),P75&"|"&Q75,"")) -> 9359311885 | Y75: =IF(X75="",0,IF(COUNTIF($X$3:X75,X75)=1,1,0)) -> 1 | Z75: =IF(V75<>1,0,IF(X75="",0,IF(COUNTIF($X$3:X74,X75)>0,1,0))) -> 0 | AA75: =IF(V75=1,SUMIF($A$3:$A$1622,A75,$O$3:$O$1622),0) -> 3780000 | AB75: =IF(V75=1,SUMIF($A$3:$A$1622,A75,$L$3:$L$1622),0) -> 2 | AC75: =IF(I75="",0,L75*IFERROR(INDEX(کاتالوگ_محصولات!$G$4:$G$303,MATCH(I75,کاتالوگ_محصولات!$A$4:$A$303,0)),0)) -> 0 | AD75: =IF(A75="",0,O75-AC75) -> 2580000 | AE75: =IF(B75="","",LEFT(B75,7)) -> 1405/07
A76: INV-0239 | B76: 1405/07/09 | C76: 2 | D76: ماحی حمیدپور | E76: full | F76: کارت | G76: جدید | H76: کانال | J76: تنگ تاپ سرمه ای | K76: تنگ تاپ سرمه ای | L76: 1 | M76: 1280000 | N76: 80000 | O76: 1200000 | P76: وحیده | Q76: ملک | R76: 9359311885 | S76: 6 | T76: 1373/06 | V76: =IF(A76="",0,IF(COUNTIF($A$3:A76,A76)=1,1,0)) -> 0 | W76: =IF(A76="",0,L76*M76) -> 1280000 | X76: =IF(R76<>"",R76,IF(AND(P76<>"",Q76<>""),P76&"|"&Q76,"")) -> 9359311885 | Y76: =IF(X76="",0,IF(COUNTIF($X$3:X76,X76)=1,1,0)) -> 0 | Z76: =IF(V76<>1,0,IF(X76="",0,IF(COUNTIF($X$3:X75,X76)>0,1,0))) -> 0 | AA76: =IF(V76=1,SUMIF($A$3:$A$1622,A76,$O$3:$O$1622),0) -> 0 | AB76: =IF(V76=1,SUMIF($A$3:$A$1622,A76,$L$3:$L$1622),0) -> 0 | AC76: =IF(I76="",0,L76*IFERROR(INDEX(کاتالوگ_محصولات!$G$4:$G$303,MATCH(I76,کاتالوگ_محصولات!$A$4:$A$303,0)),0)) -> 0 | AD76: =IF(A76="",0,O76-AC76) -> 1200000 | AE76: =IF(B76="","",LEFT(B76,7)) -> 1405/07
A77: INV-0240 | B77: 1405/07/09 | C77: 1 | D77: دریا کریمی | E77: PM | F77: کارت | G77: جدید | H77: کانال | J77: بامبر سرمه ای | K77: بامبر سرمه ای | L77: 1 | M77: 6780000 | N77: 2712000 | O77: 0 | U77: خرید پرسنلی کریمی پرداخت آخر ماه | V77: =IF(A77="",0,IF(COUNTIF($A$3:A77,A77)=1,1,0)) -> 1 | W77: =IF(A77="",0,L77*M77) -> 6780000 | X77: =IF(R77<>"",R77,IF(AND(P77<>"",Q77<>""),P77&"|"&Q77,"")) | Y77: =IF(X77="",0,IF(COUNTIF($X$3:X77,X77)=1,1,0)) -> 0 | Z77: =IF(V77<>1,0,IF(X77="",0,IF(COUNTIF($X$3:X76,X77)>0,1,0))) -> 0 | AA77: =IF(V77=1,SUMIF($A$3:$A$1622,A77,$O$3:$O$1622),0) -> 1068000 | AB77: =IF(V77=1,SUMIF($A$3:$A$1622,A77,$L$3:$L$1622),0) -> 2 | AC77: =IF(I77="",0,L77*IFERROR(INDEX(کاتالوگ_محصولات!$G$4:$G$303,MATCH(I77,کاتالوگ_محصولات!$A$4:$A$303,0)),0)) -> 0 | AD77: =IF(A77="",0,O77-AC77) -> 0 | AE77: =IF(B77="","",LEFT(B77,7)) -> 1405/07
A78: INV-0241 | B78: 1405/07/09 | C78: 2 | D78: ماحی حمیدپور | E78: full | F78: کارت | G78: جدید | H78: کانال | J78: بامبر قهوه ای | K78: بامبر قهوه ای | L78: 1 | M78: 6780000 | N78: 2712000 | O78: 0 | U78: خرید پرسنلی خانم حمیدپور پرداخت آخر ماه | V78: =IF(A78="",0,IF(COUNTIF($A$3:A78,A78)=1,1,0)) -> 1 | W78: =IF(A78="",0,L78*M78) -> 6780000 | X78: =IF(R78<>"",R78,IF(AND(P78<>"",Q78<>""),P78&"|"&Q78,"")) | Y78: =IF(X78="",0,IF(COUNTIF($X$3:X78,X78)=1,1,0)) -> 0 | Z78: =IF(V78<>1,0,IF(X78="",0,IF(COUNTIF($X$3:X77,X78)>0,1,0))) -> 0 | AA78: =IF(V78=1,SUMIF($A$3:$A$1622,A78,$O$3:$O$1622),0) -> 0 | AB78: =IF(V78=1,SUMIF($A$3:$A$1622,A78,$L$3:$L$1622),0) -> 1 | AC78: =IF(I78="",0,L78*IFERROR(INDEX(کاتالوگ_محصولات!$G$4:$G$303,MATCH(I78,کاتالوگ_محصولات!$A$4:$A$303,0)),0)) -> 0 | AD78: =IF(A78="",0,O78-AC78) -> 0 | AE78: =IF(B78="","",LEFT(B78,7)) -> 1405/07
A79: INV-0242 | B79: 1405/07/10 | C79: 1 | D79: دریا کریمی | E79: full | F79: کارت | G79: جدید | H79: کانال | J79: کیف تدی | K79: کیف تدی | L79: 1 | M79: 2040000 | N79: 0 | O79: 2040000 | P79: خانم | Q79: ستاره | R79: 9125809479 | S79: 28 | V79: =IF(A79="",0,IF(COUNTIF($A$3:A79,A79)=1,1,0)) -> 1 | W79: =IF(A79="",0,L79*M79) -> 2040000 | X79: =IF(R79<>"",R79,IF(AND(P79<>"",Q79<>""),P79&"|"&Q79,"")) -> 9125809479 | Y79: =IF(X79="",0,IF(COUNTIF($X$3:X79,X79)=1,1,0)) -> 1 | Z79: =IF(V79<>1,0,IF(X79="",0,IF(COUNTIF($X$3:X78,X79)>0,1,0))) -> 0 | AA79: =IF(V79=1,SUMIF($A$3:$A$1622,A79,$O$3:$O$1622),0) -> 4080000 | AB79: =IF(V79=1,SUMIF($A$3:$A$1622,A79,$L$3:$L$1622),0) -> 2 | AC79: =IF(I79="",0,L79*IFERROR(INDEX(کاتالوگ_محصولات!$G$4:$G$303,MATCH(I79,کاتالوگ_محصولات!$A$4:$A$303,0)),0)) -> 0 | AD79: =IF(A79="",0,O79-AC79) -> 2040000 | AE79: =IF(B79="","",LEFT(B79,7)) -> 1405/07
A80: INV-0242 | B80: 1405/07/10 | C80: 1 | D80: دریا کریمی | E80: full | F80: کارت | G80: جدید | H80: کانال | J80: کیف تدی | K80: کیف تدی | L80: 1 | M80: 2040000 | N80: 0 | O80: 2040000 | P80: خانم | Q80: ستاره | R80: 9125809479 | S80: 28 | V80: =IF(A80="",0,IF(COUNTIF($A$3:A80,A80)=1,1,0)) -> 0 | W80: =IF(A80="",0,L80*M80) -> 2040000 | X80: =IF(R80<>"",R80,IF(AND(P80<>"",Q80<>""),P80&"|"&Q80,"")) -> 9125809479 | Y80: =IF(X80="",0,IF(COUNTIF($X$3:X80,X80)=1,1,0)) -> 0 | Z80: =IF(V80<>1,0,IF(X80="",0,IF(COUNTIF($X$3:X79,X80)>0,1,0))) -> 0 | AA80: =IF(V80=1,SUMIF($A$3:$A$1622,A80,$O$3:$O$1622),0) -> 0 | AB80: =IF(V80=1,SUMIF($A$3:$A$1622,A80,$L$3:$L$1622),0) -> 0 | AC80: =IF(I80="",0,L80*IFERROR(INDEX(کاتالوگ_محصولات!$G$4:$G$303,MATCH(I80,کاتالوگ_محصولات!$A$4:$A$303,0)),0)) -> 0 | AD80: =IF(A80="",0,O80-AC80) -> 2040000 | AE80: =IF(B80="","",LEFT(B80,7)) -> 1405/07
A81: INV-0243 | B81: 1405/07/10 | C81: 1 | D81: دریا کریمی | E81: full | F81: کارت | G81: جدید | H81: کانال | J81: شومیز مانلی مشکی2 | K81: شومیز مانلی مشکی2 | L81: 1 | M81: 3450000 | N81: 0 | O81: 3450000 | V81: =IF(A81="",0,IF(COUNTIF($A$3:A81,A81)=1,1,0)) -> 1 | W81: =IF(A81="",0,L81*M81) -> 3450000 | X81: =IF(R81<>"",R81,IF(AND(P81<>"",Q81<>""),P81&"|"&Q81,"")) | Y81: =IF(X81="",0,IF(COUNTIF($X$3:X81,X81)=1,1,0)) -> 0 | Z81: =IF(V81<>1,0,IF(X81="",0,IF(COUNTIF($X$3:X80,X81)>0,1,0))) -> 0 | AA81: =IF(V81=1,SUMIF($A$3:$A$1622,A81,$O$3:$O$1622),0) -> 3450000 | AB81: =IF(V81=1,SUMIF($A$3:$A$1622,A81,$L$3:$L$1622),0) -> 1 | AC81: =IF(I81="",0,L81*IFERROR(INDEX(کاتالوگ_محصولات!$G$4:$G$303,MATCH(I81,کاتالوگ_محصولات!$A$4:$A$303,0)),0)) -> 0 | AD81: =IF(A81="",0,O81-AC81) -> 3450000 | AE81: =IF(B81="","",LEFT(B81,7)) -> 1405/07
A82: INV-0244 | B82: 1405/07/10 | C82: 1 | D82: دریا کریمی | E82: _full | F82: کارت | G82: جدید | H82: کانال | J82: شومیز سایه سفید سایز1 | K82: شومیز سایه سفید سایز1 | L82: 1 | M82: 2480000 | N82: 0 | O82: 2480000 | P82: خانم | Q82: شاهین فر | R82: 9122109039 | S82: 1 | T82: 9 | V82: =IF(A82="",0,IF(COUNTIF($A$3:A82,A82)=1,1,0)) -> 1 | W82: =IF(A82="",0,L82*M82) -> 2480000 | X82: =IF(R82<>"",R82,IF(AND(P82<>"",Q82<>""),P82&"|"&Q82,"")) -> 9122109039 | Y82: =IF(X82="",0,IF(COUNTIF($X$3:X82,X82)=1,1,0)) -> 1 | Z82: =IF(V82<>1,0,IF(X82="",0,IF(COUNTIF($X$3:X81,X82)>0,1,0))) -> 0 | AA82: =IF(V82=1,SUMIF($A$3:$A$1622,A82,$O$3:$O$1622),0) -> 8560000 | AB82: =IF(V82=1,SUMIF($A$3:$A$1622,A82,$L$3:$L$1622),0) -> 3 | AC82: =IF(I82="",0,L82*IFERROR(INDEX(کاتالوگ_محصولات!$G$4:$G$303,MATCH(I82,کاتالوگ_محصولات!$A$4:$A$303,0)),0)) -> 0 | AD82: =IF(A82="",0,O82-AC82) -> 2480000 | AE82: =IF(B82="","",LEFT(B82,7)) -> 1405/07
A83: INV-0244 | B83: 1405/07/10 | C83: 1 | D83: دریا کریمی | E83: _full | F83: کارت | G83: جدید | H83: کانال | J83: کیف 2720کرم | K83: کیف 2720کرم | L83: 1 | M83: 2880000 | N83: 0 | O83: 2880000 | P83: خانم | Q83: شاهین فر | R83: 9122109039 | S83: 1 | T83: 9 | V83: =IF(A83="",0,IF(COUNTIF($A$3:A83,A83)=1,1,0)) -> 0 | W83: =IF(A83="",0,L83*M83) -> 2880000 | X83: =IF(R83<>"",R83,IF(AND(P83<>"",Q83<>""),P83&"|"&Q83,"")) -> 9122109039 | Y83: =IF(X83="",0,IF(COUNTIF($X$3:X83,X83)=1,1,0)) -> 0 | Z83: =IF(V83<>1,0,IF(X83="",0,IF(COUNTIF($X$3:X82,X83)>0,1,0))) -> 0 | AA83: =IF(V83=1,SUMIF($A$3:$A$1622,A83,$O$3:$O$1622),0) -> 0 | AB83: =IF(V83=1,SUMIF($A$3:$A$1622,A83,$L$3:$L$1622),0) -> 0 | AC83: =IF(I83="",0,L83*IFERROR(INDEX(کاتالوگ_محصولات!$G$4:$G$303,MATCH(I83,کاتالوگ_محصولات!$A$4:$A$303,0)),0)) -> 0 | AD83: =IF(A83="",0,O83-AC83) -> 2880000 | AE83: =IF(B83="","",LEFT(B83,7)) -> 1405/07
A84: INV-0244 | B84: 1405/07/10 | C84: 1 | D84: دریا کریمی | E84: _full | F84: کارت | G84: جدید | H84: کانال | J84: وست بیژو مشکی فری | K84: وست بیژو مشکی فری | L84: 1 | M84: 3200000 | N84: 0 | O84: 3200000 | P84: خانم | Q84: شاهین فر | R84: 9122109039 | S84: 1 | T84: 9 | V84: =IF(A84="",0,IF(COUNTIF($A$3:A84,A84)=1,1,0)) -> 0 | W84: =IF(A84="",0,L84*M84) -> 3200000 | X84: =IF(R84<>"",R84,IF(AND(P84<>"",Q84<>""),P84&"|"&Q84,"")) -> 9122109039 | Y84: =IF(X84="",0,IF(COUNTIF($X$3:X84,X84)=1,1,0)) -> 0 | Z84: =IF(V84<>1,0,IF(X84="",0,IF(COUNTIF($X$3:X83,X84)>0,1,0))) -> 0 | AA84: =IF(V84=1,SUMIF($A$3:$A$1622,A84,$O$3:$O$1622),0) -> 0 | AB84: =IF(V84=1,SUMIF($A$3:$A$1622,A84,$L$3:$L$1622),0) -> 0 | AC84: =IF(I84="",0,L84*IFERROR(INDEX(کاتالوگ_محصولات!$G$4:$G$303,MATCH(I84,کاتالوگ_محصولات!$A$4:$A$303,0)),0)) -> 0 | AD84: =IF(A84="",0,O84-AC84) -> 3200000 | AE84: =IF(B84="","",LEFT(B84,7)) -> 1405/07
A85: INV-0245 | B85: 1405/07/10 | C85: 1 | D85: دریا کریمی | E85: full | F85: کارت | G85: برگشتی | H85: کانال | J85: بارونی ماهور نسکافه ای 1 | K85: بارونی ماهور نسکافه ای 1 | L85: 1 | M85: 8780000 | N85: 880000 | O85: 7900000 | P85: معصومه | Q85: هاشمی | R85: 9124018425 | S85: 11 | T85: 1378/07 | U85: 10درصد کسر شد بابت روز تولد | V85: =IF(A85="",0,IF(COUNTIF($A$3:A85,A85)=1,1,0)) -> 1 | W85: =IF(A85="",0,L85*M85) -> 8780000 | X85: =IF(R85<>"",R85,IF(AND(P85<>"",Q85<>""),P85&"|"&Q85,"")) -> 9124018425 | Y85: =IF(X85="",0,IF(COUNTIF($X$3:X85,X85)=1,1,0)) -> 1 | Z85: =IF(V85<>1,0,IF(X85="",0,IF(COUNTIF($X$3:X84,X85)>0,1,0))) -> 0 | AA85: =IF(V85=1,SUMIF($A$3:$A$1622,A85,$O$3:$O$1622),0) -> 7900000 | AB85: =IF(V85=1,SUMIF($A$3:$A$1622,A85,$L$3:$L$1622),0) -> 1 | AC85: =IF(I85="",0,L85*IFERROR(INDEX(کاتالوگ_محصولات!$G$4:$G$303,MATCH(I85,کاتالوگ_محصولات!$A$4:$A$303,0)),0)) -> 0 | AD85: =IF(A85="",0,O85-AC85) -> 7900000 | AE85: =IF(B85="","",LEFT(B85,7)) -> 1405/07
A86: INV-0246 | B86: 1405/07/11 | C86: 2 | D86: ماحی حمیدپور | E86: am | F86: کارت | G86: جدید | H86: کانال | J86: کیف 2669 مشکی | K86: کیف 2669 مشکی | L86: 1 | M86: 2880000 | N86: 0 | O86: 2880000 | P86: اسیه | Q86: کولیوند | R86: 9124596838 | V86: =IF(A86="",0,IF(COUNTIF($A$3:A86,A86)=1,1,0)) -> 1 | W86: =IF(A86="",0,L86*M86) -> 2880000 | X86: =IF(R86<>"",R86,IF(AND(P86<>"",Q86<>""),P86&"|"&Q86,"")) -> 9124596838 | Y86: =IF(X86="",0,IF(COUNTIF($X$3:X86,X86)=1,1,0)) -> 1 | Z86: =IF(V86<>1,0,IF(X86="",0,IF(COUNTIF($X$3:X85,X86)>0,1,0))) -> 0 | AA86: =IF(V86=1,SUMIF($A$3:$A$1622,A86,$O$3:$O$1622),0) -> 2880000 | AB86: =IF(V86=1,SUMIF($A$3:$A$1622,A86,$L$3:$L$1622),0) -> 1 | AC86: =IF(I86="",0,L86*IFERROR(INDEX(کاتالوگ_محصولات!$G$4:$G$303,MATCH(I86,کاتالوگ_محصولات!$A$4:$A$303,0)),0)) -> 0 | AD86: =IF(A86="",0,O86-AC86) -> 2880000 | AE86: =IF(B86="","",LEFT(B86,7)) -> 1405/07
A87: INV-0247 | B87: 1405/07/11 | C87: 1 | D87: دریا کریمی | E87: PM | F87: کارت | H87: کانال | J87: کت ژاکارد صورتی 1 | K87: کت ژاکارد صورتی 1 | L87: 1 | M87: 3850000 | N87: 0 | O87: 3850000 | P87: مریم | Q87: سلیمی | R87: 9120696926 | S87: 26 | T87: تیر | V87: =IF(A87="",0,IF(COUNTIF($A$3:A87,A87)=1,1,0)) -> 1 | W87: =IF(A87="",0,L87*M87) -> 3850000 | X87: =IF(R87<>"",R87,IF(AND(P87<>"",Q87<>""),P87&"|"&Q87,"")) -> 9120696926 | Y87: =IF(X87="",0,IF(COUNTIF($X$3:X87,X87)=1,1,0)) -> 1 | Z87: =IF(V87<>1,0,IF(X87="",0,IF(COUNTIF($X$3:X86,X87)>0,1,0))) -> 0 | AA87: =IF(V87=1,SUMIF($A$3:$A$1622,A87,$O$3:$O$1622),0) -> 3850000 | AB87: =IF(V87=1,SUMIF($A$3:$A$1622,A87,$L$3:$L$1622),0) -> 1 | AC87: =IF(I87="",0,L87*IFERROR(INDEX(کاتالوگ_محصولات!$G$4:$G$303,MATCH(I87,کاتالوگ_محصولات!$A$4:$A$303,0)),0)) -> 0 | AD87: =IF(A87="",0,O87-AC87) -> 3850000 | AE87: =IF(B87="","",LEFT(B87,7)) -> 1405/07
A88: INV-0248 | B88: 1405/07/11 | C88: 1 | D88: دریا کریمی | E88: PM | F88: کارت | H88: کانال | J88: کیف بزرگ سفید | K88: کیف بزرگ سفید | L88: 1 | M88: 2380000 | N88: 0 | O88: 2380000 | V88: =IF(A88="",0,IF(COUNTIF($A$3:A88,A88)=1,1,0)) -> 1 | W88: =IF(A88="",0,L88*M88) -> 2380000 | X88: =IF(R88<>"",R88,IF(AND(P88<>"",Q88<>""),P88&"|"&Q88,"")) | Y88: =IF(X88="",0,IF(COUNTIF($X$3:X88,X88)=1,1,0)) -> 0 | Z88: =IF(V88<>1,0,IF(X88="",0,IF(COUNTIF($X$3:X87,X88)>0,1,0))) -> 0 | AA88: =IF(V88=1,SUMIF($A$3:$A$1622,A88,$O$3:$O$1622),0) -> 2380000 | AB88: =IF(V88=1,SUMIF($A$3:$A$1622,A88,$L$3:$L$1622),0) -> 1 | AC88: =IF(I88="",0,L88*IFERROR(INDEX(کاتالوگ_محصولات!$G$4:$G$303,MATCH(I88,کاتالوگ_محصولات!$A$4:$A$303,0)),0)) -> 0 | AD88: =IF(A88="",0,O88-AC88) -> 2380000 | AE88: =IF(B88="","",LEFT(B88,7)) -> 1405/07
A89: INV-0240 | B89: 1405/07/12 | C89: 1 | D89: دریا کریمی | E89: PM | F89: کارت | H89: کانال | J89: بامبر سرمه ای | K89: بامبر سرمه ای | L89: 1 | M89: 1068000 | N89: 0 | O89: 1068000 | P89: دریا | Q89: کریمی | U89: تسویه بخشی از خرید پرسنلی | V89: =IF(A89="",0,IF(COUNTIF($A$3:A89,A89)=1,1,0)) -> 0 | W89: =IF(A89="",0,L89*M89) -> 1068000 | X89: =IF(R89<>"",R89,IF(AND(P89<>"",Q89<>""),P89&"|"&Q89,"")) -> دریا|کریمی | Y89: =IF(X89="",0,IF(COUNTIF($X$3:X89,X89)=1,1,0)) -> 1 | Z89: =IF(V89<>1,0,IF(X89="",0,IF(COUNTIF($X$3:X88,X89)>0,1,0))) -> 0 | AA89: =IF(V89=1,SUMIF($A$3:$A$1622,A89,$O$3:$O$1622),0) -> 0 | AB89: =IF(V89=1,SUMIF($A$3:$A$1622,A89,$L$3:$L$1622),0) -> 0 | AC89: =IF(I89="",0,L89*IFERROR(INDEX(کاتالوگ_محصولات!$G$4:$G$303,MATCH(I89,کاتالوگ_محصولات!$A$4:$A$303,0)),0)) -> 0 | AD89: =IF(A89="",0,O89-AC89) -> 1068000 | AE89: =IF(B89="","",LEFT(B89,7)) -> 1405/07
A90: INV-0249 | B90: 1405/07/13 | C90: 2 | D90: ماحی حمیدپور | E90: pm | F90: اسنپ پی | G90: جدید | H90: کانال | J90: شومیز حریر سفید 1 | K90: شومیز حریر سفید 1 | L90: 1 | M90: 2580000 | N90: 0 | O90: 2580000 | P90: نازنین | Q90: برزگری | R90: 9394020373 | V90: =IF(A90="",0,IF(COUNTIF($A$3:A90,A90)=1,1,0)) -> 1 | W90: =IF(A90="",0,L90*M90) -> 2580000 | X90: =IF(R90<>"",R90,IF(AND(P90<>"",Q90<>""),P90&"|"&Q90,"")) -> 9394020373 | Y90: =IF(X90="",0,IF(COUNTIF($X$3:X90,X90)=1,1,0)) -> 1 | Z90: =IF(V90<>1,0,IF(X90="",0,IF(COUNTIF($X$3:X89,X90)>0,1,0))) -> 0 | AA90: =IF(V90=1,SUMIF($A$3:$A$1622,A90,$O$3:$O$1622),0) -> 7160000 | AB90: =IF(V90=1,SUMIF($A$3:$A$1622,A90,$L$3:$L$1622),0) -> 2 | AC90: =IF(I90="",0,L90*IFERROR(INDEX(کاتالوگ_محصولات!$G$4:$G$303,MATCH(I90,کاتالوگ_محصولات!$A$4:$A$303,0)),0)) -> 0 | AD90: =IF(A90="",0,O90-AC90) -> 2580000 | AE90: =IF(B90="","",LEFT(B90,7)) -> 1405/07
A91: INV-0249 | B91: 1405/07/13 | C91: 2 | D91: ماحی حمیدپور | E91: pm | F91: اسنپ پی | G91: جدید | H91: کانال | J91: شلوار کاترین نوک مدادی 2 | K91: شلوار کاترین نوک مدادی 2 | L91: 1 | M91: 4580000 | N91: 0 | O91: 4580000 | P91: نازنین | Q91: برزگری | R91: 9394020373 | V91: =IF(A91="",0,IF(COUNTIF($A$3:A91,A91)=1,1,0)) -> 0 | W91: =IF(A91="",0,L91*M91) -> 4580000 | X91: =IF(R91<>"",R91,IF(AND(P91<>"",Q91<>""),P91&"|"&Q91,"")) -> 9394020373 | Y91: =IF(X91="",0,IF(COUNTIF($X$3:X91,X91)=1,1,0)) -> 0 | Z91: =IF(V91<>1,0,IF(X91="",0,IF(COUNTIF($X$3:X90,X91)>0,1,0))) -> 0 | AA91: =IF(V91=1,SUMIF($A$3:$A$1622,A91,$O$3:$O$1622),0) -> 0 | AB91: =IF(V91=1,SUMIF($A$3:$A$1622,A91,$L$3:$L$1622),0) -> 0 | AC91: =IF(I91="",0,L91*IFERROR(INDEX(کاتالوگ_محصولات!$G$4:$G$303,MATCH(I91,کاتالوگ_محصولات!$A$4:$A$303,0)),0)) -> 0 | AD91: =IF(A91="",0,O91-AC91) -> 4580000 | AE91: =IF(B91="","",LEFT(B91,7)) -> 1405/07
A92: INV-0250 | B92: 1405/07/14 | C92: 1 | D92: دریا کریمی | E92: PM | F92: کارت | G92: مشتری بازگشتی | H92: کانال | J92: کیف 2669 نسکافه ای | K92: کیف 2669 نسکافه ای | L92: 1 | M92: 2980000 | N92: 280000 | O92: 2700000 | P92: خانم | Q92: شاهجویی | R92: 9122197262 | S92: 18 | T92: 10 | V92: =IF(A92="",0,IF(COUNTIF($A$3:A92,A92)=1,1,0)) -> 1 | W92: =IF(A92="",0,L92*M92) -> 2980000 | X92: =IF(R92<>"",R92,IF(AND(P92<>"",Q92<>""),P92&"|"&Q92,"")) -> 9122197262 | Y92: =IF(X92="",0,IF(COUNTIF($X$3:X92,X92)=1,1,0)) -> 1 | Z92: =IF(V92<>1,0,IF(X92="",0,IF(COUNTIF($X$3:X91,X92)>0,1,0))) -> 0 | AA92: =IF(V92=1,SUMIF($A$3:$A$1622,A92,$O$3:$O$1622),0) -> 2700000 | AB92: =IF(V92=1,SUMIF($A$3:$A$1622,A92,$L$3:$L$1622),0) -> 1 | AC92: =IF(I92="",0,L92*IFERROR(INDEX(کاتالوگ_محصولات!$G$4:$G$303,MATCH(I92,کاتالوگ_محصولات!$A$4:$A$303,0)),0)) -> 0 | AD92: =IF(A92="",0,O92-AC92) -> 2700000 | AE92: =IF(B92="","",LEFT(B92,7)) -> 1405/07
A93: INV-0251 | B93: 1405/07/14 | C93: 1 | D93: دریا کریمی | E93: PM | F93: کارت به کارت | G93: جدید | H93: کانال | J93: پولو شرت | K93: پولو شرت | L93: 1 | M93: 1580000 | N93: 0 | O93: 1580000 | P93: امیر ماهان | Q93: محمدی | R93: 9120656704 | S93: 13 | T93: 6 | V93: =IF(A93="",0,IF(COUNTIF($A$3:A93,A93)=1,1,0)) -> 1 | W93: =IF(A93="",0,L93*M93) -> 1580000 | X93: =IF(R93<>"",R93,IF(AND(P93<>"",Q93<>""),P93&"|"&Q93,"")) -> 9120656704 | Y93: =IF(X93="",0,IF(COUNTIF($X$3:X93,X93)=1,1,0)) -> 1 | Z93: =IF(V93<>1,0,IF(X93="",0,IF(COUNTIF($X$3:X92,X93)>0,1,0))) -> 0 | AA93: =IF(V93=1,SUMIF($A$3:$A$1622,A93,$O$3:$O$1622),0) -> 5300000 | AB93: =IF(V93=1,SUMIF($A$3:$A$1622,A93,$L$3:$L$1622),0) -> 3 | AC93: =IF(I93="",0,L93*IFERROR(INDEX(کاتالوگ_محصولات!$G$4:$G$303,MATCH(I93,کاتالوگ_محصولات!$A$4:$A$303,0)),0)) -> 0 | AD93: =IF(A93="",0,O93-AC93) -> 1580000 | AE93: =IF(B93="","",LEFT(B93,7)) -> 1405/07
A94: INV-0251 | B94: 1405/07/14 | C94: 1 | D94: دریا کریمی | E94: PM | F94: کارت به کارت | G94: جدید | H94: کانال | J94: تاپ بند ماکارن | K94: تاپ بند ماکارن | L94: 1 | M94: 928000 | N94: 0 | O94: 928000 | P94: امیر ماهان | Q94: محمدی | R94: 9120656704 | S94: 13 | T94: 6 | V94: =IF(A94="",0,IF(COUNTIF($A$3:A94,A94)=1,1,0)) -> 0 | W94: =IF(A94="",0,L94*M94) -> 928000 | X94: =IF(R94<>"",R94,IF(AND(P94<>"",Q94<>""),P94&"|"&Q94,"")) -> 9120656704 | Y94: =IF(X94="",0,IF(COUNTIF($X$3:X94,X94)=1,1,0)) -> 0 | Z94: =IF(V94<>1,0,IF(X94="",0,IF(COUNTIF($X$3:X93,X94)>0,1,0))) -> 0 | AA94: =IF(V94=1,SUMIF($A$3:$A$1622,A94,$O$3:$O$1622),0) -> 0 | AB94: =IF(V94=1,SUMIF($A$3:$A$1622,A94,$L$3:$L$1622),0) -> 0 | AC94: =IF(I94="",0,L94*IFERROR(INDEX(کاتالوگ_محصولات!$G$4:$G$303,MATCH(I94,کاتالوگ_محصولات!$A$4:$A$303,0)),0)) -> 0 | AD94: =IF(A94="",0,O94-AC94) -> 928000 | AE94: =IF(B94="","",LEFT(B94,7)) -> 1405/07
A95: INV-0251 | B95: 1405/07/14 | C95: 1 | D95: دریا کریمی | E95: PM | F95: کارت به کارت | G95: جدید | H95: کانال | J95: کیف2720 | K95: کیف2720 | L95: 1 | M95: 2880000 | N95: 88000 | O95: 2792000 | P95: امیر ماهان | Q95: محمدی | R95: 9120656704 | S95: 13 | T95: 6 | V95: =IF(A95="",0,IF(COUNTIF($A$3:A95,A95)=1,1,0)) -> 0 | W95: =IF(A95="",0,L95*M95) -> 2880000 | X95: =IF(R95<>"",R95,IF(AND(P95<>"",Q95<>""),P95&"|"&Q95,"")) -> 9120656704 | Y95: =IF(X95="",0,IF(COUNTIF($X$3:X95,X95)=1,1,0)) -> 0 | Z95: =IF(V95<>1,0,IF(X95="",0,IF(COUNTIF($X$3:X94,X95)>0,1,0))) -> 0 | AA95: =IF(V95=1,SUMIF($A$3:$A$1622,A95,$O$3:$O$1622),0) -> 0 | AB95: =IF(V95=1,SUMIF($A$3:$A$1622,A95,$L$3:$L$1622),0) -> 0 | AC95: =IF(I95="",0,L95*IFERROR(INDEX(کاتالوگ_محصولات!$G$4:$G$303,MATCH(I95,کاتالوگ_محصولات!$A$4:$A$303,0)),0)) -> 0 | AD95: =IF(A95="",0,O95-AC95) -> 2792000 | AE95: =IF(B95="","",LEFT(B95,7)) -> 1405/07
A96: INV-0252 | B96: 1405/07/15 | C96: 1 | D96: دریا کریمی | E96: pm | F96: کارت | G96: بازگشتی | H96: کانال | J96: کت جین مشکی | K96: کت جین مشکی | L96: 1 | M96: 4850000 | N96: 0 | O96: 4850000 | Q96: علیخانی | R96: 9183369136 | S96: 23 | T96: 9 | U96: آپ سل 20میلیونی | V96: =IF(A96="",0,IF(COUNTIF($A$3:A96,A96)=1,1,0)) -> 1 | W96: =IF(A96="",0,L96*M96) -> 4850000 | X96: =IF(R96<>"",R96,IF(AND(P96<>"",Q96<>""),P96&"|"&Q96,"")) -> 9183369136 | Y96: =IF(X96="",0,IF(COUNTIF($X$3:X96,X96)=1,1,0)) -> 1 | Z96: =IF(V96<>1,0,IF(X96="",0,IF(COUNTIF($X$3:X95,X96)>0,1,0))) -> 0 | AA96: =IF(V96=1,SUMIF($A$3:$A$1622,A96,$O$3:$O$1622),0) -> 23070000 | AB96: =IF(V96=1,SUMIF($A$3:$A$1622,A96,$L$3:$L$1622),0) -> 5 | AC96: =IF(I96="",0,L96*IFERROR(INDEX(کاتالوگ_محصولات!$G$4:$G$303,MATCH(I96,کاتالوگ_محصولات!$A$4:$A$303,0)),0)) -> 0 | AD96: =IF(A96="",0,O96-AC96) -> 4850000 | AE96: =IF(B96="","",LEFT(B96,7)) -> 1405/07
A97: INV-0252 | B97: 1405/07/15 | C97: 1 | D97: دریا کریمی | E97: pm | F97: کارت | G97: بازگشتی | H97: کانال | J97: کت پیوند | K97: کت پیوند | L97: 1 | M97: 4200000 | N97: 0 | O97: 4200000 | Q97: علیخانی | R97: 9183369136 | S97: 23 | T97: 9 | V97: =IF(A97="",0,IF(COUNTIF($A$3:A97,A97)=1,1,0)) -> 0 | W97: =IF(A97="",0,L97*M97) -> 4200000 | X97: =IF(R97<>"",R97,IF(AND(P97<>"",Q97<>""),P97&"|"&Q97,"")) -> 9183369136 | Y97: =IF(X97="",0,IF(COUNTIF($X$3:X97,X97)=1,1,0)) -> 0 | Z97: =IF(V97<>1,0,IF(X97="",0,IF(COUNTIF($X$3:X96,X97)>0,1,0))) -> 0 | AA97: =IF(V97=1,SUMIF($A$3:$A$1622,A97,$O$3:$O$1622),0) -> 0 | AB97: =IF(V97=1,SUMIF($A$3:$A$1622,A97,$L$3:$L$1622),0) -> 0 | AC97: =IF(I97="",0,L97*IFERROR(INDEX(کاتالوگ_محصولات!$G$4:$G$303,MATCH(I97,کاتالوگ_محصولات!$A$4:$A$303,0)),0)) -> 0 | AD97: =IF(A97="",0,O97-AC97) -> 4200000 | AE97: =IF(B97="","",LEFT(B97,7)) -> 1405/07
A98: INV-0252 | B98: 1405/07/15 | C98: 1 | D98: دریا کریمی | E98: pm | F98: کارت | G98: بازگشتی | H98: کانال | J98: دامن جین مشکی | K98: دامن جین مشکی | L98: 1 | M98: 4280000 | N98: 0 | O98: 4280000 | Q98: علیخانی | R98: 9183369136 | S98: 23 | T98: 9 | V98: =IF(A98="",0,IF(COUNTIF($A$3:A98,A98)=1,1,0)) -> 0 | W98: =IF(A98="",0,L98*M98) -> 4280000 | X98: =IF(R98<>"",R98,IF(AND(P98<>"",Q98<>""),P98&"|"&Q98,"")) -> 9183369136 | Y98: =IF(X98="",0,IF(COUNTIF($X$3:X98,X98)=1,1,0)) -> 0 | Z98: =IF(V98<>1,0,IF(X98="",0,IF(COUNTIF($X$3:X97,X98)>0,1,0))) -> 0 | AA98: =IF(V98=1,SUMIF($A$3:$A$1622,A98,$O$3:$O$1622),0) -> 0 | AB98: =IF(V98=1,SUMIF($A$3:$A$1622,A98,$L$3:$L$1622),0) -> 0 | AC98: =IF(I98="",0,L98*IFERROR(INDEX(کاتالوگ_محصولات!$G$4:$G$303,MATCH(I98,کاتالوگ_محصولات!$A$4:$A$303,0)),0)) -> 0 | AD98: =IF(A98="",0,O98-AC98) -> 4280000 | AE98: =IF(B98="","",LEFT(B98,7)) -> 1405/07
A99: INV-0252 | B99: 1405/07/15 | C99: 1 | D99: دریا کریمی | E99: pm | F99: کارت | G99: بازگشتی | H99: کانال | J99: شومیز لینن سونای سفید1 | K99: شومیز لینن سونای سفید1 | L99: 1 | M99: 3780000 | N99: 0 | O99: 3780000 | Q99: علیخانی | R99: 9183369136 | S99: 23 | T99: 9 | V99: =IF(A99="",0,IF(COUNTIF($A$3:A99,A99)=1,1,0)) -> 0 | W99: =IF(A99="",0,L99*M99) -> 3780000 | X99: =IF(R99<>"",R99,IF(AND(P99<>"",Q99<>""),P99&"|"&Q99,"")) -> 9183369136 | Y99: =IF(X99="",0,IF(COUNTIF($X$3:X99,X99)=1,1,0)) -> 0 | Z99: =IF(V99<>1,0,IF(X99="",0,IF(COUNTIF($X$3:X98,X99)>0,1,0))) -> 0 | AA99: =IF(V99=1,SUMIF($A$3:$A$1622,A99,$O$3:$O$1622),0) -> 0 | AB99: =IF(V99=1,SUMIF($A$3:$A$1622,A99,$L$3:$L$1622),0) -> 0 | AC99: =IF(I99="",0,L99*IFERROR(INDEX(کاتالوگ_محصولات!$G$4:$G$303,MATCH(I99,کاتالوگ_محصولات!$A$4:$A$303,0)),0)) -> 0 | AD99: =IF(A99="",0,O99-AC99) -> 3780000 | AE99: =IF(B99="","",LEFT(B99,7)) -> 1405/07
A100: INV-0252 | B100: 1405/07/15 | C100: 1 | D100: دریا کریمی | E100: pm | F100: کارت | G100: بازگشتی | H100: کانال | J100: بامبر سلین سرمه ای | K100: بامبر سلین سرمه ای | L100: 1 | M100: 6780000 | N100: 820000 | O100: 5960000 | Q100: علیخانی | R100: 9183369136 | S100: 23 | T100: 9 | V100: =IF(A100="",0,IF(COUNTIF($A$3:A100,A100)=1,1,0)) -> 0 | W100: =IF(A100="",0,L100*M100) -> 6780000 | X100: =IF(R100<>"",R100,IF(AND(P100<>"",Q100<>""),P100&"|"&Q100,"")) -> 9183369136 | Y100: =IF(X100="",0,IF(COUNTIF($X$3:X100,X100)=1,1,0)) -> 0 | Z100: =IF(V100<>1,0,IF(X100="",0,IF(COUNTIF($X$3:X99,X100)>0,1,0))) -> 0 | AA100: =IF(V100=1,SUMIF($A$3:$A$1622,A100,$O$3:$O$1622),0) -> 0 | AB100: =IF(V100=1,SUMIF($A$3:$A$1622,A100,$L$3:$L$1622),0) -> 0 | AC100: =IF(I100="",0,L100*IFERROR(INDEX(کاتالوگ_محصولات!$G$4:$G$303,MATCH(I100,کاتالوگ_محصولات!$A$4:$A$303,0)),0)) -> 0 | AD100: =IF(A100="",0,O100-AC100) -> 5960000 | AE100: =IF(B100="","",LEFT(B100,7)) -> 1405/07
...

Sheet کاتالوگ_محصولات
A2: کاتالوگ محصولات
A3: SKU (خودکار) | B3: بارکد/شناسه Barcode | C3: نام محصول Product_Name | D3: دسته‌بندی Category | E3: پارچه Fabric | F3: فصل Season | G3: قیمت خرید Cost | H3: قیمت فروش Price | I3: موجودی اولیه Open_Stock | J3: فروخته شده Sold | K3: موجودی فعلی Curr_Stock | L3: وضعیت Status
A4: =IF(C4="","","SKU-"&TEXT(ROW()-3,"0000")) -> SKU-0001 | B4: CHSHLSNDCR2 | C4: شلوار لینن سندبادی کرم سایز1 | D4: شلوار | E4: Linen | F4: Spring/Summer | H4: 3490000 | I4: 9 | J4: =IFERROR(SUMIF(لاگ_فاکتور!$I$3:$I$1622,A4,لاگ_فاکتور!$L$3:$L$1622),0) -> 0 | K4: =MAX(0,I4-J4) -> 9 | L4: =IF(C4="","",IF(K4<=0,"🔴 تمام",IF(K4<=تنظیمات_سیستم!$C$7,"🟠 کم","🟢 OK"))) -> 🟢 OK
A5: =IF(C5="","","SKU-"&TEXT(ROW()-3,"0000")) -> SKU-0002 | B5: CHSHLSNDCR1 | C5: شلوار لینن سندبادی کرم سایز2 | D5: شلوار | E5: Linen | F5: Spring/Summer | H5: 3490000 | I5: 9 | J5: =IFERROR(SUMIF(لاگ_فاکتور!$I$3:$I$1622,A5,لاگ_فاکتور!$L$3:$L$1622),0) -> 0 | K5: =MAX(0,I5-J5) -> 9 | L5: =IF(C5="","",IF(K5<=0,"🔴 تمام",IF(K5<=تنظیمات_سیستم!$C$7,"🟠 کم","🟢 OK"))) -> 🟢 OK
A6: =IF(C6="","","SKU-"&TEXT(ROW()-3,"0000")) -> SKU-0003 | B6: CHSHLSNDBK1 | C6: شلوار لینن سندبادی مشکی سایز1 | D6: شلوار | E6: Linen | F6: Spring/Summer | H6: 3490000 | I6: 9 | J6: =IFERROR(SUMIF(لاگ_فاکتور!$I$3:$I$1622,A6,لاگ_فاکتور!$L$3:$L$1622),0) -> 0 | K6: =MAX(0,I6-J6) -> 9 | L6: =IF(C6="","",IF(K6<=0,"🔴 تمام",IF(K6<=تنظیمات_سیستم!$C$7,"🟠 کم","🟢 OK"))) -> 🟢 OK
A7: =IF(C7="","","SKU-"&TEXT(ROW()-3,"0000")) -> SKU-0004 | B7: CHSHLSNDBK2 | C7: شلوار لینن سندبادی مشکی سایز2 | D7: شلوار | E7: Linen | F7: Spring/Summer | H7: 3490000 | I7: 9 | J7: =IFERROR(SUMIF(لاگ_فاکتور!$I$3:$I$1622,A7,لاگ_فاکتور!$L$3:$L$1622),0) -> 0 | K7: =MAX(0,I7-J7) -> 9 | L7: =IF(C7="","",IF(K7<=0,"🔴 تمام",IF(K7<=تنظیمات_سیستم!$C$7,"🟠 کم","🟢 OK"))) -> 🟢 OK
A8: =IF(C8="","","SKU-"&TEXT(ROW()-3,"0000")) -> SKU-0005 | B8: CHSHLSNDBR1 | C8: شلوار لینن سندبادی قهوه ای سایز1 | D8: شلوار | E8: Linen | F8: Spring/Summer | H8: 3490000 | I8: 9 | J8: =IFERROR(SUMIF(لاگ_فاکتور!$I$3:$I$1622,A8,لاگ_فاکتور!$L$3:$L$1622),0) -> 0 | K8: =MAX(0,I8-J8) -> 9 | L8: =IF(C8="","",IF(K8<=0,"🔴 تمام",IF(K8<=تنظیمات_سیستم!$C$7,"🟠 کم","🟢 OK"))) -> 🟢 OK
A9: =IF(C9="","","SKU-"&TEXT(ROW()-3,"0000")) -> SKU-0006 | B9: CHSHLSNDBR2 | C9: شلوار لینن سندبادی قهوه ای سایز2 | D9: شلوار | E9: Linen | F9: Spring/Summer | H9: 3490000 | I9: 9 | J9: =IFERROR(SUMIF(لاگ_فاکتور!$I$3:$I$1622,A9,لاگ_فاکتور!$L$3:$L$1622),0) -> 0 | K9: =MAX(0,I9-J9) -> 9 | L9: =IF(C9="","",IF(K9<=0,"🔴 تمام",IF(K9<=تنظیمات_سیستم!$C$7,"🟠 کم","🟢 OK"))) -> 🟢 OK
A10: =IF(C10="","","SKU-"&TEXT(ROW()-3,"0000")) -> SKU-0007 | B10: CHSHLSNDMU1 | C10: شلوار لینن سندبادی سرمه ای سایز1 | D10: شلوار | E10: Linen | F10: Spring/Summer | H10: 3490000 | I10: 9 | J10: =IFERROR(SUMIF(لاگ_فاکتور!$I$3:$I$1622,A10,لاگ_فاکتور!$L$3:$L$1622),0) -> 0 | K10: =MAX(0,I10-J10) -> 9 | L10: =IF(C10="","",IF(K10<=0,"🔴 تمام",IF(K10<=تنظیمات_سیستم!$C$7,"🟠 کم","🟢 OK"))) -> 🟢 OK
A11: =IF(C11="","","SKU-"&TEXT(ROW()-3,"0000")) -> SKU-0008 | B11: CHSHLSNDMU2 | C11: شلوار لینن سندبادی سرمه ای سایز2 | D11: شلوار | E11: Linen | F11: Spring/Summer | H11: 3490000 | I11: 9 | J11: =IFERROR(SUMIF(لاگ_فاکتور!$I$3:$I$1622,A11,لاگ_فاکتور!$L$3:$L$1622),0) -> 0 | K11: =MAX(0,I11-J11) -> 9 | L11: =IF(C11="","",IF(K11<=0,"🔴 تمام",IF(K11<=تنظیمات_سیستم!$C$7,"🟠 کم","🟢 OK"))) -> 🟢 OK
A12: =IF(C12="","","SKU-"&TEXT(ROW()-3,"0000")) -> SKU-0009 | B12: CHSMSYHWH1 | C12: شومیز سایه سفید سایز1 | D12: شومیز | E12: Cotton | F12: All-Season | H12: 2480000 | I12: 9 | J12: =IFERROR(SUMIF(لاگ_فاکتور!$I$3:$I$1622,A12,لاگ_فاکتور!$L$3:$L$1622),0) -> 0 | K12: =MAX(0,I12-J12) -> 9 | L12: =IF(C12="","",IF(K12<=0,"🔴 تمام",IF(K12<=تنظیمات_سیستم!$C$7,"🟠 کم","🟢 OK"))) -> 🟢 OK
A13: =IF(C13="","","SKU-"&TEXT(ROW()-3,"0000")) -> SKU-0010 | C13: شومیز سایه سفید سایز2 | D13: شومیز | E13: Cotton | F13: All-Season | H13: 2480000 | I13: 9 | J13: =IFERROR(SUMIF(لاگ_فاکتور!$I$3:$I$1622,A13,لاگ_فاکتور!$L$3:$L$1622),0) -> 0 | K13: =MAX(0,I13-J13) -> 9 | L13: =IF(C13="","",IF(K13<=0,"🔴 تمام",IF(K13<=تنظیمات_سیستم!$C$7,"🟠 کم","🟢 OK"))) -> 🟢 OK
A14: =IF(C14="","","SKU-"&TEXT(ROW()-3,"0000")) -> SKU-0011 | B14: CHSMSYHBK1 | C14: شومیز سایه مشکی سایز1 | D14: شومیز | E14: Cotton | F14: All-Season | H14: 2480000 | I14: 9 | J14: =IFERROR(SUMIF(لاگ_فاکتور!$I$3:$I$1622,A14,لاگ_فاکتور!$L$3:$L$1622),0) -> 0 | K14: =MAX(0,I14-J14) -> 9 | L14: =IF(C14="","",IF(K14<=0,"🔴 تمام",IF(K14<=تنظیمات_سیستم!$C$7,"🟠 کم","🟢 OK"))) -> 🟢 OK
A15: =IF(C15="","","SKU-"&TEXT(ROW()-3,"0000")) -> SKU-0012 | B15: CHSMSYHBK2 | C15: شومیز سایه مشکی سایز2 | D15: شومیز | E15: Cotton | F15: All-Season | H15: 2480000 | I15: 9 | J15: =IFERROR(SUMIF(لاگ_فاکتور!$I$3:$I$1622,A15,لاگ_فاکتور!$L$3:$L$1622),0) -> 0 | K15: =MAX(0,I15-J15) -> 9 | L15: =IF(C15="","",IF(K15<=0,"🔴 تمام",IF(K15<=تنظیمات_سیستم!$C$7,"🟠 کم","🟢 OK"))) -> 🟢 OK
A16: =IF(C16="","","SKU-"&TEXT(ROW()-3,"0000")) -> SKU-0013 | B16: CHSMSYHWH2 | C16: شومیز سایه طوسی سایز1 | D16: شومیز | E16: Cotton | F16: All-Season | H16: 2480000 | I16: 9 | J16: =IFERROR(SUMIF(لاگ_فاکتور!$I$3:$I$1622,A16,لاگ_فاکتور!$L$3:$L$1622),0) -> 0 | K16: =MAX(0,I16-J16) -> 9 | L16: =IF(C16="","",IF(K16<=0,"🔴 تمام",IF(K16<=تنظیمات_سیستم!$C$7,"🟠 کم","🟢 OK"))) -> 🟢 OK
A17: =IF(C17="","","SKU-"&TEXT(ROW()-3,"0000")) -> SKU-0014 | B17: CHSMSYHBK2 | C17: شومیز سایه طوسی سایز2 | D17: شومیز | E17: Cotton | F17: All-Season | H17: 2480000 | I17: 9 | J17: =IFERROR(SUMIF(لاگ_فاکتور!$I$3:$I$1622,A17,لاگ_فاکتور!$L$3:$L$1622),0) -> 0 | K17: =MAX(0,I17-J17) -> 9 | L17: =IF(C17="","",IF(K17<=0,"🔴 تمام",IF(K17<=تنظیمات_سیستم!$C$7,"🟠 کم","🟢 OK"))) -> 🟢 OK
A18: =IF(C18="","","SKU-"&TEXT(ROW()-3,"0000")) -> SKU-0015 | B18: CHSMSYHGR1 | C18: شومیز سایه زرد سایز1 | D18: شومیز | E18: Cotton | F18: All-Season | H18: 2480000 | I18: 9 | J18: =IFERROR(SUMIF(لاگ_فاکتور!$I$3:$I$1622,A18,لاگ_فاکتور!$L$3:$L$1622),0) -> 0 | K18: =MAX(0,I18-J18) -> 9 | L18: =IF(C18="","",IF(K18<=0,"🔴 تمام",IF(K18<=تنظیمات_سیستم!$C$7,"🟠 کم","🟢 OK"))) -> 🟢 OK
A19: =IF(C19="","","SKU-"&TEXT(ROW()-3,"0000")) -> SKU-0016 | B19: CHSMSYHGR2 | C19: شومیز سایه زرد سایز2 | D19: شومیز | E19: Cotton | F19: All-Season | H19: 900000 | I19: 9 | J19: =IFERROR(SUMIF(لاگ_فاکتور!$I$3:$I$1622,A19,لاگ_فاکتور!$L$3:$L$1622),0) -> 0 | K19: =MAX(0,I19-J19) -> 9 | L19: =IF(C19="","",IF(K19<=0,"🔴 تمام",IF(K19<=تنظیمات_سیستم!$C$7,"🟠 کم","🟢 OK"))) -> 🟢 OK
A20: =IF(C20="","","SKU-"&TEXT(ROW()-3,"0000")) -> SKU-0017 | B20: CHSMSYHYL1 | C20: شومیز سایه خالدار سفیدزرد سایز1 | D20: شومیز | E20: Cotton | F20: All-Season | H20: 900000 | I20: 9 | J20: =IFERROR(SUMIF(لاگ_فاکتور!$I$3:$I$1622,A20,لاگ_فاکتور!$L$3:$L$1622),0) -> 0 | K20: =MAX(0,I20-J20) -> 9 | L20: =IF(C20="","",IF(K20<=0,"🔴 تمام",IF(K20<=تنظیمات_سیستم!$C$7,"🟠 کم","🟢 OK"))) -> 🟢 OK
A21: =IF(C21="","","SKU-"&TEXT(ROW()-3,"0000")) -> SKU-0018 | B21: CHSMSYHYL2 | C21: شومیز سایه خالدار سفیدزرد سایز2 | D21: شومیز | E21: Cotton | F21: All-Season | H21: 900000 | I21: 9 | J21: =IFERROR(SUMIF(لاگ_فاکتور!$I$3:$I$1622,A21,لاگ_فاکتور!$L$3:$L$1622),0) -> 0 | K21: =MAX(0,I21-J21) -> 9 | L21: =IF(C21="","",IF(K21<=0,"🔴 تمام",IF(K21<=تنظیمات_سیستم!$C$7,"🟠 کم","🟢 OK"))) -> 🟢 OK
A22: =IF(C22="","","SKU-"&TEXT(ROW()-3,"0000")) -> SKU-0019 | B22: CHSMSYHPT1 | C22: شومیز گیپور زرد فری | D22: شومیز | E22: Cotton | F22: Spring/Summer | H22: 1080000 | I22: 9 | J22: =IFERROR(SUMIF(لاگ_فاکتور!$I$3:$I$1622,A22,لاگ_فاکتور!$L$3:$L$1622),0) -> 0 | K22: =MAX(0,I22-J22) -> 9 | L22: =IF(C22="","",IF(K22<=0,"🔴 تمام",IF(K22<=تنظیمات_سیستم!$C$7,"🟠 کم","🟢 OK"))) -> 🟢 OK
A23: =IF(C23="","","SKU-"&TEXT(ROW()-3,"0000")) -> SKU-0020 | B23: CHSMSYHPT2 | C23: شومیز گیپور طوسی فری | D23: شومیز | E23: Cotton | F23: Spring/Summer | H23: 1080000 | I23: 9 | J23: =IFERROR(SUMIF(لاگ_فاکتور!$I$3:$I$1622,A23,لاگ_فاکتور!$L$3:$L$1622),0) -> 0 | K23: =MAX(0,I23-J23) -> 9 | L23: =IF(C23="","",IF(K23<=0,"🔴 تمام",IF(K23<=تنظیمات_سیستم!$C$7,"🟠 کم","🟢 OK"))) -> 🟢 OK
A24: =IF(C24="","","SKU-"&TEXT(ROW()-3,"0000")) -> SKU-0021 | B24: CHSMGPRYLFR | C24: شومیز گیپور آبی فری | D24: شومیز | E24: Cotton | F24: Spring/Summer | H24: 1080000 | I24: 9 | J24: =IFERROR(SUMIF(لاگ_فاکتور!$I$3:$I$1622,A24,لاگ_فاکتور!$L$3:$L$1622),0) -> 0 | K24: =MAX(0,I24-J24) -> 9 | L24: =IF(C24="","",IF(K24<=0,"🔴 تمام",IF(K24<=تنظیمات_سیستم!$C$7,"🟠 کم","🟢 OK"))) -> 🟢 OK
A25: =IF(C25="","","SKU-"&TEXT(ROW()-3,"0000")) -> SKU-0022 | B25: CHSMGPRGRFR | C25: شومیز گیپور صورتی فری | D25: شومیز | E25: Cotton | F25: Spring/Summer | H25: 1080000 | I25: 9 | J25: =IFERROR(SUMIF(لاگ_فاکتور!$I$3:$I$1622,A25,لاگ_فاکتور!$L$3:$L$1622),0) -> 0 | K25: =MAX(0,I25-J25) -> 9 | L25: =IF(C25="","",IF(K25<=0,"🔴 تمام",IF(K25<=تنظیمات_سیستم!$C$7,"🟠 کم","🟢 OK"))) -> 🟢 OK
... A86: =IF(C86="","","SKU-"&TEXT(ROW()-3,"0000")) -> SKU-0083 | B86: CHSHKTRMU3 | C86: شلوار کاترین نسکافه ای3 | D86: شلوار | E86: Crepe | F86: All-Season | H86: 4580000 | I86: 9 | J86: =IFERROR(SUMIF(لاگ_فاکتور!$I$3:$I$1622,A86,لاگ_فاکتور!$L$3:$L$1622),0) -> 0 | K86: =MAX(0,I86-J86) -> 9 | L86: =IF(C86="","",IF(K86<=0,"🔴 تمام",IF(K86<=تنظیمات_سیستم!$C$7,"🟠 کم","🟢 OK"))) -> 🟢 OK
A87: =IF(C87="","","SKU-"&TEXT(ROW()-3,"0000")) -> SKU-0084 | C87: شلوار کاترین نوک مدادی 1 | D87: شلوار | E87: Crepe | F87: All-Season | H87: 4580000 | I87: 9 | J87: =IFERROR(SUMIF(لاگ_فاکتور!$I$3:$I$1622,A87,لاگ_فاکتور!$L$3:$L$1622),0) -> 0 | K87: =MAX(0,I87-J87) -> 9 | L87: =IF(C87="","",IF(K87<=0,"🔴 تمام",IF(K87<=تنظیمات_سیستم!$C$7,"🟠 کم","🟢 OK"))) -> 🟢 OK
A88: =IF(C88="","","SKU-"&TEXT(ROW()-3,"0000")) -> SKU-0085 | B88: CHSHKTRCH3 | C88: شلوار کاترین نوک مدادی 2 | D88: شلوار | E88: Crepe | F88: All-Season | H88: 4580000 | I88: 9 | J88: =IFERROR(SUMIF(لاگ_فاکتور!$I$3:$I$1622,A88,لاگ_فاکتور!$L$3:$L$1622),0) -> 0 | K88: =MAX(0,I88-J88) -> 9 | L88: =IF(C88="","",IF(K88<=0,"🔴 تمام",IF(K88<=تنظیمات_سیستم!$C$7,"🟠 کم","🟢 OK"))) -> 🟢 OK
A89: =IF(C89="","","SKU-"&TEXT(ROW()-3,"0000")) -> SKU-0086 | B89: CHSHKTRIV1 | C89: شلوار کاترین نوک مدادی3 | D89: شلوار | E89: Crepe | F89: All-Season | H89: 4580000 | I89: 9 | J89: =IFERROR(SUMIF(لاگ_فاکتور!$I$3:$I$1622,A89,لاگ_فاکتور!$L$3:$L$1622),0) -> 0 | K89: =MAX(0,I89-J89) -> 9 | L89: =IF(C89="","",IF(K89<=0,"🔴 تمام",IF(K89<=تنظیمات_سیستم!$C$7,"🟠 کم","🟢 OK"))) -> 🟢 OK
A90: =IF(C90="","","SKU-"&TEXT(ROW()-3,"0000")) -> SKU-0087 | B90: CHSHKTRCH1 | C90: شلوار کاترین استخوانی 1 | D90: شلوار | E90: Crepe | F90: All-Season | H90: 4580000 | I90: 9 | J90: =IFERROR(SUMIF(لاگ_فاکتور!$I$3:$I$1622,A90,لاگ_فاکتور!$L$3:$L$1622),0) -> 0 | K90: =MAX(0,I90-J90) -> 9 | L90: =IF(C90="","",IF(K90<=0,"🔴 تمام",IF(K90<=تنظیمات_سیستم!$C$7,"🟠 کم","🟢 OK"))) -> 🟢 OK
A91: =IF(C91="","","SKU-"&TEXT(ROW()-3,"0000")) -> SKU-0088 | B91: CHSHKTRCH2 | C91: شلوار کاترین استخوانی2 | D91: شلوار | E91: Crepe | F91: All-Season | H91: 4580000 | I91: 9 | J91: =IFERROR(SUMIF(لاگ_فاکتور!$I$3:$I$1622,A91,لاگ_فاکتور!$L$3:$L$1622),0) -> 0 | K91: =MAX(0,I91-J91) -> 9 | L91: =IF(C91="","",IF(K91<=0,"🔴 تمام",IF(K91<=تنظیمات_سیستم!$C$7,"🟠 کم","🟢 OK"))) -> 🟢 OK
A92: =IF(C92="","","SKU-"&TEXT(ROW()-3,"0000")) -> SKU-0089 | B92: CHSHKTRCO2 | C92: شلوار کاترین استخوانی3 | D92: شلوار | E92: Crepe | F92: All-Season | H92: 4580000 | I92: 9 | J92: =IFERROR(SUMIF(لاگ_فاکتور!$I$3:$I$1622,A92,لاگ_فاکتور!$L$3:$L$1622),0) -> 0 | K92: =MAX(0,I92-J92) -> 9 | L92: =IF(C92="","",IF(K92<=0,"🔴 تمام",IF(K92<=تنظیمات_سیستم!$C$7,"🟠 کم","🟢 OK"))) -> 🟢 OK
A93: =IF(C93="","","SKU-"&TEXT(ROW()-3,"0000")) -> SKU-0090 | B93: CHSHKTRBK2 | C93: شومیز تایملس سبز فری | D93: شومیز | E93: Silk | F93: All-Season | H93: 2680000 | I93: 9 | J93: =IFERROR(SUMIF(لاگ_فاکتور!$I$3:$I$1622,A93,لاگ_فاکتور!$L$3:$L$1622),0) -> 0 | K93: =MAX(0,I93-J93) -> 9 | L93: =IF(C93="","",IF(K93<=0,"🔴 تمام",IF(K93<=تنظیمات_سیستم!$C$7,"🟠 کم","🟢 OK"))) -> 🟢 OK
A94: =IF(C94="","","SKU-"&TEXT(ROW()-3,"0000")) -> SKU-0091 | B94: CHSMLIVWH1 | C94: شومیز تایملس مشکی فری | D94: شومیز | E94: Silk | F94: All-Season | H94: 2680000 | I94: 9 | J94: =IFERROR(SUMIF(لاگ_فاکتور!$I$3:$I$1622,A94,لاگ_فاکتور!$L$3:$L$1622),0) -> 0 | K94: =MAX(0,I94-J94) -> 9 | L94: =IF(C94="","",IF(K94<=0,"🔴 تمام",IF(K94<=تنظیمات_سیستم!$C$7,"🟠 کم","🟢 OK"))) -> 🟢 OK
A95: =IF(C95="","","SKU-"&TEXT(ROW()-3,"0000")) -> SKU-0092 | B95: CHSMDRYBK1 | C95: شومیز لینن سونای سفید1 | D95: شومیز | E95: linen | F95: Spring/Summer | H95: 3780000 | I95: 9 | J95: =IFERROR(SUMIF(لاگ_فاکتور!$I$3:$I$1622,A95,لاگ_فاکتور!$L$3:$L$1622),0) -> 0 | K95: =MAX(0,I95-J95) -> 9 | L95: =IF(C95="","",IF(K95<=0,"🔴 تمام",IF(K95<=تنظیمات_سیستم!$C$7,"🟠 کم","🟢 OK"))) -> 🟢 OK
A96: =IF(C96="","","SKU-"&TEXT(ROW()-3,"0000")) -> SKU-0093 | B96: CHSMDRYBK2 | C96: شومیز لینن سونای سفید2 | D96: شومیز | E96: linen | F96: Spring/Summer | H96: 3780000 | I96: 9 | J96: =IFERROR(SUMIF(لاگ_فاکتور!$I$3:$I$1622,A96,لاگ_فاکتور!$L$3:$L$1622),0) -> 0 | K96: =MAX(0,I96-J96) -> 9 | L96: =IF(C96="","",IF(K96<=0,"🔴 تمام",IF(K96<=تنظیمات_سیستم!$C$7,"🟠 کم","🟢 OK"))) -> 🟢 OK
A97: =IF(C97="","","SKU-"&TEXT(ROW()-3,"0000")) -> SKU-0094 | B97: CHSMDRYCR1 | C97: شومیز لینن سونای مشکی 1 | D97: شومیز | E97: linen | F97: Spring/Summer | H97: 3780000 | I97: 9 | J97: =IFERROR(SUMIF(لاگ_فاکتور!$I$3:$I$1622,A97,لاگ_فاکتور!$L$3:$L$1622),0) -> 0 | K97: =MAX(0,I97-J97) -> 9 | L97: =IF(C97="","",IF(K97<=0,"🔴 تمام",IF(K97<=تنظیمات_سیستم!$C$7,"🟠 کم","🟢 OK"))) -> 🟢 OK
A98: =IF(C98="","","SKU-"&TEXT(ROW()-3,"0000")) -> SKU-0095 | B98: CHSMDRYCR2 | C98: شومیز لینن سونای مشکی2 | D98: شومیز | E98: linen | F98: Spring/Summer | H98: 3780000 | I98: 9 | J98: =IFERROR(SUMIF(لاگ_فاکتور!$I$3:$I$1622,A98,لاگ_فاکتور!$L$3:$L$1622),0) -> 0 | K98: =MAX(0,I98-J98) -> 9 | L98: =IF(C98="","",IF(K98<=0,"🔴 تمام",IF(K98<=تنظیمات_سیستم!$C$7,"🟠 کم","🟢 OK"))) -> 🟢 OK
A99: =IF(C99="","","SKU-"&TEXT(ROW()-3,"0000")) -> SKU-0096 | B99: CHSMDRYCT1 | C99: شومیز لینن سونای سرمه ای 1 | D99: شومیز | E99: linen | F99: Spring/Summer | H99: 3780000 | I99: 9 | J99: =IFERROR(SUMIF(لاگ_فاکتور!$I$3:$I$1622,A99,لاگ_فاکتور!$L$3:$L$1622),0) -> 0 | K99: =MAX(0,I99-J99) -> 9 | L99: =IF(C99="","",IF(K99<=0,"🔴 تمام",IF(K99<=تنظیمات_سیستم!$C$7,"🟠 کم","🟢 OK"))) -> 🟢 OK
... A109: =IF(C109="","","SKU-"&TEXT(ROW()-3,"0000")) -> SKU-0106 | B109: CHSMLSNWH2 | C109: شلوار پنتر 2 | D109: شلوار | E109: Crepe | F109: Spring/Summer | H109: 1680000 | I109: 9 | J109: =IFERROR(SUMIF(لاگ_فاکتور!$I$3:$I$1622,A109,لاگ_فاکتور!$L$3:$L$1622),0) -> 0 | K109: =MAX(0,I109-J109) -> 9 | L109: =IF(C109="","",IF(K109<=0,"🔴 تمام",IF(K109<=تنظیمات_سیستم!$C$7,"🟠 کم","🟢 OK"))) -> 🟢 OK
A110: =IF(C110="","","SKU-"&TEXT(ROW()-3,"0000")) -> SKU-0107 | B110: CHSHPNY--2 | C110: شلوار مانا کله غازی1 | D110: شلوار | E110: Linen | F110: Spring/Summer | I110: 9 | J110: =IFERROR(SUMIF(لاگ_فاکتور!$I$3:$I$1622,A110,لاگ_فاکتور!$L$3:$L$1622),0) -> 0 | K110: =MAX(0,I110-J110) -> 9 | L110: =IF(C110="","",IF(K110<=0,"🔴 تمام",IF(K110<=تنظیمات_سیستم!$C$7,"🟠 کم","🟢 OK"))) -> 🟢 OK
A111: =IF(C111="","","SKU-"&TEXT(ROW()-3,"0000")) -> SKU-0108 | B111: CHSHMKLKH1 | C111: شلوار مانا کله غازی2 | D111: شلوار | E111: Linen | F111: Spring/Summer | H111: 1680000 | I111: 9 | J111: =IFERROR(SUMIF(لاگ_فاکتور!$I$3:$I$1622,A111,لاگ_فاکتور!$L$3:$L$1622),0) -> 0 | K111: =MAX(0,I111-J111) -> 9 | L111: =IF(C111="","",IF(K111<=0,"🔴 تمام",IF(K111<=تنظیمات_سیستم!$C$7,"🟠 کم","🟢 OK"))) -> 🟢 OK
A112: =IF(C112="","","SKU-"&TEXT(ROW()-3,"0000")) -> SKU-0109 | B112: CHSHMKLKH2 | C112: شلوار مانا زیتونی 1 | D112: شلوار | E112: Linen | F112: Spring/Summer | I112: 9 | J112: =IFERROR(SUMIF(لاگ_فاکتور!$I$3:$I$1622,A112,لاگ_فاکتور!$L$3:$L$1622),0) -> 0 | K112: =MAX(0,I112-J112) -> 9 | L112: =IF(C112="","",IF(K112<=0,"🔴 تمام",IF(K112<=تنظیمات_سیستم!$C$7,"🟠 کم","🟢 OK"))) -> 🟢 OK
A113: =IF(C113="","","SKU-"&TEXT(ROW()-3,"0000")) -> SKU-0110 | B113: CHSHMNAOL1 | C113: شلوار مانا زیتونی2 | D113: شلوار | E113: Linen | F113: Spring/Summer | I113: 9 | J113: =IFERROR(SUMIF(لاگ_فاکتور!$I$3:$I$1622,A113,لاگ_فاکتور!$L$3:$L$1622),0) -> 0 | K113: =MAX(0,I113-J113) -> 9 | L113: =IF(C113="","",IF(K113<=0,"🔴 تمام",IF(K113<=تنظیمات_سیستم!$C$7,"🟠 کم","🟢 OK"))) -> 🟢 OK
A114: =IF(C114="","","SKU-"&TEXT(ROW()-3,"0000")) -> SKU-0111 | B114: CHSMLSNBK1 | C114: شلوار بیسیک سفید1 | D114: شلوار | E114: Crepe | F114: All-Season | H114: 2380000 | I114: 9 | J114: =IFERROR(SUMIF(لاگ_فاکتور!$I$3:$I$1622,A114,لاگ_فاکتور!$L$3:$L$1622),0) -> 0 | K114: =MAX(0,I114-J114) -> 9 | L114: =IF(C114="","",IF(K114<=0,"🔴 تمام",IF(K114<=تنظیمات_سیستم!$C$7,"🟠 کم","🟢 OK"))) -> 🟢 OK
A115: =IF(C115="","","SKU-"&TEXT(ROW()-3,"0000")) -> SKU-0112 | B115: CHSMLSNBK2 | C115: شلوار بیسیک سفید2 | D115: شلوار | E115: Crepe | F115: All-Season | H115: 1440000 | I115: 9 | J115: =IFERROR(SUMIF(لاگ_فاکتور!$I$3:$I$1622,A115,لاگ_فاکتور!$L$3:$L$1622),0) -> 0 | K115: =MAX(0,I115-J115) -> 9 | L115: =IF(C115="","",IF(K115<=0,"🔴 تمام",IF(K115<=تنظیمات_سیستم!$C$7,"🟠 کم","🟢 OK"))) -> 🟢 OK
A116: =IF(C116="","","SKU-"&TEXT(ROW()-3,"0000")) -> SKU-0113 | B116: CHSMLSNMU1 | C116: شلوار بیسیک مشکی1 | D116: شلوار | E116: Crepe | F116: All-Season | H116: 1440000 | I116: 9 | J116: =IFERROR(SUMIF(لاگ_فاکتور!$I$3:$I$1622,A116,لاگ_فاکتور!$L$3:$L$1622),0) -> 0 | K116: =MAX(0,I116-J116) -> 9 | L116: =IF(C116="","",IF(K116<=0,"🔴 تمام",IF(K116<=تنظیمات_سیستم!$C$7,"🟠 کم","🟢 OK"))) -> 🟢 OK
A117: =IF(C117="","","SKU-"&TEXT(ROW()-3,"0000")) -> SKU-0114 | B117: CHSMLSNMU2 | C117: شلوار بیسیک مشکی2 | D117: شلوار | E117: Crepe | F117: All-Season | H117: 1440000 | I117: 9 | J117: =IFERROR(SUMIF(لاگ_فاکتور!$I$3:$I$1622,A117,لاگ_فاکتور!$L$3:$L$1622),0) -> 0 | K117: =MAX(0,I117-J117) -> 9 | L117: =IF(C117="","",IF(K117<=0,"🔴 تمام",IF(K117<=تنظیمات_سیستم!$C$7,"🟠 کم","🟢 OK"))) -> 🟢 OK
A118: =IF(C118="","","SKU-"&TEXT(ROW()-3,"0000")) -> SKU-0115 | B118: CHVSBJHBKFR | C118: وست دیپلمات مشکی فری | D118: وست | E118: Cotton | F118: All-Season | H118: 3980000 | I118: 9 | J118: =IFERROR(SUMIF(لاگ_فاکتور!$I$3:$I$1622,A118,لاگ_فاکتور!$L$3:$L$1622),0) -> 0 | K118: =MAX(0,I118-J118) -> 9 | L118: =IF(C118="","",IF(K118<=0,"🔴 تمام",IF(K118<=تنظیمات_سیستم!$C$7,"🟠 کم","🟢 OK"))) -> 🟢 OK
A119: =IF(C119="","","SKU-"&TEXT(ROW()-3,"0000")) -> SKU-0116 | B119: CHVSBJHBLFR | C119: وست دیپلمات طوسی فری | D119: وست | E119: Cotton | F119: All-Season | H119: 3980000 | I119: 9 | J119: =IFERROR(SUMIF(لاگ_فاکتور!$I$3:$I$1622,A119,لاگ_فاکتور!$L$3:$L$1622),0) -> 0 | K119: =MAX(0,I119-J119) -> 9 | L119: =IF(C119="","",IF(K119<=0,"🔴 تمام",IF(K119<=تنظیمات_سیستم!$C$7,"🟠 کم","🟢 OK"))) -> 🟢 OK
A120: =IF(C120="","","SKU-"&TEXT(ROW()-3,"0000")) -> SKU-0117 | B120: CHSMLSNBR1 | C120: تاپ اولدمانی کرم1 | D120: تاپ | E120: Linen | F120: Spring/Summer | H120: 2380000 | I120: 9 | J120: =IFERROR(SUMIF(لاگ_فاکتور!$I$3:$I$1622,A120,لاگ_فاکتور!$L$3:$L$1622),0) -> 0 | K120: =MAX(0,I120-J120) -> 9 | L120: =IF(C120="","",IF(K120<=0,"🔴 تمام",IF(K120<=تنظیمات_سیستم!$C$7,"🟠 کم","🟢 OK"))) -> 🟢 OK
A121: =IF(C121="","","SKU-"&TEXT(ROW()-3,"0000")) -> SKU-0118 | B121: CHSMLSNBR2 | C121: تاپ اولدمانی کرم2 | D121: تاپ | E121: Linen | F121: Spring/Summer | H121: 2380000 | I121: 9 | J121: =IFERROR(SUMIF(لاگ_فاکتور!$I$3:$I$1622,A121,لاگ_فاکتور!$L$3:$L$1622),0) -> 0 | K121: =MAX(0,I121-J121) -> 9 | L121: =IF(C121="","",IF(K121<=0,"🔴 تمام",IF(K121<=تنظیمات_سیستم!$C$7,"🟠 کم","🟢 OK"))) -> 🟢 OK
A122: =IF(C122="","","SKU-"&TEXT(ROW()-3,"0000")) -> SKU-0119 | B122: CHSMTMLBKFR | C122: تاپ اولدمانی کرم3 | D122: تاپ | E122: Linen | F122: Spring/Summer | H122: 2380000 | I122: 9 | J122: =IFERROR(SUMIF(لاگ_فاکتور!$I$3:$I$1622,A122,لاگ_فاکتور!$L$3:$L$1622),0) -> 0 | K122: =MAX(0,I122-J122) -> 9 | L122: =IF(C122="","",IF(K122<=0,"🔴 تمام",IF(K122<=تنظیمات_سیستم!$C$7,"🟠 کم","🟢 OK"))) -> 🟢 OK
A123: =IF(C123="","","SKU-"&TEXT(ROW()-3,"0000")) -> SKU-0120 | B123: CHTPOLDBK1 | C123: تاپ اولدمانی مشکی 1 | D123: تاپ | E123: Linen | F123: Spring/Summer | H123: 2380000 | I123: 9 | J123: =IFERROR(SUMIF(لاگ_فاکتور!$I$3:$I$1622,A123,لاگ_فاکتور!$L$3:$L$1622),0) -> 0 | K123: =MAX(0,I123-J123) -> 9 | L123: =IF(C123="","",IF(K123<=0,"🔴 تمام",IF(K123<=تنظیمات_سیستم!$C$7,"🟠 کم","🟢 OK"))) -> 🟢 OK
A124: =IF(C124="","","SKU-"&TEXT(ROW()-3,"0000")) -> SKU-0121 | B124: CHTPOLDBK2 | C124: تاپ اولدمانی مشکی2 | D124: تاپ | E124: Linen | F124: Spring/Summer | H124: 2380000 | I124: 9 | J124: =IFERROR(SUMIF(لاگ_فاکتور!$I$3:$I$1622,A124,لاگ_فاکتور!$L$3:$L$1622),0) -> 0 | K124: =MAX(0,I124-J124) -> 9 | L124: =IF(C124="","",IF(K124<=0,"🔴 تمام",IF(K124<=تنظیمات_سیستم!$C$7,"🟠 کم","🟢 OK"))) -> 🟢 OK
A125: =IF(C125="","","SKU-"&TEXT(ROW()-3,"0000")) -> SKU-0122 | B125: CHTPOLDCR3 | C125: تاپ اولدمانی مشکی3 | D125: تاپ | E125: Linen | F125: Spring/Summer | H125: 2380000 | I125: 9 | J125: =IFERROR(SUMIF(لاگ_فاکتور!$I$3:$I$1622,A125,لاگ_فاکتور!$L$3:$L$1622),0) -> 0 | K125: =MAX(0,I125-J125) -> 9 | L125: =IF(C125="","",IF(K125<=0,"🔴 تمام",IF(K125<=تنظیمات_سیستم!$C$7,"🟠 کم","🟢 OK"))) -> 🟢 OK
... A187: =IF(C187="","","SKU-"&TEXT(ROW()-3,"0000")) -> SKU-0184 | B187: CHVSBJHGRFR | C187: وست بیژو مشکی فری | D187: وست | E187: Cotton | F187: Fall/Winter | H187: 3200000 | I187: 9 | J187: =IFERROR(SUMIF(لاگ_فاکتور!$I$3:$I$1622,A187,لاگ_فاکتور!$L$3:$L$1622),0) -> 0 | K187: =MAX(0,I187-J187) -> 9 | L187: =IF(C187="","",IF(K187<=0,"🔴 تمام",IF(K187<=تنظیمات_سیستم!$C$7,"🟠 کم","🟢 OK"))) -> 🟢 OK
A188: =IF(C188="","","SKU-"&TEXT(ROW()-3,"0000")) -> SKU-0185 | B188: CHVSBJHBKFR | C188: وست بیژو آبی نفتی فری | D188: وست | E188: Cotton | F188: Fall/Winter | I188: 9 | J188: =IFERROR(SUMIF(لاگ_فاکتور!$I$3:$I$1622,A188,لاگ_فاکتور!$L$3:$L$1622),0) -> 0 | K188: =MAX(0,I188-J188) -> 9 | L188: =IF(C188="","",IF(K188<=0,"🔴 تمام",IF(K188<=تنظیمات_سیستم!$C$7,"🟠 کم","🟢 OK"))) -> 🟢 OK
A189: =IF(C189="","","SKU-"&TEXT(ROW()-3,"0000")) -> SKU-0186 | B189: CHVSBJHBLFR | C189: وست بیژو فیلی فری | D189: وست | E189: Cotton | F189: Fall/Winter | H189: 2600000 | I189: 9 | J189: =IFERROR(SUMIF(لاگ_فاکتور!$I$3:$I$1622,A189,لاگ_فاکتور!$L$3:$L$1622),0) -> 0 | K189: =MAX(0,I189-J189) -> 9 | L189: =IF(C189="","",IF(K189<=0,"🔴 تمام",IF(K189<=تنظیمات_سیستم!$C$7,"🟠 کم","🟢 OK"))) -> 🟢 OK
A190: =IF(C190="","","SKU-"&TEXT(ROW()-3,"0000")) -> SKU-0187 | B190: CHVSBJHEGFR | C190: شلوار بیژو مشکی فری | D190: شلوار | E190: Cotton | F190: Fall/Winter | H190: 1100000 | I190: 9 | J190: =IFERROR(SUMIF(لاگ_فاکتور!$I$3:$I$1622,A190,لاگ_فاکتور!$L$3:$L$1622),0) -> 0 | K190: =MAX(0,I190-J190) -> 9 | L190: =IF(C190="","",IF(K190<=0,"🔴 تمام",IF(K190<=تنظیمات_سیستم!$C$7,"🟠 کم","🟢 OK"))) -> 🟢 OK
A191: =IF(C191="","","SKU-"&TEXT(ROW()-3,"0000")) -> SKU-0188 | B191: CHSHBJHBKFR | C191: شلوار بیژو آبی نفتی فری | D191: شلوار | E191: Cotton | F191: Fall/Winter | H191: 1180000 | I191: 9 | J191: =IFERROR(SUMIF(لاگ_فاکتور!$I$3:$I$1622,A191,لاگ_فاکتور!$L$3:$L$1622),0) -> 0 | K191: =MAX(0,I191-J191) -> 9 | L191: =IF(C191="","",IF(K191<=0,"🔴 تمام",IF(K191<=تنظیمات_سیستم!$C$7,"🟠 کم","🟢 OK"))) -> 🟢 OK
A192: =IF(C192="","","SKU-"&TEXT(ROW()-3,"0000")) -> SKU-0189 | B192: CHSHBJHBLFR | C192: شلوار بیژو فیلی فری | D192: شلوار | E192: Cotton | F192: Fall/Winter | H192: 1100000 | I192: 9 | J192: =IFERROR(SUMIF(لاگ_فاکتور!$I$3:$I$1622,A192,لاگ_فاکتور!$L$3:$L$1622),0) -> 0 | K192: =MAX(0,I192-J192) -> 9 | L192: =IF(C192="","",IF(K192<=0,"🔴 تمام",IF(K192<=تنظیمات_سیستم!$C$7,"🟠 کم","🟢 OK"))) -> 🟢 OK
A193: =IF(C193="","","SKU-"&TEXT(ROW()-3,"0000")) -> SKU-0190 | B193: CHSHBJHEGFR | C193: کت بیژو مشکی فری | D193: کت | E193: Cotton | F193: Fall/Winter | H193: 2650000 | I193: 9 | J193: =IFERROR(SUMIF(لاگ_فاکتور!$I$3:$I$1622,A193,لاگ_فاکتور!$L$3:$L$1622),0) -> 0 | K193: =MAX(0,I193-J193) -> 9 | L193: =IF(C193="","",IF(K193<=0,"🔴 تمام",IF(K193<=تنظیمات_سیستم!$C$7,"🟠 کم","🟢 OK"))) -> 🟢 OK
A194: =IF(C194="","","SKU-"&TEXT(ROW()-3,"0000")) -> SKU-0191 | B194: CHKTBJHBKFR | C194: کت بیژو فیلی فیری | D194: کت | E194: Cotton | F194: Fall/Winter | H194: 2650000 | I194: 9 | J194: =IFERROR(SUMIF(لاگ_فاکتور!$I$3:$I$1622,A194,لاگ_فاکتور!$L$3:$L$1622),0) -> 0 | K194: =MAX(0,I194-J194) -> 9 | L194: =IF(C194="","",IF(K194<=0,"🔴 تمام",IF(K194<=تنظیمات_سیستم!$C$7,"🟠 کم","🟢 OK"))) -> 🟢 OK
A195: =IF(C195="","","SKU-"&TEXT(ROW()-3,"0000")) -> SKU-0192 | B195: CHKTBJHEGFR | C195: کت بیژو آبی نفتی فری | D195: کت | E195: Cotton | F195: Fall/Winter | H195: 2650000 | I195: 9 | J195: =IFERROR(SUMIF(لاگ_فاکتور!$I$3:$I$1622,A195,لاگ_فاکتور!$L$3:$L$1622),0) -> 0 | K195: =MAX(0,I195-J195) -> 9 | L195: =IF(C195="","",IF(K195<=0,"🔴 تمام",IF(K195<=تنظیمات_سیستم!$C$7,"🟠 کم","🟢 OK"))) -> 🟢 OK
A196: =IF(C196="","","SKU-"&TEXT(ROW()-3,"0000")) -> SKU-0193 | B196: CHKTBJHBLFR | C196: کت بیژو کرم فری | D196: کت | E196: Cotton | F196: Fall/Winter | H196: 2650000 | I196: 9 | J196: =IFERROR(SUMIF(لاگ_فاکتور!$I$3:$I$1622,A196,لاگ_فاکتور!$L$3:$L$1622),0) -> 0 | K196: =MAX(0,I196-J196) -> 9 | L196: =IF(C196="","",IF(K196<=0,"🔴 تمام",IF(K196<=تنظیمات_سیستم!$C$7,"🟠 کم","🟢 OK"))) -> 🟢 OK
A197: =IF(C197="","","SKU-"&TEXT(ROW()-3,"0000")) -> SKU-0194 | B197: CHKTBJHCRFR | C197: کت مازراتی سبز | D197: کت | E197: Crepe | F197: Fall/Winter | H197: 1800000 | I197: 9 | J197: =IFERROR(SUMIF(لاگ_فاکتور!$I$3:$I$1622,A197,لاگ_فاکتور!$L$3:$L$1622),0) -> 0 | K197: =MAX(0,I197-J197) -> 9 | L197: =IF(C197="","",IF(K197<=0,"🔴 تمام",IF(K197<=تنظیمات_سیستم!$C$7,"🟠 کم","🟢 OK"))) -> 🟢 OK
A198: =IF(C198="","","SKU-"&TEXT(ROW()-3,"0000")) -> SKU-0195 | B198: CHKTMZROLFR | C198: کت مازراتی کرم | D198: کت | E198: Crepe | F198: Fall/Winter | H198: 1800000 | I198: 9 | J198: =IFERROR(SUMIF(لاگ_فاکتور!$I$3:$I$1622,A198,لاگ_فاکتور!$L$3:$L$1622),0) -> 0 | K198: =MAX(0,I198-J198) -> 9 | L198: =IF(C198="","",IF(K198<=0,"🔴 تمام",IF(K198<=تنظیمات_سیستم!$C$7,"🟠 کم","🟢 OK"))) -> 🟢 OK
A199: =IF(C199="","","SKU-"&TEXT(ROW()-3,"0000")) -> SKU-0196 | B199: CHKTMZRCRFR | C199: کراپ تافته شیری 1 | D199: تاپ | E199: Taffeta | F199: All-Season | H199: 1200000 | I199: 9 | J199: =IFERROR(SUMIF(لاگ_فاکتور!$I$3:$I$1622,A199,لاگ_فاکتور!$L$3:$L$1622),0) -> 0 | K199: =MAX(0,I199-J199) -> 9 | L199: =IF(C199="","",IF(K199<=0,"🔴 تمام",IF(K199<=تنظیمات_سیستم!$C$7,"🟠 کم","🟢 OK"))) -> 🟢 OK
A200: =IF(C200="","","SKU-"&TEXT(ROW()-3,"0000")) -> SKU-0197 | B200: CHTPCTFIV1 | C200: کراپ تافته شیری2 | D200: تاپ | E200: Taffeta | F200: All-Season | H200: 1200000 | I200: 9 | J200: =IFERROR(SUMIF(لاگ_فاکتور!$I$3:$I$1622,A200,لاگ_فاکتور!$L$3:$L$1622),0) -> 0 | K200: =MAX(0,I200-J200) -> 9 | L200: =IF(C200="","",IF(K200<=0,"🔴 تمام",IF(K200<=تنظیمات_سیستم!$C$7,"🟠 کم","🟢 OK"))) -> 🟢 OK
... A207: =IF(C207="","","SKU-"&TEXT(ROW()-3,"0000")) -> SKU-0204 | B207: CHSMZBRPT2 | C207: شلوار ثمین مشکی1 | D207: شلوار | E207: Crepe | F207: All-Season | H207: 1980000 | I207: 9 | J207: =IFERROR(SUMIF(لاگ_فاکتور!$I$3:$I$1622,A207,لاگ_فاکتور!$L$3:$L$1622),0) -> 0 | K207: =MAX(0,I207-J207) -> 9 | L207: =IF(C207="","",IF(K207<=0,"🔴 تمام",IF(K207<=تنظیمات_سیستم!$C$7,"🟠 کم","🟢 OK"))) -> 🟢 OK
A208: =IF(C208="","","SKU-"&TEXT(ROW()-3,"0000")) -> SKU-0205 | B208: CHSHSMNBK1 | C208: شلوار ثمین مشکی 2 | D208: شلوار | E208: Crepe | F208: All-Season | I208: 9 | J208: =IFERROR(SUMIF(لاگ_فاکتور!$I$3:$I$1622,A208,لاگ_فاکتور!$L$3:$L$1622),0) -> 0 | K208: =MAX(0,I208-J208) -> 9 | L208: =IF(C208="","",IF(K208<=0,"🔴 تمام",IF(K208<=تنظیمات_سیستم!$C$7,"🟠 کم","🟢 OK"))) -> 🟢 OK
A209: =IF(C209="","","SKU-"&TEXT(ROW()-3,"0000")) -> SKU-0206 | B209: CHSHSMNBK2 | C209: شلوار ثمین سبز1 | D209: شلوار | E209: Crepe | F209: All-Season | I209: 9 | J209: =IFERROR(SUMIF(لاگ_فاکتور!$I$3:$I$1622,A209,لاگ_فاکتور!$L$3:$L$1622),0) -> 0 | K209: =MAX(0,I209-J209) -> 9 | L209: =IF(C209="","",IF(K209<=0,"🔴 تمام",IF(K209<=تنظیمات_سیستم!$C$7,"🟠 کم","🟢 OK"))) -> 🟢 OK
A210: =IF(C210="","","SKU-"&TEXT(ROW()-3,"0000")) -> SKU-0207 | B210: CHSHSMNOL1 | C210: شلوار ثمین سبز2 | D210: شلوار | E210: Crepe | F210: All-Season | I210: 9 | J210: =IFERROR(SUMIF(لاگ_فاکتور!$I$3:$I$1622,A210,لاگ_فاکتور!$L$3:$L$1622),0) -> 0 | K210: =MAX(0,I210-J210) -> 9 | L210: =IF(C210="","",IF(K210<=0,"🔴 تمام",IF(K210<=تنظیمات_سیستم!$C$7,"🟠 کم","🟢 OK"))) -> 🟢 OK
A211: =IF(C211="","","SKU-"&TEXT(ROW()-3,"0000")) -> SKU-0208 | B211: CHSHSMNOL2 | C211: شلوار ثمین آبی 1 | D211: شلوار | E211: Crepe | F211: All-Season | I211: 9 | J211: =IFERROR(SUMIF(لاگ_فاکتور!$I$3:$I$1622,A211,لاگ_فاکتور!$L$3:$L$1622),0) -> 0 | K211: =MAX(0,I211-J211) -> 9 | L211: =IF(C211="","",IF(K211<=0,"🔴 تمام",IF(K211<=تنظیمات_سیستم!$C$7,"🟠 کم","🟢 OK"))) -> 🟢 OK
A212: =IF(C212="","","SKU-"&TEXT(ROW()-3,"0000")) -> SKU-0209 | B212: CHSHSMNBL1 | C212: شلوار ثمین آبی2 | D212: شلوار | E212: Crepe | F212: All-Season | I212: 9 | J212: =IFERROR(SUMIF(لاگ_فاکتور!$I$3:$I$1622,A212,لاگ_فاکتور!$L$3:$L$1622),0) -> 0 | K212: =MAX(0,I212-J212) -> 9 | L212: =IF(C212="","",IF(K212<=0,"🔴 تمام",IF(K212<=تنظیمات_سیستم!$C$7,"🟠 کم","🟢 OK"))) -> 🟢 OK
A213: =IF(C213="","","SKU-"&TEXT(ROW()-3,"0000")) -> SKU-0210 | B213: CHSHSMNBL2 | C213: کت ژاکارد صورتی 1 | D213: کت | E213: Jaquard | F213: Fall/Winter | H213: 3850000 | I213: 9 | J213: =IFERROR(SUMIF(لاگ_فاکتور!$I$3:$I$1622,A213,لاگ_فاکتور!$L$3:$L$1622),0) -> 0 | K213: =MAX(0,I213-J213) -> 9 | L213: =IF(C213="","",IF(K213<=0,"🔴 تمام",IF(K213<=تنظیمات_سیستم!$C$7,"🟠 کم","🟢 OK"))) -> 🟢 OK
A214: =IF(C214="","","SKU-"&TEXT(ROW()-3,"0000")) -> SKU-0211 | B214: CHKTJKDRDFR | C214: ست اسمارت کرم فری | D214: ست | E214: Linen | F214: Spring/Summer | I214: 9 | J214: =IFERROR(SUMIF(لاگ_فاکتور!$I$3:$I$1622,A214,لاگ_فاکتور!$L$3:$L$1622),0) -> 0 | K214: =MAX(0,I214-J214) -> 9 | L214: =IF(C214="","",IF(K214<=0,"🔴 تمام",IF(K214<=تنظیمات_سیستم!$C$7,"🟠 کم","🟢 OK"))) -> 🟢 OK
A215: =IF(C215="","","SKU-"&TEXT(ROW()-3,"0000")) -> SKU-0212 | B215: CHSTSMTCRFR | C215: ست سامر آجری 1 | D215: ست | E215: Tencel | F215: Spring/Summer | I215: 9 | J215: =IFERROR(SUMIF(لاگ_فاکتور!$I$3:$I$1622,A215,لاگ_فاکتور!$L$3:$L$1622),0) -> 0 | K215: =MAX(0,I215-J215) -> 9 | L215: =IF(C215="","",IF(K215<=0,"🔴 تمام",IF(K215<=تنظیمات_سیستم!$C$7,"🟠 کم","🟢 OK"))) -> 🟢 OK
A216: =IF(C216="","","SKU-"&TEXT(ROW()-3,"0000")) -> SKU-0213 | B216: CHSTSMRRD1 | C216: ست سامر آجری 2 | D216: ست | E216: Tencel | F216: Spring/Summer | H216: 4200000 | I216: 9 | J216: =IFERROR(SUMIF(لاگ_فاکتور!$I$3:$I$1622,A216,لاگ_فاکتور!$L$3:$L$1622),0) -> 0 | K216: =MAX(0,I216-J216) -> 9 | L216: =IF(C216="","",IF(K216<=0,"🔴 تمام",IF(K216<=تنظیمات_سیستم!$C$7,"🟠 کم","🟢 OK"))) -> 🟢 OK
A217: =IF(C217="","","SKU-"&TEXT(ROW()-3,"0000")) -> SKU-0214 | B217: CHSTSMRRD2 | C217: شومیز ستیا زرشکی 1 | D217: شومیز | E217: Wool | F217: All-Season | I217: 9 | J217: =IFERROR(SUMIF(لاگ_فاکتور!$I$3:$I$1622,A217,لاگ_فاکتور!$L$3:$L$1622),0) -> 0 | K217: =MAX(0,I217-J217) -> 9 | L217: =IF(C217="","",IF(K217<=0,"🔴 تمام",IF(K217<=تنظیمات_سیستم!$C$7,"🟠 کم","🟢 OK"))) -> 🟢 OK
A218: =IF(C218="","","SKU-"&TEXT(ROW()-3,"0000")) -> SKU-0215 | B218: CHSMSTYRD1 | C218: شومیز ستیا زرد 2 | D218: شومیز | E218: Crepe | F218: All-Season | H218: 2680000 | I218: 9 | J218: =IFERROR(SUMIF(لاگ_فاکتور!$I$3:$I$1622,A218,لاگ_فاکتور!$L$3:$L$1622),0) -> 0 | K218: =MAX(0,I218-J218) -> 9 | L218: =IF(C218="","",IF(K218<=0,"🔴 تمام",IF(K218<=تنظیمات_سیستم!$C$7,"🟠 کم","🟢 OK"))) -> 🟢 OK
A219: =IF(C219="","","SKU-"&TEXT(ROW()-3,"0000")) -> SKU-0216 | B219: CHSMSTYRD2 | C219: شلوار | D219: شومیز | E219: Crepe | F219: All-Season | G219: 1580000 | H219: 2200000 | I219: 9 | J219: =IFERROR(SUMIF(لاگ_فاکتور!$I$3:$I$1622,A219,لاگ_فاکتور!$L$3:$L$1622),0) -> 0 | K219: =MAX(0,I219-J219) -> 9 | L219: =IF(C219="","",IF(K219<=0,"🔴 تمام",IF(K219<=تنظیمات_سیستم!$C$7,"🟠 کم","🟢 OK"))) -> 🟢 OK
A220: =IF(C220="","","SKU-"&TEXT(ROW()-3,"0000")) -> SKU-0217 | B220: CHSMSTYPT1 | C220: شومیز ستیا پلنگی 2 | D220: شومیز | E220: Crepe | F220: All-Season | I220: 9 | J220: =IFERROR(SUMIF(لاگ_فاکتور!$I$3:$I$1622,A220,لاگ_فاکتور!$L$3:$L$1622),0) -> 0 | K220: =MAX(0,I220-J220) -> 9 | L220: =IF(C220="","",IF(K220<=0,"🔴 تمام",IF(K220<=تنظیمات_سیستم!$C$7,"🟠 کم","🟢 OK"))) -> 🟢 OK
A221: =IF(C221="","","SKU-"&TEXT(ROW()-3,"0000")) -> SKU-0218 | B221: CHSMSTYPT2 | C221: کت باربی قهوه ای1 | D221: کت | E221: Lyocel | F221: Fall/Winter | H221: 4180000 | I221: 9 | J221: =IFERROR(SUMIF(لاگ_فاکتور!$I$3:$I$1622,A221,لاگ_فاکتور!$L$3:$L$1622),0) -> 0 | K221: =MAX(0,I221-J221) -> 9 | L221: =IF(C221="","",IF(K221<=0,"🔴 تمام",IF(K221<=تنظیمات_سیستم!$C$7,"🟠 کم","🟢 OK"))) -> 🟢 OK
A222: =IF(C222="","","SKU-"&TEXT(ROW()-3,"0000")) -> SKU-0219 | B222: CHKTBARBR1 | C222: کت باربی قهوه ای2 | D222: کت | E222: Lyocel | F222: Fall/Winter | H222: 4180000 | I222: 9 | J222: =IFERROR(SUMIF(لاگ_فاکتور!$I$3:$I$1622,A222,لاگ_فاکتور!$L$3:$L$1622),0) -> 0 | K222: =MAX(0,I222-J222) -> 9 | L222: =IF(C222="","",IF(K222<=0,"🔴 تمام",IF(K222<=تنظیمات_سیستم!$C$7,"🟠 کم","🟢 OK"))) -> 🟢 OK
A223: =IF(C223="","","SKU-"&TEXT(ROW()-3,"0000")) -> SKU-0220 | B223: CHKTBARBR2 | C223: کت باربی آبی 1 | D223: کت | E223: Lyocel | F223: Fall/Winter | H223: 4180000 | I223: 9 | J223: =IFERROR(SUMIF(لاگ_فاکتور!$I$3:$I$1622,A223,لاگ_فاکتور!$L$3:$L$1622),0) -> 0 | K223: =MAX(0,I223-J223) -> 9 | L223: =IF(C223="","",IF(K223<=0,"🔴 تمام",IF(K223<=تنظیمات_سیستم!$C$7,"🟠 کم","🟢 OK"))) -> 🟢 OK
A224: =IF(C224="","","SKU-"&TEXT(ROW()-3,"0000")) -> SKU-0221 | B224: CHKTBARBL1 | C224: کت باربی آبی 2 | D224: کت | E224: Lyocel | F224: Fall/Winter | H224: 4180000 | I224: 9 | J224: =IFERROR(SUMIF(لاگ_فاکتور!$I$3:$I$1622,A224,لاگ_فاکتور!$L$3:$L$1622),0) -> 0 | K224: =MAX(0,I224-J224) -> 9 | L224: =IF(C224="","",IF(K224<=0,"🔴 تمام",IF(K224<=تنظیمات_سیستم!$C$7,"🟠 کم","🟢 OK"))) -> 🟢 OK
A225: =IF(C225="","","SKU-"&TEXT(ROW()-3,"0000")) -> SKU-0222 | B225: CHKTBARBL2 | C225: کت باربی مشکی1 | D225: کت | E225: Lyocel | F225: Fall/Winter | H225: 4180000 | I225: 9 | J225: =IFERROR(SUMIF(لاگ_فاکتور!$I$3:$I$1622,A225,لاگ_فاکتور!$L$3:$L$1622),0) -> 0 | K225: =MAX(0,I225-J225) -> 9 | L225: =IF(C225="","",IF(K225<=0,"🔴 تمام",IF(K225<=تنظیمات_سیستم!$C$7,"🟠 کم","🟢 OK"))) -> 🟢 OK
A226: =IF(C226="","","SKU-"&TEXT(ROW()-3,"0000")) -> SKU-0223 | B226: CHKTBARBK1 | C226: کت باربی مشکی2 | D226: کت | E226: Lyocel | F226: Fall/Winter | H226: 4180000 | I226: 9 | J226: =IFERROR(SUMIF(لاگ_فاکتور!$I$3:$I$1622,A226,لاگ_فاکتور!$L$3:$L$1622),0) -> 0 | K226: =MAX(0,I226-J226) -> 9 | L226: =IF(C226="","",IF(K226<=0,"🔴 تمام",IF(K226<=تنظیمات_سیستم!$C$7,"🟠 کم","🟢 OK"))) -> 🟢 OK
A227: =IF(C227="","","SKU-"&TEXT(ROW()-3,"0000")) -> SKU-0224 | B227: CHKTBARBK2 | C227: شلوارک کرپ مشکی1 | D227: شلوارک | E227: Crepe | F227: Spring/Summer | H227: 1280000 | I227: 9 | J227: =IFERROR(SUMIF(لاگ_فاکتور!$I$3:$I$1622,A227,لاگ_فاکتور!$L$3:$L$1622),0) -> 0 | K227: =MAX(0,I227-J227) -> 9 | L227: =IF(C227="","",IF(K227<=0,"🔴 تمام",IF(K227<=تنظیمات_سیستم!$C$7,"🟠 کم","🟢 OK"))) -> 🟢 OK
A228: =IF(C228="","","SKU-"&TEXT(ROW()-3,"0000")) -> SKU-0225 | B228: CHSKKRPBK1 | C228: شلوارک کرپ مشکی2 | D228: شلوارک | E228: Crepe | F228: Fall/Winter | H228: 1280000 | I228: 9 | J228: =IFERROR(SUMIF(لاگ_فاکتور!$I$3:$I$1622,A228,لاگ_فاکتور!$L$3:$L$1622),0) -> 0 | K228: =MAX(0,I228-J228) -> 9 | L228: =IF(C228="","",IF(K228<=0,"🔴 تمام",IF(K228<=تنظیمات_سیستم!$C$7,"🟠 کم","🟢 OK"))) -> 🟢 OK
A229: =IF(C229="","","SKU-"&TEXT(ROW()-3,"0000")) -> SKU-0226 | B229: CHSKKRPBK2 | C229: شومیز آلیس صورتی1 | D229: شومیز | E229: Silk | F229: All-Season | I229: 9 | J229: =IFERROR(SUMIF(لاگ_فاکتور!$I$3:$I$1622,A229,لاگ_فاکتور!$L$3:$L$1622),0) -> 0 | K229: =MAX(0,I229-J229) -> 9 | L229: =IF(C229="","",IF(K229<=0,"🔴 تمام",IF(K229<=تنظیمات_سیستم!$C$7,"🟠 کم","🟢 OK"))) -> 🟢 OK
A230: =IF(C230="","","SKU-"&TEXT(ROW()-3,"0000")) -> SKU-0227 | B230: CHSMALSPK1 | C230: شومیز آلیس صورتی2 | D230: شومیز | E230: Silk | F230: All-Season | I230: 9 | J230: =IFERROR(SUMIF(لاگ_فاکتور!$I$3:$I$1622,A230,لاگ_فاکتور!$L$3:$L$1622),0) -> 0 | K230: =MAX(0,I230-J230) -> 9 | L230: =IF(C230="","",IF(K230<=0,"🔴 تمام",IF(K230<=تنظیمات_سیستم!$C$7,"🟠 کم","🟢 OK"))) -> 🟢 OK
A231: =IF(C231="","","SKU-"&TEXT(ROW()-3,"0000")) -> SKU-0228 | B231: CHSMALSPK2 | C231: شومیز آلیس صورتی3 | D231: شومیز | E231: Silk | F231: All-Season | I231: 9 | J231: =IFERROR(SUMIF(لاگ_فاکتور!$I$3:$I$1622,A231,لاگ_فاکتور!$L$3:$L$1622),0) -> 0 | K231: =MAX(0,I231-J231) -> 9 | L231: =IF(C231="","",IF(K231<=0,"🔴 تمام",IF(K231<=تنظیمات_سیستم!$C$7,"🟠 کم","🟢 OK"))) -> 🟢 OK
A232: =IF(C232="","","SKU-"&TEXT(ROW()-3,"0000")) -> SKU-0229 | B232: CHSMALSPK3 | C232: ست دنیزکرم1 | D232: ست | E232: Cotton | F232: Spring/Summer | H232: 2980000 | I232: 9 | J232: =IFERROR(SUMIF(لاگ_فاکتور!$I$3:$I$1622,A232,لاگ_فاکتور!$L$3:$L$1622),0) -> 0 | K232: =MAX(0,I232-J232) -> 9 | L232: =IF(C232="","",IF(K232<=0,"🔴 تمام",IF(K232<=تنظیمات_سیستم!$C$7,"🟠 کم","🟢 OK"))) -> 🟢 OK
A233: =IF(C233="","","SKU-"&TEXT(ROW()-3,"0000")) -> SKU-0230 | B233: CHSTDNYCR1 | C233: ست دنیز کرم2 | D233: ست | E233: Cotton | F233: Spring/Summer | H233: 2980000 | I233: 9 | J233: =IFERROR(SUMIF(لاگ_فاکتور!$I$3:$I$1622,A233,لاگ_فاکتور!$L$3:$L$1622),0) -> 0 | K233: =MAX(0,I233-J233) -> 9 | L233: =IF(C233="","",IF(K233<=0,"🔴 تمام",IF(K233<=تنظیمات_سیستم!$C$7,"🟠 کم","🟢 OK"))) -> 🟢 OK
A234: =IF(C234="","","SKU-"&TEXT(ROW()-3,"0000")) -> SKU-0231 | B234: CHSTDNYCR2 | C234: ست دنیز سبز1 | D234: ست | E234: Cotton | F234: Spring/Summer | H234: 2980000 | I234: 9 | J234: =IFERROR(SUMIF(لاگ_فاکتور!$I$3:$I$1622,A234,لاگ_فاکتور!$L$3:$L$1622),0) -> 0 | K234: =MAX(0,I234-J234) -> 9 | L234: =IF(C234="","",IF(K234<=0,"🔴 تمام",IF(K234<=تنظیمات_سیستم!$C$7,"🟠 کم","🟢 OK"))) -> 🟢 OK
A235: =IF(C235="","","SKU-"&TEXT(ROW()-3,"0000")) -> SKU-0232 | B235: CHSTDNYOL1 | C235: ست دنیز سبز2 | D235: ست | E235: Cotton | F235: Spring/Summer | H235: 2980000 | I235: 9 | J235: =IFERROR(SUMIF(لاگ_فاکتور!$I$3:$I$1622,A235,لاگ_فاکتور!$L$3:$L$1622),0) -> 0 | K235: =MAX(0,I235-J235) -> 9 | L235: =IF(C235="","",IF(K235<=0,"🔴 تمام",IF(K235<=تنظیمات_سیستم!$C$7,"🟠 کم","🟢 OK"))) -> 🟢 OK
A236: =IF(C236="","","SKU-"&TEXT(ROW()-3,"0000")) -> SKU-0233 | B236: CHSTDNYOL2 | C236: دامن بانو کرم فری | D236: دامن | E236: Cotton | F236: Spring/Summer | H236: 720000 | I236: 9 | J236: =IFERROR(SUMIF(لاگ_فاکتور!$I$3:$I$1622,A236,لاگ_فاکتور!$L$3:$L$1622),0) -> 0 | K236: =MAX(0,I236-J236) -> 9 | L236: =IF(C236="","",IF(K236<=0,"🔴 تمام",IF(K236<=تنظیمات_سیستم!$C$7,"🟠 کم","🟢 OK"))) -> 🟢 OK
A237: =IF(C237="","","SKU-"&TEXT(ROW()-3,"0000")) -> SKU-0234 | B237: CHDMBNOCRFR | C237: دامن بانو سفید فری | D237: دامن | E237: Cotton | F237: Spring/Summer | H237: 720000 | I237: 9 | J237: =IFERROR(SUMIF(لاگ_فاکتور!$I$3:$I$1622,A237,لاگ_فاکتور!$L$3:$L$1622),0) -> 0 | K237: =MAX(0,I237-J237) -> 9 | L237: =IF(C237="","",IF(K237<=0,"🔴 تمام",IF(K237<=تنظیمات_سیستم!$C$7,"🟠 کم","🟢 OK"))) -> 🟢 OK
...

Sheet KPI_روزانه
A2: KPIروزانه فروشگاه
A3: سلول‌های زرد = ورود دستی | سلول‌های آبی‌تیره = فرمول خودکار از لاگ فاکتور
A4: تاریخ Date | B4: کد پرسنل Staff_ID | C4: نام پرسنل Name | D4: ورودی مشتری Footfall | E4: اتاق پرو Fitting_Room | F4: تعداد فاکتور Invoices | G4: فروش (تومان) Sales | H4: تخفیف داده Discounts | I4: مرجوعی Returns | J4: اپ‌سل موفق Upsell | K4: نرخ تبدیل% Conv_Rate | L4: ATV (میانگین فاکتور) | M4: UPT (میانگین اقلام) | N4: شکایت Complaints | O4: رویداد روز Events | P4: یادداشت مدیر Mgr_Notes
A5: 1405/07/01 | B5: 0 | C5: =IFERROR(INDEX(اطلاعات_پرسنل!$D$4:$D$59,MATCH(B5,اطلاعات_پرسنل!$A$4:$A$59,0)),"") -> فروشگاه | D5: 4 | E5: 1 | F5: =IFERROR(SUMIFS(لاگ_فاکتور!$V$3:$V$1622,لاگ_فاکتور!$B$3:$B$1622,A5,لاگ_فاکتور!$C$3:$C$1622,B5),0) -> 1 | G5: =IFERROR(SUMIFS(لاگ_فاکتور!$O$3:$O$1622,لاگ_فاکتور!$B$3:$B$1622,A5,لاگ_فاکتور!$C$3:$C$1622,B5),0) -> 2000000 | H5: =IFERROR(SUMIFS(لاگ_فاکتور!$N$3:$N$1622,لاگ_فاکتور!$B$3:$B$1622,A5,لاگ_فاکتور!$C$3:$C$1622,B5),0) -> 0 | I5: 0 | J5: 0 | K5: =IFERROR(F5/D5,0) -> 0.25 | L5: =IFERROR(G5/F5,0) -> 2000000 | M5: =IFERROR(SUMIFS(لاگ_فاکتور!$L$3:$L$1622,لاگ_فاکتور!$B$3:$B$1622,A5,لاگ_فاکتور!$C$3:$C$1622,B5)/F5,0) -> 1 | N5: 0
A6: 1405/07/01 | B6: 1 | C6: =IFERROR(INDEX(اطلاعات_پرسنل!$D$4:$D$59,MATCH(B6,اطلاعات_پرسنل!$A$4:$A$59,0)),"") -> دریا کریمی | D6: 4 | F6: =IFERROR(SUMIFS(لاگ_فاکتور!$V$3:$V$1622,لاگ_فاکتور!$B$3:$B$1622,A6,لاگ_فاکتور!$C$3:$C$1622,B6),0) -> 0 | G6: =IFERROR(SUMIFS(لاگ_فاکتور!$O$3:$O$1622,لاگ_فاکتور!$B$3:$B$1622,A6,لاگ_فاکتور!$C$3:$C$1622,B6),0) -> 0 | H6: =IFERROR(SUMIFS(لاگ_فاکتور!$N$3:$N$1622,لاگ_فاکتور!$B$3:$B$1622,A6,لاگ_فاکتور!$C$3:$C$1622,B6),0) -> 0 | I6: 0 | J6: 0 | K6: =IFERROR(F6/D6,0) -> 0 | L6: =IFERROR(G6/F6,0) -> 0 | M6: =IFERROR(SUMIFS(لاگ_فاکتور!$L$3:$L$1622,لاگ_فاکتور!$B$3:$B$1622,A6,لاگ_فاکتور!$C$3:$C$1622,B6)/F6,0) -> 0 | N6: 0
A7: 1405/07/01 | B7: 2 | C7: =IFERROR(INDEX(اطلاعات_پرسنل!$D$4:$D$59,MATCH(B7,اطلاعات_پرسنل!$A$4:$A$59,0)),"") -> ماحی حمیدپور | D7: 2 | F7: =IFERROR(SUMIFS(لاگ_فاکتور!$V$3:$V$1622,لاگ_فاکتور!$B$3:$B$1622,A7,لاگ_فاکتور!$C$3:$C$1622,B7),0) -> 0 | G7: =IFERROR(SUMIFS(لاگ_فاکتور!$O$3:$O$1622,لاگ_فاکتور!$B$3:$B$1622,A7,لاگ_فاکتور!$C$3:$C$1622,B7),0) -> 0 | H7: =IFERROR(SUMIFS(لاگ_فاکتور!$N$3:$N$1622,لاگ_فاکتور!$B$3:$B$1622,A7,لاگ_فاکتور!$C$3:$C$1622,B7),0) -> 0 | I7: 0 | J7: 0 | K7: =IFERROR(F7/D7,0) -> 0 | L7: =IFERROR(G7/F7,0) -> 0 | M7: =IFERROR(SUMIFS(لاگ_فاکتور!$L$3:$L$1622,لاگ_فاکتور!$B$3:$B$1622,A7,لاگ_فاکتور!$C$3:$C$1622,B7)/F7,0) -> 0 | N7: 0
A8: 1405/07/02 | B8: 0 | C8: =IFERROR(INDEX(اطلاعات_پرسنل!$D$4:$D$59,MATCH(B8,اطلاعات_پرسنل!$A$4:$A$59,0)),"") -> فروشگاه | D8: 1 | E8: 1 | F8: =IFERROR(SUMIFS(لاگ_فاکتور!$V$3:$V$1622,لاگ_فاکتور!$B$3:$B$1622,A8,لاگ_فاکتور!$C$3:$C$1622,B8),0) -> 1 | G8: =IFERROR(SUMIFS(لاگ_فاکتور!$O$3:$O$1622,لاگ_فاکتور!$B$3:$B$1622,A8,لاگ_فاکتور!$C$3:$C$1622,B8),0) -> 3960000 | H8: =IFERROR(SUMIFS(لاگ_فاکتور!$N$3:$N$1622,لاگ_فاکتور!$B$3:$B$1622,A8,لاگ_فاکتور!$C$3:$C$1622,B8),0) -> 0 | I8: 0 | J8: 0 | K8: =IFERROR(F8/D8,0) -> 1 | L8: =IFERROR(G8/F8,0) -> 3960000 | M8: =IFERROR(SUMIFS(لاگ_فاکتور!$L$3:$L$1622,لاگ_فاکتور!$B$3:$B$1622,A8,لاگ_فاکتور!$C$3:$C$1622,B8)/F8,0) -> 2 | N8: 0
A9: 1405/07/02 | B9: 2 | C9: =IFERROR(INDEX(اطلاعات_پرسنل!$D$4:$D$59,MATCH(B9,اطلاعات_پرسنل!$A$4:$A$59,0)),"") -> ماحی حمیدپور | D9: 14 | E9: 3 | F9: =IFERROR(SUMIFS(لاگ_فاکتور!$V$3:$V$1622,لاگ_فاکتور!$B$3:$B$1622,A9,لاگ_فاکتور!$C$3:$C$1622,B9),0) -> 3 | G9: =IFERROR(SUMIFS(لاگ_فاکتور!$O$3:$O$1622,لاگ_فاکتور!$B$3:$B$1622,A9,لاگ_فاکتور!$C$3:$C$1622,B9),0) -> 5636000 | H9: =IFERROR(SUMIFS(لاگ_فاکتور!$N$3:$N$1622,لاگ_فاکتور!$B$3:$B$1622,A9,لاگ_فاکتور!$C$3:$C$1622,B9),0) -> 0 | I9: 0 | J9: 0 | K9: =IFERROR(F9/D9,0) -> 0.21428571 | L9: =IFERROR(G9/F9,0) -> 1878666.7 | M9: =IFERROR(SUMIFS(لاگ_فاکتور!$L$3:$L$1622,لاگ_فاکتور!$B$3:$B$1622,A9,لاگ_فاکتور!$C$3:$C$1622,B9)/F9,0) -> 1 | N9: 0
A10: 1405/07/02 | B10: 1 | C10: =IFERROR(INDEX(اطلاعات_پرسنل!$D$4:$D$59,MATCH(B10,اطلاعات_پرسنل!$A$4:$A$59,0)),"") -> دریا کریمی | D10: 18 | E10: 4 | F10: =IFERROR(SUMIFS(لاگ_فاکتور!$V$3:$V$1622,لاگ_فاکتور!$B$3:$B$1622,A10,لاگ_فاکتور!$C$3:$C$1622,B10),0) -> 0 | G10: =IFERROR(SUMIFS(لاگ_فاکتور!$O$3:$O$1622,لاگ_فاکتور!$B$3:$B$1622,A10,لاگ_فاکتور!$C$3:$C$1622,B10),0) -> 0 | H10: =IFERROR(SUMIFS(لاگ_فاکتور!$N$3:$N$1622,لاگ_فاکتور!$B$3:$B$1622,A10,لاگ_فاکتور!$C$3:$C$1622,B10),0) -> 0 | I10: 0 | J10: 0 | K10: =IFERROR(F10/D10,0) -> 0 | L10: =IFERROR(G10/F10,0) -> 0 | M10: =IFERROR(SUMIFS(لاگ_فاکتور!$L$3:$L$1622,لاگ_فاکتور!$B$3:$B$1622,A10,لاگ_فاکتور!$C$3:$C$1622,B10)/F10,0) -> 0 | N10: 0
A11: 1405/07/03 | B11: 0 | C11: =IFERROR(INDEX(اطلاعات_پرسنل!$D$4:$D$59,MATCH(B11,اطلاعات_پرسنل!$A$4:$A$59,0)),"") -> فروشگاه | D11: 3 | E11: 2 | F11: =IFERROR(SUMIFS(لاگ_فاکتور!$V$3:$V$1622,لاگ_فاکتور!$B$3:$B$1622,A11,لاگ_فاکتور!$C$3:$C$1622,B11),0) -> 0 | G11: =IFERROR(SUMIFS(لاگ_فاکتور!$O$3:$O$1622,لاگ_فاکتور!$B$3:$B$1622,A11,لاگ_فاکتور!$C$3:$C$1622,B11),0) -> 0 | H11: =IFERROR(SUMIFS(لاگ_فاکتور!$N$3:$N$1622,لاگ_فاکتور!$B$3:$B$1622,A11,لاگ_فاکتور!$C$3:$C$1622,B11),0) -> 0 | I11: 0 | J11: 0 | K11: =IFERROR(F11/D11,0) -> 0 | L11: =IFERROR(G11/F11,0) -> 0 | M11: =IFERROR(SUMIFS(لاگ_فاکتور!$L$3:$L$1622,لاگ_فاکتور!$B$3:$B$1622,A11,لاگ_فاکتور!$C$3:$C$1622,B11)/F11,0) -> 0 | N11: 0 | P11: پرو لوفر
A12: 1405/07/03 | B12: 2 | C12: =IFERROR(INDEX(اطلاعات_پرسنل!$D$4:$D$59,MATCH(B12,اطلاعات_پرسنل!$A$4:$A$59,0)),"") -> ماحی حمیدپور | D12: 30 | E12: 14 | F12: =IFERROR(SUMIFS(لاگ_فاکتور!$V$3:$V$1622,لاگ_فاکتور!$B$3:$B$1622,A12,لاگ_فاکتور!$C$3:$C$1622,B12),0) -> 7 | G12: =IFERROR(SUMIFS(لاگ_فاکتور!$O$3:$O$1622,لاگ_فاکتور!$B$3:$B$1622,A12,لاگ_فاکتور!$C$3:$C$1622,B12),0) -> 58560000 | H12: =IFERROR(SUMIFS(لاگ_فاکتور!$N$3:$N$1622,لاگ_فاکتور!$B$3:$B$1622,A12,لاگ_فاکتور!$C$3:$C$1622,B12),0) -> 0 | I12: 0 | J12: 1 | K12: =IFERROR(F12/D12,0) -> 0.23333333 | L12: =IFERROR(G12/F12,0) -> 8365714.3 | M12: =IFERROR(SUMIFS(لاگ_فاکتور!$L$3:$L$1622,لاگ_فاکتور!$B$3:$B$1622,A12,لاگ_فاکتور!$C$3:$C$1622,B12)/F12,0) -> 2.5714286 | N12: 0
A13: 1405/07/03 | B13: 1 | C13: =IFERROR(INDEX(اطلاعات_پرسنل!$D$4:$D$59,MATCH(B13,اطلاعات_پرسنل!$A$4:$A$59,0)),"") -> دریا کریمی | D13: 23 | E13: 7 | F13: =IFERROR(SUMIFS(لاگ_فاکتور!$V$3:$V$1622,لاگ_فاکتور!$B$3:$B$1622,A13,لاگ_فاکتور!$C$3:$C$1622,B13),0) -> 2 | G13: =IFERROR(SUMIFS(لاگ_فاکتور!$O$3:$O$1622,لاگ_فاکتور!$B$3:$B$1622,A13,لاگ_فاکتور!$C$3:$C$1622,B13),0) -> 16118000 | H13: =IFERROR(SUMIFS(لاگ_فاکتور!$N$3:$N$1622,لاگ_فاکتور!$B$3:$B$1622,A13,لاگ_فاکتور!$C$3:$C$1622,B13),0) -> 0 | I13: 0 | J13: 1 | K13: =IFERROR(F13/D13,0) -> 0.086956522 | L13: =IFERROR(G13/F13,0) -> 8059000 | M13: =IFERROR(SUMIFS(لاگ_فاکتور!$L$3:$L$1622,لاگ_فاکتور!$B$3:$B$1622,A13,لاگ_فاکتور!$C$3:$C$1622,B13)/F13,0) -> 3.5 | N13: 0
A14: 1405/07/04 | B14: 2 | C14: =IFERROR(INDEX(اطلاعات_پرسنل!$D$4:$D$59,MATCH(B14,اطلاعات_پرسنل!$A$4:$A$59,0)),"") -> ماحی حمیدپور | D14: 1 | F14: =IFERROR(SUMIFS(لاگ_فاکتور!$V$3:$V$1622,لاگ_فاکتور!$B$3:$B$1622,A14,لاگ_فاکتور!$C$3:$C$1622,B14),0) -> 1 | G14: =IFERROR(SUMIFS(لاگ_فاکتور!$O$3:$O$1622,لاگ_فاکتور!$B$3:$B$1622,A14,لاگ_فاکتور!$C$3:$C$1622,B14),0) -> 4170000 | H14: =IFERROR(SUMIFS(لاگ_فاکتور!$N$3:$N$1622,لاگ_فاکتور!$B$3:$B$1622,A14,لاگ_فاکتور!$C$3:$C$1622,B14),0) -> 0 | I14: 0 | J14: 0 | K14: =IFERROR(F14/D14,0) -> 1 | L14: =IFERROR(G14/F14,0) -> 4170000 | M14: =IFERROR(SUMIFS(لاگ_فاکتور!$L$3:$L$1622,لاگ_فاکتور!$B$3:$B$1622,A14,لاگ_فاکتور!$C$3:$C$1622,B14)/F14,0) -> 2 | N14: 0
A15: 1405/07/04 | B15: 1 | C15: =IFERROR(INDEX(اطلاعات_پرسنل!$D$4:$D$59,MATCH(B15,اطلاعات_پرسنل!$A$4:$A$59,0)),"") -> دریا کریمی | D15: 10 | E15: 7 | F15: =IFERROR(SUMIFS(لاگ_فاکتور!$V$3:$V$1622,لاگ_فاکتور!$B$3:$B$1622,A15,لاگ_فاکتور!$C$3:$C$1622,B15),0) -> 6 | G15: =IFERROR(SUMIFS(لاگ_فاکتور!$O$3:$O$1622,لاگ_فاکتور!$B$3:$B$1622,A15,لاگ_فاکتور!$C$3:$C$1622,B15),0) -> 18860000 | H15: =IFERROR(SUMIFS(لاگ_فاکتور!$N$3:$N$1622,لاگ_فاکتور!$B$3:$B$1622,A15,لاگ_فاکتور!$C$3:$C$1622,B15),0) -> 0 | I15: 0 | J15: 0 | K15: =IFERROR(F15/D15,0) -> 0.6 | L15: =IFERROR(G15/F15,0) -> 3143333.3 | M15: =IFERROR(SUMIFS(لاگ_فاکتور!$L$3:$L$1622,لاگ_فاکتور!$B$3:$B$1622,A15,لاگ_فاکتور!$C$3:$C$1622,B15)/F15,0) -> 1.5 | N15: 0
A16: 1405/07/05 | B16: 0 | C16: =IFERROR(INDEX(اطلاعات_پرسنل!$D$4:$D$59,MATCH(B16,اطلاعات_پرسنل!$A$4:$A$59,0)),"") -> فروشگاه | D16: 5 | E16: 2 | F16: =IFERROR(SUMIFS(لاگ_فاکتور!$V$3:$V$1622,لاگ_فاکتور!$B$3:$B$1622,A16,لاگ_فاکتور!$C$3:$C$1622,B16),0) -> 0 | G16: =IFERROR(SUMIFS(لاگ_فاکتور!$O$3:$O$1622,لاگ_فاکتور!$B$3:$B$1622,A16,لاگ_فاکتور!$C$3:$C$1622,B16),0) -> 0 | H16: =IFERROR(SUMIFS(لاگ_فاکتور!$N$3:$N$1622,لاگ_فاکتور!$B$3:$B$1622,A16,لاگ_فاکتور!$C$3:$C$1622,B16),0) -> 0 | I16: 0 | J16: 0 | K16: =IFERROR(F16/D16,0) -> 0 | L16: =IFERROR(G16/F16,0) -> 0 | M16: =IFERROR(SUMIFS(لاگ_فاکتور!$L$3:$L$1622,لاگ_فاکتور!$B$3:$B$1622,A16,لاگ_فاکتور!$C$3:$C$1622,B16)/F16,0) -> 0 | N16: 0
A17: 1405/07/05 | B17: 1 | C17: =IFERROR(INDEX(اطلاعات_پرسنل!$D$4:$D$59,MATCH(B17,اطلاعات_پرسنل!$A$4:$A$59,0)),"") -> دریا کریمی | D17: 11 | E17: 2 | F17: =IFERROR(SUMIFS(لاگ_فاکتور!$V$3:$V$1622,لاگ_فاکتور!$B$3:$B$1622,A17,لاگ_فاکتور!$C$3:$C$1622,B17),0) -> 2 | G17: =IFERROR(SUMIFS(لاگ_فاکتور!$O$3:$O$1622,لاگ_فاکتور!$B$3:$B$1622,A17,لاگ_فاکتور!$C$3:$C$1622,B17),0) -> 18240000 | H17: =IFERROR(SUMIFS(لاگ_فاکتور!$N$3:$N$1622,لاگ_فاکتور!$B$3:$B$1622,A17,لاگ_فاکتور!$C$3:$C$1622,B17),0) -> 0 | I17: 0 | J17: 1 | K17: =IFERROR(F17/D17,0) -> 0.18181818 | L17: =IFERROR(G17/F17,0) -> 9120000 | M17: =IFERROR(SUMIFS(لاگ_فاکتور!$L$3:$L$1622,لاگ_فاکتور!$B$3:$B$1622,A17,لاگ_فاکتور!$C$3:$C$1622,B17)/F17,0) -> 2 | N17: 0
A18: 1405/07/06 | B18: 0 | C18: =IFERROR(INDEX(اطلاعات_پرسنل!$D$4:$D$59,MATCH(B18,اطلاعات_پرسنل!$A$4:$A$59,0)),"") -> فروشگاه | D18: 5 | E18: 2 | F18: =IFERROR(SUMIFS(لاگ_فاکتور!$V$3:$V$1622,لاگ_فاکتور!$B$3:$B$1622,A18,لاگ_فاکتور!$C$3:$C$1622,B18),0) -> 1 | G18: =IFERROR(SUMIFS(لاگ_فاکتور!$O$3:$O$1622,لاگ_فاکتور!$B$3:$B$1622,A18,لاگ_فاکتور!$C$3:$C$1622,B18),0) -> 4580000 | H18: =IFERROR(SUMIFS(لاگ_فاکتور!$N$3:$N$1622,لاگ_فاکتور!$B$3:$B$1622,A18,لاگ_فاکتور!$C$3:$C$1622,B18),0) -> 0 | I18: 0 | J18: 0 | K18: =IFERROR(F18/D18,0) -> 0.2 | L18: =IFERROR(G18/F18,0) -> 4580000 | M18: =IFERROR(SUMIFS(لاگ_فاکتور!$L$3:$L$1622,لاگ_فاکتور!$B$3:$B$1622,A18,لاگ_فاکتور!$C$3:$C$1622,B18)/F18,0) -> 1 | N18: 0
A19: 1405/07/06 | B19: 2 | C19: =IFERROR(INDEX(اطلاعات_پرسنل!$D$4:$D$59,MATCH(B19,اطلاعات_پرسنل!$A$4:$A$59,0)),"") -> ماحی حمیدپور | D19: 9 | E19: 6 | F19: =IFERROR(SUMIFS(لاگ_فاکتور!$V$3:$V$1622,لاگ_فاکتور!$B$3:$B$1622,A19,لاگ_فاکتور!$C$3:$C$1622,B19),0) -> 2 | G19: =IFERROR(SUMIFS(لاگ_فاکتور!$O$3:$O$1622,لاگ_فاکتور!$B$3:$B$1622,A19,لاگ_فاکتور!$C$3:$C$1622,B19),0) -> 26500000 | H19: =IFERROR(SUMIFS(لاگ_فاکتور!$N$3:$N$1622,لاگ_فاکتور!$B$3:$B$1622,A19,لاگ_فاکتور!$C$3:$C$1622,B19),0) -> 0 | I19: 0 | J19: 1 | K19: =IFERROR(F19/D19,0) -> 0.22222222 | L19: =IFERROR(G19/F19,0) -> 13250000 | M19: =IFERROR(SUMIFS(لاگ_فاکتور!$L$3:$L$1622,لاگ_فاکتور!$B$3:$B$1622,A19,لاگ_فاکتور!$C$3:$C$1622,B19)/F19,0) -> 2.5 | N19: 0
A20: 1405/07/07 | B20: 0 | C20: =IFERROR(INDEX(اطلاعات_پرسنل!$D$4:$D$59,MATCH(B20,اطلاعات_پرسنل!$A$4:$A$59,0)),"") -> فروشگاه | D20: 1 | E20: 1 | F20: =IFERROR(SUMIFS(لاگ_فاکتور!$V$3:$V$1622,لاگ_فاکتور!$B$3:$B$1622,A20,لاگ_فاکتور!$C$3:$C$1622,B20),0) -> 1 | G20: =IFERROR(SUMIFS(لاگ_فاکتور!$O$3:$O$1622,لاگ_فاکتور!$B$3:$B$1622,A20,لاگ_فاکتور!$C$3:$C$1622,B20),0) -> 6900000 | H20: =IFERROR(SUMIFS(لاگ_فاکتور!$N$3:$N$1622,لاگ_فاکتور!$B$3:$B$1622,A20,لاگ_فاکتور!$C$3:$C$1622,B20),0) -> 0 | I20: 0 | J20: 0 | K20: =IFERROR(F20/D20,0) -> 1 | L20: =IFERROR(G20/F20,0) -> 6900000 | M20: =IFERROR(SUMIFS(لاگ_فاکتور!$L$3:$L$1622,لاگ_فاکتور!$B$3:$B$1622,A20,لاگ_فاکتور!$C$3:$C$1622,B20)/F20,0) -> 2 | N20: 0
A21: 1405/07/07 | B21: 1 | C21: =IFERROR(INDEX(اطلاعات_پرسنل!$D$4:$D$59,MATCH(B21,اطلاعات_پرسنل!$A$4:$A$59,0)),"") -> دریا کریمی | D21: 6 | E21: 2 | F21: =IFERROR(SUMIFS(لاگ_فاکتور!$V$3:$V$1622,لاگ_فاکتور!$B$3:$B$1622,A21,لاگ_فاکتور!$C$3:$C$1622,B21),0) -> 2 | G21: =IFERROR(SUMIFS(لاگ_فاکتور!$O$3:$O$1622,لاگ_فاکتور!$B$3:$B$1622,A21,لاگ_فاکتور!$C$3:$C$1622,B21),0) -> 5460000 | H21: =IFERROR(SUMIFS(لاگ_فاکتور!$N$3:$N$1622,لاگ_فاکتور!$B$3:$B$1622,A21,لاگ_فاکتور!$C$3:$C$1622,B21),0) -> 0 | I21: 0 | J21: 0 | K21: =IFERROR(F21/D21,0) -> 0.33333333 | L21: =IFERROR(G21/F21,0) -> 2730000 | M21: =IFERROR(SUMIFS(لاگ_فاکتور!$L$3:$L$1622,لاگ_فاکتور!$B$3:$B$1622,A21,لاگ_فاکتور!$C$3:$C$1622,B21)/F21,0) -> 1 | N21: 0
A22: 1405/07/07 | B22: 2 | C22: =IFERROR(INDEX(اطلاعات_پرسنل!$D$4:$D$59,MATCH(B22,اطلاعات_پرسنل!$A$4:$A$59,0)),"") -> ماحی حمیدپور | D22: 6 | E22: 1 | F22: =IFERROR(SUMIFS(لاگ_فاکتور!$V$3:$V$1622,لاگ_فاکتور!$B$3:$B$1622,A22,لاگ_فاکتور!$C$3:$C$1622,B22),0) -> 0 | G22: =IFERROR(SUMIFS(لاگ_فاکتور!$O$3:$O$1622,لاگ_فاکتور!$B$3:$B$1622,A22,لاگ_فاکتور!$C$3:$C$1622,B22),0) -> 0 | H22: =IFERROR(SUMIFS(لاگ_فاکتور!$N$3:$N$1622,لاگ_فاکتور!$B$3:$B$1622,A22,لاگ_فاکتور!$C$3:$C$1622,B22),0) -> 0 | I22: 0 | J22: 0 | K22: =IFERROR(F22/D22,0) -> 0 | L22: =IFERROR(G22/F22,0) -> 0 | M22: =IFERROR(SUMIFS(لاگ_فاکتور!$L$3:$L$1622,لاگ_فاکتور!$B$3:$B$1622,A22,لاگ_فاکتور!$C$3:$C$1622,B22)/F22,0) -> 0 | N22: 0
A23: 1405/07/08 | B23: 0 | C23: =IFERROR(INDEX(اطلاعات_پرسنل!$D$4:$D$59,MATCH(B23,اطلاعات_پرسنل!$A$4:$A$59,0)),"") -> فروشگاه | D23: 6 | E23: 4 | F23: =IFERROR(SUMIFS(لاگ_فاکتور!$V$3:$V$1622,لاگ_فاکتور!$B$3:$B$1622,A23,لاگ_فاکتور!$C$3:$C$1622,B23),0) -> 0 | G23: =IFERROR(SUMIFS(لاگ_فاکتور!$O$3:$O$1622,لاگ_فاکتور!$B$3:$B$1622,A23,لاگ_فاکتور!$C$3:$C$1622,B23),0) -> 0 | H23: =IFERROR(SUMIFS(لاگ_فاکتور!$N$3:$N$1622,لاگ_فاکتور!$B$3:$B$1622,A23,لاگ_فاکتور!$C$3:$C$1622,B23),0) -> 0 | I23: 0 | J23: 0 | K23: =IFERROR(F23/D23,0) -> 0 | L23: =IFERROR(G23/F23,0) -> 0 | M23: =IFERROR(SUMIFS(لاگ_فاکتور!$L$3:$L$1622,لاگ_فاکتور!$B$3:$B$1622,A23,لاگ_فاکتور!$C$3:$C$1622,B23)/F23,0) -> 0 | N23: 0 | P23: پرو لوفر
A24: 1405/07/08 | B24: 1 | C24: =IFERROR(INDEX(اطلاعات_پرسنل!$D$4:$D$59,MATCH(B24,اطلاعات_پرسنل!$A$4:$A$59,0)),"") -> دریا کریمی | D24: 4 | E24: 3 | F24: =IFERROR(SUMIFS(لاگ_فاکتور!$V$3:$V$1622,لاگ_فاکتور!$B$3:$B$1622,A24,لاگ_فاکتور!$C$3:$C$1622,B24),0) -> 3 | G24: =IFERROR(SUMIFS(لاگ_فاکتور!$O$3:$O$1622,لاگ_فاکتور!$B$3:$B$1622,A24,لاگ_فاکتور!$C$3:$C$1622,B24),0) -> 9710000 | H24: =IFERROR(SUMIFS(لاگ_فاکتور!$N$3:$N$1622,لاگ_فاکتور!$B$3:$B$1622,A24,لاگ_فاکتور!$C$3:$C$1622,B24),0) -> 0 | I24: 0 | J24: 0 | K24: =IFERROR(F24/D24,0) -> 0.75 | L24: =IFERROR(G24/F24,0) -> 3236666.7 | M24: =IFERROR(SUMIFS(لاگ_فاکتور!$L$3:$L$1622,لاگ_فاکتور!$B$3:$B$1622,A24,لاگ_فاکتور!$C$3:$C$1622,B24)/F24,0) -> 1.3333333 | N24: 0
A25: 1405/07/08 | B25: 2 | C25: =IFERROR(INDEX(اطلاعات_پرسنل!$D$4:$D$59,MATCH(B25,اطلاعات_پرسنل!$A$4:$A$59,0)),"") -> ماحی حمیدپور | D25: 8 | E25: 4 | F25: =IFERROR(SUMIFS(لاگ_فاکتور!$V$3:$V$1622,لاگ_فاکتور!$B$3:$B$1622,A25,لاگ_فاکتور!$C$3:$C$1622,B25),0) -> 2 | G25: =IFERROR(SUMIFS(لاگ_فاکتور!$O$3:$O$1622,لاگ_فاکتور!$B$3:$B$1622,A25,لاگ_فاکتور!$C$3:$C$1622,B25),0) -> 7740000 | H25: =IFERROR(SUMIFS(لاگ_فاکتور!$N$3:$N$1622,لاگ_فاکتور!$B$3:$B$1622,A25,لاگ_فاکتور!$C$3:$C$1622,B25),0) -> 0 | I25: 0 | J25: 0 | K25: =IFERROR(F25/D25,0) -> 0.25 | L25: =IFERROR(G25/F25,0) -> 3870000 | M25: =IFERROR(SUMIFS(لاگ_فاکتور!$L$3:$L$1622,لاگ_فاکتور!$B$3:$B$1622,A25,لاگ_فاکتور!$C$3:$C$1622,B25)/F25,0) -> 1.5 | N25: 0
A26: 1405/07/09 | B26: 0 | C26: =IFERROR(INDEX(اطلاعات_پرسنل!$D$4:$D$59,MATCH(B26,اطلاعات_پرسنل!$A$4:$A$59,0)),"") -> فروشگاه | D26: 1 | F26: =IFERROR(SUMIFS(لاگ_فاکتور!$V$3:$V$1622,لاگ_فاکتور!$B$3:$B$1622,A26,لاگ_فاکتور!$C$3:$C$1622,B26),0) -> 0 | G26: =IFERROR(SUMIFS(لاگ_فاکتور!$O$3:$O$1622,لاگ_فاکتور!$B$3:$B$1622,A26,لاگ_فاکتور!$C$3:$C$1622,B26),0) -> 0 | H26: =IFERROR(SUMIFS(لاگ_فاکتور!$N$3:$N$1622,لاگ_فاکتور!$B$3:$B$1622,A26,لاگ_فاکتور!$C$3:$C$1622,B26),0) -> 0 | I26: 0 | J26: 0 | K26: =IFERROR(F26/D26,0) -> 0 | L26: =IFERROR(G26/F26,0) -> 0 | M26: =IFERROR(SUMIFS(لاگ_فاکتور!$L$3:$L$1622,لاگ_فاکتور!$B$3:$B$1622,A26,لاگ_فاکتور!$C$3:$C$1622,B26)/F26,0) -> 0 | N26: 0
A27: 1405/07/09 | B27: 1 | C27: =IFERROR(INDEX(اطلاعات_پرسنل!$D$4:$D$59,MATCH(B27,اطلاعات_پرسنل!$A$4:$A$59,0)),"") -> دریا کریمی | D27: 21 | E27: 4 | F27: =IFERROR(SUMIFS(لاگ_فاکتور!$V$3:$V$1622,لاگ_فاکتور!$B$3:$B$1622,A27,لاگ_فاکتور!$C$3:$C$1622,B27),0) -> 3 | G27: =IFERROR(SUMIFS(لاگ_فاکتور!$O$3:$O$1622,لاگ_فاکتور!$B$3:$B$1622,A27,لاگ_فاکتور!$C$3:$C$1622,B27),0) -> 7060000 | H27: =IFERROR(SUMIFS(لاگ_فاکتور!$N$3:$N$1622,لاگ_فاکتور!$B$3:$B$1622,A27,لاگ_فاکتور!$C$3:$C$1622,B27),0) -> 2712000 | I27: 0 | J27: 0 | K27: =IFERROR(F27/D27,0) -> 0.14285714 | L27: =IFERROR(G27/F27,0) -> 2353333.3 | M27: =IFERROR(SUMIFS(لاگ_فاکتور!$L$3:$L$1622,لاگ_فاکتور!$B$3:$B$1622,A27,لاگ_فاکتور!$C$3:$C$1622,B27)/F27,0) -> 1 | N27: 0 | P27: پرو صندل
A28: 1405/07/09 | B28: 2 | C28: =IFERROR(INDEX(اطلاعات_پرسنل!$D$4:$D$59,MATCH(B28,اطلاعات_پرسنل!$A$4:$A$59,0)),"") -> ماحی حمیدپور | D28: 28 | E28: 6 | F28: =IFERROR(SUMIFS(لاگ_فاکتور!$V$3:$V$1622,لاگ_فاکتور!$B$3:$B$1622,A28,لاگ_فاکتور!$C$3:$C$1622,B28),0) -> 5 | G28: =IFERROR(SUMIFS(لاگ_فاکتور!$O$3:$O$1622,لاگ_فاکتور!$B$3:$B$1622,A28,لاگ_فاکتور!$C$3:$C$1622,B28),0) -> 33100000 | H28: =IFERROR(SUMIFS(لاگ_فاکتور!$N$3:$N$1622,لاگ_فاکتور!$B$3:$B$1622,A28,لاگ_فاکتور!$C$3:$C$1622,B28),0) -> 2792000 | I28: 0 | J28: 1 | K28: =IFERROR(F28/D28,0) -> 0.17857143 | L28: =IFERROR(G28/F28,0) -> 6620000 | M28: =IFERROR(SUMIFS(لاگ_فاکتور!$L$3:$L$1622,لاگ_فاکتور!$B$3:$B$1622,A28,لاگ_فاکتور!$C$3:$C$1622,B28)/F28,0) -> 2.2 | N28: 0
A29: 1405/07/10 | B29: 0 | C29: =IFERROR(INDEX(اطلاعات_پرسنل!$D$4:$D$59,MATCH(B29,اطلاعات_پرسنل!$A$4:$A$59,0)),"") -> فروشگاه | D29: 2 | F29: =IFERROR(SUMIFS(لاگ_فاکتور!$V$3:$V$1622,لاگ_فاکتور!$B$3:$B$1622,A29,لاگ_فاکتور!$C$3:$C$1622,B29),0) -> 0 | G29: =IFERROR(SUMIFS(لاگ_فاکتور!$O$3:$O$1622,لاگ_فاکتور!$B$3:$B$1622,A29,لاگ_فاکتور!$C$3:$C$1622,B29),0) -> 0 | H29: =IFERROR(SUMIFS(لاگ_فاکتور!$N$3:$N$1622,لاگ_فاکتور!$B$3:$B$1622,A29,لاگ_فاکتور!$C$3:$C$1622,B29),0) -> 0 | I29: 0 | J29: 0 | K29: =IFERROR(F29/D29,0) -> 0 | L29: =IFERROR(G29/F29,0) -> 0 | M29: =IFERROR(SUMIFS(لاگ_فاکتور!$L$3:$L$1622,لاگ_فاکتور!$B$3:$B$1622,A29,لاگ_فاکتور!$C$3:$C$1622,B29)/F29,0) -> 0 | N29: 0
A30: 1405/07/10 | B30: 1 | C30: =IFERROR(INDEX(اطلاعات_پرسنل!$D$4:$D$59,MATCH(B30,اطلاعات_پرسنل!$A$4:$A$59,0)),"") -> دریا کریمی | D30: 21 | E30: 3 | F30: =IFERROR(SUMIFS(لاگ_فاکتور!$V$3:$V$1622,لاگ_فاکتور!$B$3:$B$1622,A30,لاگ_فاکتور!$C$3:$C$1622,B30),0) -> 4 | G30: =IFERROR(SUMIFS(لاگ_فاکتور!$O$3:$O$1622,لاگ_فاکتور!$B$3:$B$1622,A30,لاگ_فاکتور!$C$3:$C$1622,B30),0) -> 23990000 | H30: =IFERROR(SUMIFS(لاگ_فاکتور!$N$3:$N$1622,لاگ_فاکتور!$B$3:$B$1622,A30,لاگ_فاکتور!$C$3:$C$1622,B30),0) -> 880000 | I30: 0 | J30: 0 | K30: =IFERROR(F30/D30,0) -> 0.19047619 | L30: =IFERROR(G30/F30,0) -> 5997500 | M30: =IFERROR(SUMIFS(لاگ_فاکتور!$L$3:$L$1622,لاگ_فاکتور!$B$3:$B$1622,A30,لاگ_فاکتور!$C$3:$C$1622,B30)/F30,0) -> 1.75 | N30: 0
A31: 1405/07/10 | B31: 2 | C31: =IFERROR(INDEX(اطلاعات_پرسنل!$D$4:$D$59,MATCH(B31,اطلاعات_پرسنل!$A$4:$A$59,0)),"") -> ماحی حمیدپور | D31: 11 | E31: 1 | F31: =IFERROR(SUMIFS(لاگ_فاکتور!$V$3:$V$1622,لاگ_فاکتور!$B$3:$B$1622,A31,لاگ_فاکتور!$C$3:$C$1622,B31),0) -> 0 | G31: =IFERROR(SUMIFS(لاگ_فاکتور!$O$3:$O$1622,لاگ_فاکتور!$B$3:$B$1622,A31,لاگ_فاکتور!$C$3:$C$1622,B31),0) -> 0 | H31: =IFERROR(SUMIFS(لاگ_فاکتور!$N$3:$N$1622,لاگ_فاکتور!$B$3:$B$1622,A31,لاگ_فاکتور!$C$3:$C$1622,B31),0) -> 0 | I31: 0 | J31: 0 | K31: =IFERROR(F31/D31,0) -> 0 | L31: =IFERROR(G31/F31,0) -> 0 | M31: =IFERROR(SUMIFS(لاگ_فاکتور!$L$3:$L$1622,لاگ_فاکتور!$B$3:$B$1622,A31,لاگ_فاکتور!$C$3:$C$1622,B31)/F31,0) -> 0 | N31: 0
A32: 1405/07/11 | B32: 2 | C32: =IFERROR(INDEX(اطلاعات_پرسنل!$D$4:$D$59,MATCH(B32,اطلاعات_پرسنل!$A$4:$A$59,0)),"") -> ماحی حمیدپور | D32: 3 | E32: 1 | F32: =IFERROR(SUMIFS(لاگ_فاکتور!$V$3:$V$1622,لاگ_فاکتور!$B$3:$B$1622,A32,لاگ_فاکتور!$C$3:$C$1622,B32),0) -> 1 | G32: =IFERROR(SUMIFS(لاگ_فاکتور!$O$3:$O$1622,لاگ_فاکتور!$B$3:$B$1622,A32,لاگ_فاکتور!$C$3:$C$1622,B32),0) -> 2880000 | H32: =IFERROR(SUMIFS(لاگ_فاکتور!$N$3:$N$1622,لاگ_فاکتور!$B$3:$B$1622,A32,لاگ_فاکتور!$C$3:$C$1622,B32),0) -> 0 | I32: 0 | J32: 0 | K32: =IFERROR(F32/D32,0) -> 0.33333333 | L32: =IFERROR(G32/F32,0) -> 2880000 | M32: =IFERROR(SUMIFS(لاگ_فاکتور!$L$3:$L$1622,لاگ_فاکتور!$B$3:$B$1622,A32,لاگ_فاکتور!$C$3:$C$1622,B32)/F32,0) -> 1 | N32: 0
A33: 1405/07/11 | B33: 1 | C33: =IFERROR(INDEX(اطلاعات_پرسنل!$D$4:$D$59,MATCH(B33,اطلاعات_پرسنل!$A$4:$A$59,0)),"") -> دریا کریمی | D33: 8 | E33: 4 | F33: =IFERROR(SUMIFS(لاگ_فاکتور!$V$3:$V$1622,لاگ_فاکتور!$B$3:$B$1622,A33,لاگ_فاکتور!$C$3:$C$1622,B33),0) -> 2 | G33: =IFERROR(SUMIFS(لاگ_فاکتور!$O$3:$O$1622,لاگ_فاکتور!$B$3:$B$1622,A33,لاگ_فاکتور!$C$3:$C$1622,B33),0) -> 6230000 | H33: =IFERROR(SUMIFS(لاگ_فاکتور!$N$3:$N$1622,لاگ_فاکتور!$B$3:$B$1622,A33,لاگ_فاکتور!$C$3:$C$1622,B33),0) -> 0 | I33: 0 | J33: 0 | K33: =IFERROR(F33/D33,0) -> 0.25 | L33: =IFERROR(G33/F33,0) -> 3115000 | M33: =IFERROR(SUMIFS(لاگ_فاکتور!$L$3:$L$1622,لاگ_فاکتور!$B$3:$B$1622,A33,لاگ_فاکتور!$C$3:$C$1622,B33)/F33,0) -> 1 | N33: 0
A34: 1405/07/12 | B34: 0 | C34: =IFERROR(INDEX(اطلاعات_پرسنل!$D$4:$D$59,MATCH(B34,اطلاعات_پرسنل!$A$4:$A$59,0)),"") -> فروشگاه | D34: 2 | F34: =IFERROR(SUMIFS(لاگ_فاکتور!$V$3:$V$1622,لاگ_فاکتور!$B$3:$B$1622,A34,لاگ_فاکتور!$C$3:$C$1622,B34),0) -> 0 | G34: =IFERROR(SUMIFS(لاگ_فاکتور!$O$3:$O$1622,لاگ_فاکتور!$B$3:$B$1622,A34,لاگ_فاکتور!$C$3:$C$1622,B34),0) -> 0 | H34: =IFERROR(SUMIFS(لاگ_فاکتور!$N$3:$N$1622,لاگ_فاکتور!$B$3:$B$1622,A34,لاگ_فاکتور!$C$3:$C$1622,B34),0) -> 0 | I34: 0 | J34: 0 | K34: =IFERROR(F34/D34,0) -> 0 | L34: =IFERROR(G34/F34,0) -> 0 | M34: =IFERROR(SUMIFS(لاگ_فاکتور!$L$3:$L$1622,لاگ_فاکتور!$B$3:$B$1622,A34,لاگ_فاکتور!$C$3:$C$1622,B34)/F34,0) -> 0 | N34: 0
A35: 1405/07/12 | B35: 1 | C35: =IFERROR(INDEX(اطلاعات_پرسنل!$D$4:$D$59,MATCH(B35,اطلاعات_پرسنل!$A$4:$A$59,0)),"") -> دریا کریمی | D35: 8 | E35: 1 | F35: =IFERROR(SUMIFS(لاگ_فاکتور!$V$3:$V$1622,لاگ_فاکتور!$B$3:$B$1622,A35,لاگ_فاکتور!$C$3:$C$1622,B35),0) -> 0 | G35: =IFERROR(SUMIFS(لاگ_فاکتور!$O$3:$O$1622,لاگ_فاکتور!$B$3:$B$1622,A35,لاگ_فاکتور!$C$3:$C$1622,B35),0) -> 1068000 | H35: =IFERROR(SUMIFS(لاگ_فاکتور!$N$3:$N$1622,لاگ_فاکتور!$B$3:$B$1622,A35,لاگ_فاکتور!$C$3:$C$1622,B35),0) -> 0 | I35: 0 | J35: 0 | K35: =IFERROR(F35/D35,0) -> 0 | L35: =IFERROR(G35/F35,0) -> 0 | M35: =IFERROR(SUMIFS(لاگ_فاکتور!$L$3:$L$1622,لاگ_فاکتور!$B$3:$B$1622,A35,لاگ_فاکتور!$C$3:$C$1622,B35)/F35,0) -> 0 | N35: 0 | P35: 1میلیون 68 هزار تومان از خرید پرسنلی تسویه شد.
A36: 1405/07/13 | B36: 0 | C36: =IFERROR(INDEX(اطلاعات_پرسنل!$D$4:$D$59,MATCH(B36,اطلاعات_پرسنل!$A$4:$A$59,0)),"") -> فروشگاه | D36: 3 | E36: 1 | F36: =IFERROR(SUMIFS(لاگ_فاکتور!$V$3:$V$1622,لاگ_فاکتور!$B$3:$B$1622,A36,لاگ_فاکتور!$C$3:$C$1622,B36),0) -> 0 | G36: =IFERROR(SUMIFS(لاگ_فاکتور!$O$3:$O$1622,لاگ_فاکتور!$B$3:$B$1622,A36,لاگ_فاکتور!$C$3:$C$1622,B36),0) -> 0 | H36: =IFERROR(SUMIFS(لاگ_فاکتور!$N$3:$N$1622,لاگ_فاکتور!$B$3:$B$1622,A36,لاگ_فاکتور!$C$3:$C$1622,B36),0) -> 0 | I36: 0 | J36: 0 | K36: =IFERROR(F36/D36,0) -> 0 | L36: =IFERROR(G36/F36,0) -> 0 | M36: =IFERROR(SUMIFS(لاگ_فاکتور!$L$3:$L$1622,لاگ_فاکتور!$B$3:$B$1622,A36,لاگ_فاکتور!$C$3:$C$1622,B36)/F36,0) -> 0 | N36: 0
A37: 1405/07/13 | B37: 2 | C37: =IFERROR(INDEX(اطلاعات_پرسنل!$D$4:$D$59,MATCH(B37,اطلاعات_پرسنل!$A$4:$A$59,0)),"") -> ماحی حمیدپور | D37: 6 | E37: 1 | F37: =IFERROR(SUMIFS(لاگ_فاکتور!$V$3:$V$1622,لاگ_فاکتور!$B$3:$B$1622,A37,لاگ_فاکتور!$C$3:$C$1622,B37),0) -> 1 | G37: =IFERROR(SUMIFS(لاگ_فاکتور!$O$3:$O$1622,لاگ_فاکتور!$B$3:$B$1622,A37,لاگ_فاکتور!$C$3:$C$1622,B37),0) -> 7160000 | H37: =IFERROR(SUMIFS(لاگ_فاکتور!$N$3:$N$1622,لاگ_فاکتور!$B$3:$B$1622,A37,لاگ_فاکتور!$C$3:$C$1622,B37),0) -> 0 | I37: 0 | J37: 0 | K37: =IFERROR(F37/D37,0) -> 0.16666667 | L37: =IFERROR(G37/F37,0) -> 7160000 | M37: =IFERROR(SUMIFS(لاگ_فاکتور!$L$3:$L$1622,لاگ_فاکتور!$B$3:$B$1622,A37,لاگ_فاکتور!$C$3:$C$1622,B37)/F37,0) -> 2 | N37: 0
A38: 1405/07/14 | B38: 0 | C38: =IFERROR(INDEX(اطلاعات_پرسنل!$D$4:$D$59,MATCH(B38,اطلاعات_پرسنل!$A$4:$A$59,0)),"") -> فروشگاه | D38: 2 | F38: =IFERROR(SUMIFS(لاگ_فاکتور!$V$3:$V$1622,لاگ_فاکتور!$B$3:$B$1622,A38,لاگ_فاکتور!$C$3:$C$1622,B38),0) -> 0 | G38: =IFERROR(SUMIFS(لاگ_فاکتور!$O$3:$O$1622,لاگ_فاکتور!$B$3:$B$1622,A38,لاگ_فاکتور!$C$3:$C$1622,B38),0) -> 0 | H38: =IFERROR(SUMIFS(لاگ_فاکتور!$N$3:$N$1622,لاگ_فاکتور!$B$3:$B$1622,A38,لاگ_فاکتور!$C$3:$C$1622,B38),0) -> 0 | I38: 0 | J38: 0 | K38: =IFERROR(F38/D38,0) -> 0 | L38: =IFERROR(G38/F38,0) -> 0 | M38: =IFERROR(SUMIFS(لاگ_فاکتور!$L$3:$L$1622,لاگ_فاکتور!$B$3:$B$1622,A38,لاگ_فاکتور!$C$3:$C$1622,B38)/F38,0) -> 0 | N38: 0
A39: 1405/07/14 | B39: 1 | C39: =IFERROR(INDEX(اطلاعات_پرسنل!$D$4:$D$59,MATCH(B39,اطلاعات_پرسنل!$A$4:$A$59,0)),"") -> دریا کریمی | D39: 8 | E39: 3 | F39: =IFERROR(SUMIFS(لاگ_فاکتور!$V$3:$V$1622,لاگ_فاکتور!$B$3:$B$1622,A39,لاگ_فاکتور!$C$3:$C$1622,B39),0) -> 2 | G39: =IFERROR(SUMIFS(لاگ_فاکتور!$O$3:$O$1622,لاگ_فاکتور!$B$3:$B$1622,A39,لاگ_فاکتور!$C$3:$C$1622,B39),0) -> 8000000 | H39: =IFERROR(SUMIFS(لاگ_فاکتور!$N$3:$N$1622,لاگ_فاکتور!$B$3:$B$1622,A39,لاگ_فاکتور!$C$3:$C$1622,B39),0) -> 368000 | I39: 0 | J39: 0 | K39: =IFERROR(F39/D39,0) -> 0.25 | L39: =IFERROR(G39/F39,0) -> 4000000 | M39: =IFERROR(SUMIFS(لاگ_فاکتور!$L$3:$L$1622,لاگ_فاکتور!$B$3:$B$1622,A39,لاگ_فاکتور!$C$3:$C$1622,B39)/F39,0) -> 2 | N39: 0
A40: 1405/07/15 | B40: 0 | C40: =IFERROR(INDEX(اطلاعات_پرسنل!$D$4:$D$59,MATCH(B40,اطلاعات_پرسنل!$A$4:$A$59,0)),"") -> فروشگاه | D40: 4 | E40: 1 | F40: =IFERROR(SUMIFS(لاگ_فاکتور!$V$3:$V$1622,لاگ_فاکتور!$B$3:$B$1622,A40,لاگ_فاکتور!$C$3:$C$1622,B40),0) -> 0 | G40: =IFERROR(SUMIFS(لاگ_فاکتور!$O$3:$O$1622,لاگ_فاکتور!$B$3:$B$1622,A40,لاگ_فاکتور!$C$3:$C$1622,B40),0) -> 0 | H40: =IFERROR(SUMIFS(لاگ_فاکتور!$N$3:$N$1622,لاگ_فاکتور!$B$3:$B$1622,A40,لاگ_فاکتور!$C$3:$C$1622,B40),0) -> 0 | I40: 0 | J40: 0 | K40: =IFERROR(F40/D40,0) -> 0 | L40: =IFERROR(G40/F40,0) -> 0 | M40: =IFERROR(SUMIFS(لاگ_فاکتور!$L$3:$L$1622,لاگ_فاکتور!$B$3:$B$1622,A40,لاگ_فاکتور!$C$3:$C$1622,B40)/F40,0) -> 0 | N40: 0 | P40: پرو لوفر
A41: 1405/07/15 | B41: 1 | C41: =IFERROR(INDEX(اطلاعات_پرسنل!$D$4:$D$59,MATCH(B41,اطلاعات_پرسنل!$A$4:$A$59,0)),"") -> دریا کریمی | D41: 6 | E41: 1 | F41: =IFERROR(SUMIFS(لاگ_فاکتور!$V$3:$V$1622,لاگ_فاکتور!$B$3:$B$1622,A41,لاگ_فاکتور!$C$3:$C$1622,B41),0) -> 1 | G41: =IFERROR(SUMIFS(لاگ_فاکتور!$O$3:$O$1622,لاگ_فاکتور!$B$3:$B$1622,A41,لاگ_فاکتور!$C$3:$C$1622,B41),0) -> 23070000 | H41: =IFERROR(SUMIFS(لاگ_فاکتور!$N$3:$N$1622,لاگ_فاکتور!$B$3:$B$1622,A41,لاگ_فاکتور!$C$3:$C$1622,B41),0) -> 820000 | I41: 0 | J41: 1 | K41: =IFERROR(F41/D41,0) -> 0.16666667 | L41: =IFERROR(G41/F41,0) -> 23070000 | M41: =IFERROR(SUMIFS(لاگ_فاکتور!$L$3:$L$1622,لاگ_فاکتور!$B$3:$B$1622,A41,لاگ_فاکتور!$C$3:$C$1622,B41)/F41,0) -> 5 | N41: 0
A42: 1405/07/15 | B42: 2 | C42: =IFERROR(INDEX(اطلاعات_پرسنل!$D$4:$D$59,MATCH(B42,اطلاعات_پرسنل!$A$4:$A$59,0)),"") -> ماحی حمیدپور | D42: 7 | E42: 5 | F42: =IFERROR(SUMIFS(لاگ_فاکتور!$V$3:$V$1622,لاگ_فاکتور!$B$3:$B$1622,A42,لاگ_فاکتور!$C$3:$C$1622,B42),0) -> 1 | G42: =IFERROR(SUMIFS(لاگ_فاکتور!$O$3:$O$1622,لاگ_فاکتور!$B$3:$B$1622,A42,لاگ_فاکتور!$C$3:$C$1622,B42),0) -> 1180000 | H42: =IFERROR(SUMIFS(لاگ_فاکتور!$N$3:$N$1622,لاگ_فاکتور!$B$3:$B$1622,A42,لاگ_فاکتور!$C$3:$C$1622,B42),0) -> 0 | I42: 0 | J42: 0 | K42: =IFERROR(F42/D42,0) -> 0.14285714 | L42: =IFERROR(G42/F42,0) -> 1180000 | M42: =IFERROR(SUMIFS(لاگ_فاکتور!$L$3:$L$1622,لاگ_فاکتور!$B$3:$B$1622,A42,لاگ_فاکتور!$C$3:$C$1622,B42)/F42,0) -> 1 | N42: 0
A43: 1405/07/16 | B43: 0 | C43: =IFERROR(INDEX(اطلاعات_پرسنل!$D$4:$D$59,MATCH(B43,اطلاعات_پرسنل!$A$4:$A$59,0)),"") -> فروشگاه | F43: =IFERROR(SUMIFS(لاگ_فاکتور!$V$3:$V$1622,لاگ_فاکتور!$B$3:$B$1622,A43,لاگ_فاکتور!$C$3:$C$1622,B43),0) -> 0 | G43: =IFERROR(SUMIFS(لاگ_فاکتور!$O$3:$O$1622,لاگ_فاکتور!$B$3:$B$1622,A43,لاگ_فاکتور!$C$3:$C$1622,B43),0) -> 0 | H43: =IFERROR(SUMIFS(لاگ_فاکتور!$N$3:$N$1622,لاگ_فاکتور!$B$3:$B$1622,A43,لاگ_فاکتور!$C$3:$C$1622,B43),0) -> 0 | I43: 0 | J43: 0 | K43: =IFERROR(F43/D43,0) -> 0 | L43: =IFERROR(G43/F43,0) -> 0 | M43: =IFERROR(SUMIFS(لاگ_فاکتور!$L$3:$L$1622,لاگ_فاکتور!$B$3:$B$1622,A43,لاگ_فاکتور!$C$3:$C$1622,B43)/F43,0) -> 0 | N43: 0
A44: 1405/07/16 | B44: 1 | C44: =IFERROR(INDEX(اطلاعات_پرسنل!$D$4:$D$59,MATCH(B44,اطلاعات_پرسنل!$A$4:$A$59,0)),"") -> دریا کریمی | D44: 19 | E44: 7 | F44: =IFERROR(SUMIFS(لاگ_فاکتور!$V$3:$V$1622,لاگ_فاکتور!$B$3:$B$1622,A44,لاگ_فاکتور!$C$3:$C$1622,B44),0) -> 6 | G44: =IFERROR(SUMIFS(لاگ_فاکتور!$O$3:$O$1622,لاگ_فاکتور!$B$3:$B$1622,A44,لاگ_فاکتور!$C$3:$C$1622,B44),0) -> 23600000 | H44: =IFERROR(SUMIFS(لاگ_فاکتور!$N$3:$N$1622,لاگ_فاکتور!$B$3:$B$1622,A44,لاگ_فاکتور!$C$3:$C$1622,B44),0) -> 0 | I44: 0 | J44: 0 | K44: =IFERROR(F44/D44,0) -> 0.31578947 | L44: =IFERROR(G44/F44,0) -> 3933333.3 | M44: =IFERROR(SUMIFS(لاگ_فاکتور!$L$3:$L$1622,لاگ_فاکتور!$B$3:$B$1622,A44,لاگ_فاکتور!$C$3:$C$1622,B44)/F44,0) -> 1.3333333 | N44: 0
A45: 1405/07/16 | B45: 2 | C45: =IFERROR(INDEX(اطلاعات_پرسنل!$D$4:$D$59,MATCH(B45,اطلاعات_پرسنل!$A$4:$A$59,0)),"") -> ماحی حمیدپور | D45: 15 | E45: 5 | F45: =IFERROR(SUMIFS(لاگ_فاکتور!$V$3:$V$1622,لاگ_فاکتور!$B$3:$B$1622,A45,لاگ_فاکتور!$C$3:$C$1622,B45),0) -> 4 | G45: =IFERROR(SUMIFS(لاگ_فاکتور!$O$3:$O$1622,لاگ_فاکتور!$B$3:$B$1622,A45,لاگ_فاکتور!$C$3:$C$1622,B45),0) -> 14340000 | H45: =IFERROR(SUMIFS(لاگ_فاکتور!$N$3:$N$1622,لاگ_فاکتور!$B$3:$B$1622,A45,لاگ_فاکتور!$C$3:$C$1622,B45),0) -> 0 | I45: 0 | J45: 0 | K45: =IFERROR(F45/D45,0) -> 0.26666667 | L45: =IFERROR(G45/F45,0) -> 3585000 | M45: =IFERROR(SUMIFS(لاگ_فاکتور!$L$3:$L$1622,لاگ_فاکتور!$B$3:$B$1622,A45,لاگ_فاکتور!$C$3:$C$1622,B45)/F45,0) -> 1.25 | N45: 0
A46: 1405/07/17 | B46: 0 | C46: =IFERROR(INDEX(اطلاعات_پرسنل!$D$4:$D$59,MATCH(B46,اطلاعات_پرسنل!$A$4:$A$59,0)),"") -> فروشگاه | F46: =IFERROR(SUMIFS(لاگ_فاکتور!$V$3:$V$1622,لاگ_فاکتور!$B$3:$B$1622,A46,لاگ_فاکتور!$C$3:$C$1622,B46),0) -> 0 | G46: =IFERROR(SUMIFS(لاگ_فاکتور!$O$3:$O$1622,لاگ_فاکتور!$B$3:$B$1622,A46,لاگ_فاکتور!$C$3:$C$1622,B46),0) -> 0 | H46: =IFERROR(SUMIFS(لاگ_فاکتور!$N$3:$N$1622,لاگ_فاکتور!$B$3:$B$1622,A46,لاگ_فاکتور!$C$3:$C$1622,B46),0) -> 0 | I46: 0 | J46: 0 | K46: =IFERROR(F46/D46,0) -> 0 | L46: =IFERROR(G46/F46,0) -> 0 | M46: =IFERROR(SUMIFS(لاگ_فاکتور!$L$3:$L$1622,لاگ_فاکتور!$B$3:$B$1622,A46,لاگ_فاکتور!$C$3:$C$1622,B46)/F46,0) -> 0 | N46: 0
A47: 1405/07/17 | B47: 2 | C47: =IFERROR(INDEX(اطلاعات_پرسنل!$D$4:$D$59,MATCH(B47,اطلاعات_پرسنل!$A$4:$A$59,0)),"") -> ماحی حمیدپور | D47: 27 | E47: 7 | F47: =IFERROR(SUMIFS(لاگ_فاکتور!$V$3:$V$1622,لاگ_فاکتور!$B$3:$B$1622,A47,لاگ_فاکتور!$C$3:$C$1622,B47),0) -> 6 | G47: =IFERROR(SUMIFS(لاگ_فاکتور!$O$3:$O$1622,لاگ_فاکتور!$B$3:$B$1622,A47,لاگ_فاکتور!$C$3:$C$1622,B47),0) -> 25300000 | H47: =IFERROR(SUMIFS(لاگ_فاکتور!$N$3:$N$1622,لاگ_فاکتور!$B$3:$B$1622,A47,لاگ_فاکتور!$C$3:$C$1622,B47),0) -> 0 | I47: 0 | J47: 0 | K47: =IFERROR(F47/D47,0) -> 0.22222222 | L47: =IFERROR(G47/F47,0) -> 4216666.7 | M47: =IFERROR(SUMIFS(لاگ_فاکتور!$L$3:$L$1622,لاگ_فاکتور!$B$3:$B$1622,A47,لاگ_فاکتور!$C$3:$C$1622,B47)/F47,0) -> 1.1666667 | N47: 0
A48: 1405/07/17 | B48: 1 | C48: =IFERROR(INDEX(اطلاعات_پرسنل!$D$4:$D$59,MATCH(B48,اطلاعات_پرسنل!$A$4:$A$59,0)),"") -> دریا کریمی | D48: 17 | E48: 6 | F48: =IFERROR(SUMIFS(لاگ_فاکتور!$V$3:$V$1622,لاگ_فاکتور!$B$3:$B$1622,A48,لاگ_فاکتور!$C$3:$C$1622,B48),0) -> 5 | G48: =IFERROR(SUMIFS(لاگ_فاکتور!$O$3:$O$1622,لاگ_فاکتور!$B$3:$B$1622,A48,لاگ_فاکتور!$C$3:$C$1622,B48),0) -> 23228000 | H48: =IFERROR(SUMIFS(لاگ_فاکتور!$N$3:$N$1622,لاگ_فاکتور!$B$3:$B$1622,A48,لاگ_فاکتور!$C$3:$C$1622,B48),0) -> 0 | I48: 0 | J48: 0 | K48: =IFERROR(F48/D48,0) -> 0.29411765 | L48: =IFERROR(G48/F48,0) -> 4645600 | M48: =IFERROR(SUMIFS(لاگ_فاکتور!$L$3:$L$1622,لاگ_فاکتور!$B$3:$B$1622,A48,لاگ_فاکتور!$C$3:$C$1622,B48)/F48,0) -> 1.8 | N48: 0
A49: 1405/07/18 | B49: 1 | C49: =IFERROR(INDEX(اطلاعات_پرسنل!$D$4:$D$59,MATCH(B49,اطلاعات_پرسنل!$A$4:$A$59,0)),"") -> دریا کریمی | D49: 7 | E49: 2 | F49: =IFERROR(SUMIFS(لاگ_فاکتور!$V$3:$V$1622,لاگ_فاکتور!$B$3:$B$1622,A49,لاگ_فاکتور!$C$3:$C$1622,B49),0) -> 1 | G49: =IFERROR(SUMIFS(لاگ_فاکتور!$O$3:$O$1622,لاگ_فاکتور!$B$3:$B$1622,A49,لاگ_فاکتور!$C$3:$C$1622,B49),0) -> 825000 | H49: =IFERROR(SUMIFS(لاگ_فاکتور!$N$3:$N$1622,لاگ_فاکتور!$B$3:$B$1622,A49,لاگ_فاکتور!$C$3:$C$1622,B49),0) -> 0 | I49: 0 | J49: 0 | K49: =IFERROR(F49/D49,0) -> 0.14285714 | L49: =IFERROR(G49/F49,0) -> 825000 | M49: =IFERROR(SUMIFS(لاگ_فاکتور!$L$3:$L$1622,لاگ_فاکتور!$B$3:$B$1622,A49,لاگ_فاکتور!$C$3:$C$1622,B49)/F49,0) -> 1 | N49: 0
A50: 1405/07/18 | B50: 2 | C50: =IFERROR(INDEX(اطلاعات_پرسنل!$D$4:$D$59,MATCH(B50,اطلاعات_پرسنل!$A$4:$A$59,0)),"") -> ماحی حمیدپور | D50: 0 | F50: =IFERROR(SUMIFS(لاگ_فاکتور!$V$3:$V$1622,لاگ_فاکتور!$B$3:$B$1622,A50,لاگ_فاکتور!$C$3:$C$1622,B50),0) -> 0 | G50: =IFERROR(SUMIFS(لاگ_فاکتور!$O$3:$O$1622,لاگ_فاکتور!$B$3:$B$1622,A50,لاگ_فاکتور!$C$3:$C$1622,B50),0) -> 0 | H50: =IFERROR(SUMIFS(لاگ_فاکتور!$N$3:$N$1622,لاگ_فاکتور!$B$3:$B$1622,A50,لاگ_فاکتور!$C$3:$C$1622,B50),0) -> 0 | I50: 0 | J50: 0 | K50: =IFERROR(F50/D50,0) -> 0 | L50: =IFERROR(G50/F50,0) -> 0 | M50: =IFERROR(SUMIFS(لاگ_فاکتور!$L$3:$L$1622,لاگ_فاکتور!$B$3:$B$1622,A50,لاگ_فاکتور!$C$3:$C$1622,B50)/F50,0) -> 0 | N50: 0
A51: 1405/07/19 | B51: 0 | C51: =IFERROR(INDEX(اطلاعات_پرسنل!$D$4:$D$59,MATCH(B51,اطلاعات_پرسنل!$A$4:$A$59,0)),"") -> فروشگاه | D51: 16 | E51: 6 | F51: =IFERROR(SUMIFS(لاگ_فاکتور!$V$3:$V$1622,لاگ_فاکتور!$B$3:$B$1622,A51,لاگ_فاکتور!$C$3:$C$1622,B51),0) -> 3 | G51: =IFERROR(SUMIFS(لاگ_فاکتور!$O$3:$O$1622,لاگ_فاکتور!$B$3:$B$1622,A51,لاگ_فاکتور!$C$3:$C$1622,B51),0) -> 8240000 | H51: =IFERROR(SUMIFS(لاگ_فاکتور!$N$3:$N$1622,لاگ_فاکتور!$B$3:$B$1622,A51,لاگ_فاکتور!$C$3:$C$1622,B51),0) -> 0 | I51: 0 | J51: 0 | K51: =IFERROR(F51/D51,0) -> 0.1875 | L51: =IFERROR(G51/F51,0) -> 2746666.7 | M51: =IFERROR(SUMIFS(لاگ_فاکتور!$L$3:$L$1622,لاگ_فاکتور!$B$3:$B$1622,A51,لاگ_فاکتور!$C$3:$C$1622,B51)/F51,0) -> 1 | N51: 0 | P51: پرو لوفر
A52: 1405/07/20 | B52: 0 | C52: =IFERROR(INDEX(اطلاعات_پرسنل!$D$4:$D$59,MATCH(B52,اطلاعات_پرسنل!$A$4:$A$59,0)),"") -> فروشگاه | F52: =IFERROR(SUMIFS(لاگ_فاکتور!$V$3:$V$1622,لاگ_فاکتور!$B$3:$B$1622,A52,لاگ_فاکتور!$C$3:$C$1622,B52),0) -> 0 | G52: =IFERROR(SUMIFS(لاگ_فاکتور!$O$3:$O$1622,لاگ_فاکتور!$B$3:$B$1622,A52,لاگ_فاکتور!$C$3:$C$1622,B52),0) -> 0 | H52: =IFERROR(SUMIFS(لاگ_فاکتور!$N$3:$N$1622,لاگ_فاکتور!$B$3:$B$1622,A52,لاگ_فاکتور!$C$3:$C$1622,B52),0) -> 0 | I52: 0 | J52: 0 | K52: =IFERROR(F52/D52,0) -> 0 | L52: =IFERROR(G52/F52,0) -> 0 | M52: =IFERROR(SUMIFS(لاگ_فاکتور!$L$3:$L$1622,لاگ_فاکتور!$B$3:$B$1622,A52,لاگ_فاکتور!$C$3:$C$1622,B52)/F52,0) -> 0 | N52: 0
A53: 1405/07/20 | B53: 2 | C53: =IFERROR(INDEX(اطلاعات_پرسنل!$D$4:$D$59,MATCH(B53,اطلاعات_پرسنل!$A$4:$A$59,0)),"") -> ماحی حمیدپور | F53: =IFERROR(SUMIFS(لاگ_فاکتور!$V$3:$V$1622,لاگ_فاکتور!$B$3:$B$1622,A53,لاگ_فاکتور!$C$3:$C$1622,B53),0) -> 0 | G53: =IFERROR(SUMIFS(لاگ_فاکتور!$O$3:$O$1622,لاگ_فاکتور!$B$3:$B$1622,A53,لاگ_فاکتور!$C$3:$C$1622,B53),0) -> 0 | H53: =IFERROR(SUMIFS(لاگ_فاکتور!$N$3:$N$1622,لاگ_فاکتور!$B$3:$B$1622,A53,لاگ_فاکتور!$C$3:$C$1622,B53),0) -> 0 | I53: 0 | J53: 0 | K53: =IFERROR(F53/D53,0) -> 0 | L53: =IFERROR(G53/F53,0) -> 0 | M53: =IFERROR(SUMIFS(لاگ_فاکتور!$L$3:$L$1622,لاگ_فاکتور!$B$3:$B$1622,A53,لاگ_فاکتور!$C$3:$C$1622,B53)/F53,0) -> 0 | N53: 0
A54: 1405/06/21 | B54: 0 | C54: =IFERROR(INDEX(اطلاعات_پرسنل!$D$4:$D$59,MATCH(B54,اطلاعات_پرسنل!$A$4:$A$59,0)),"") -> فروشگاه | F54: =IFERROR(SUMIFS(لاگ_فاکتور!$V$3:$V$1622,لاگ_فاکتور!$B$3:$B$1622,A54,لاگ_فاکتور!$C$3:$C$1622,B54),0) -> 0 | G54: =IFERROR(SUMIFS(لاگ_فاکتور!$O$3:$O$1622,لاگ_فاکتور!$B$3:$B$1622,A54,لاگ_فاکتور!$C$3:$C$1622,B54),0) -> 0 | H54: =IFERROR(SUMIFS(لاگ_فاکتور!$N$3:$N$1622,لاگ_فاکتور!$B$3:$B$1622,A54,لاگ_فاکتور!$C$3:$C$1622,B54),0) -> 0 | I54: 0 | J54: 0 | K54: =IFERROR(F54/D54,0) -> 0 | L54: =IFERROR(G54/F54,0) -> 0 | M54: =IFERROR(SUMIFS(لاگ_فاکتور!$L$3:$L$1622,لاگ_فاکتور!$B$3:$B$1622,A54,لاگ_فاکتور!$C$3:$C$1622,B54)/F54,0) -> 0 | N54: 0
A55: 1405/06/21 | B55: 1 | C55: =IFERROR(INDEX(اطلاعات_پرسنل!$D$4:$D$59,MATCH(B55,اطلاعات_پرسنل!$A$4:$A$59,0)),"") -> دریا کریمی | F55: =IFERROR(SUMIFS(لاگ_فاکتور!$V$3:$V$1622,لاگ_فاکتور!$B$3:$B$1622,A55,لاگ_فاکتور!$C$3:$C$1622,B55),0) -> 0 | G55: =IFERROR(SUMIFS(لاگ_فاکتور!$O$3:$O$1622,لاگ_فاکتور!$B$3:$B$1622,A55,لاگ_فاکتور!$C$3:$C$1622,B55),0) -> 0 | H55: =IFERROR(SUMIFS(لاگ_فاکتور!$N$3:$N$1622,لاگ_فاکتور!$B$3:$B$1622,A55,لاگ_فاکتور!$C$3:$C$1622,B55),0) -> 0 | I55: 0 | J55: 0 | K55: =IFERROR(F55/D55,0) -> 0 | L55: =IFERROR(G55/F55,0) -> 0 | M55: =IFERROR(SUMIFS(لاگ_فاکتور!$L$3:$L$1622,لاگ_فاکتور!$B$3:$B$1622,A55,لاگ_فاکتور!$C$3:$C$1622,B55)/F55,0) -> 0 | N55: 0
A56: 1405/06/21 | B56: 2 | C56: =IFERROR(INDEX(اطلاعات_پرسنل!$D$4:$D$59,MATCH(B56,اطلاعات_پرسنل!$A$4:$A$59,0)),"") -> ماحی حمیدپور | F56: =IFERROR(SUMIFS(لاگ_فاکتور!$V$3:$V$1622,لاگ_فاکتور!$B$3:$B$1622,A56,لاگ_فاکتور!$C$3:$C$1622,B56),0) -> 0 | G56: =IFERROR(SUMIFS(لاگ_فاکتور!$O$3:$O$1622,لاگ_فاکتور!$B$3:$B$1622,A56,لاگ_فاکتور!$C$3:$C$1622,B56),0) -> 0 | H56: =IFERROR(SUMIFS(لاگ_فاکتور!$N$3:$N$1622,لاگ_فاکتور!$B$3:$B$1622,A56,لاگ_فاکتور!$C$3:$C$1622,B56),0) -> 0 | I56: 0 | J56: 0 | K56: =IFERROR(F56/D56,0) -> 0 | L56: =IFERROR(G56/F56,0) -> 0 | M56: =IFERROR(SUMIFS(لاگ_فاکتور!$L$3:$L$1622,لاگ_فاکتور!$B$3:$B$1622,A56,لاگ_فاکتور!$C$3:$C$1622,B56)/F56,0) -> 0 | N56: 0
A57: 1405/06/22 | B57: 0 | C57: =IFERROR(INDEX(اطلاعات_پرسنل!$D$4:$D$59,MATCH(B57,اطلاعات_پرسنل!$A$4:$A$59,0)),"") -> فروشگاه | F57: =IFERROR(SUMIFS(لاگ_فاکتور!$V$3:$V$1622,لاگ_فاکتور!$B$3:$B$1622,A57,لاگ_فاکتور!$C$3:$C$1622,B57),0) -> 0 | G57: =IFERROR(SUMIFS(لاگ_فاکتور!$O$3:$O$1622,لاگ_فاکتور!$B$3:$B$1622,A57,لاگ_فاکتور!$C$3:$C$1622,B57),0) -> 0 | H57: =IFERROR(SUMIFS(لاگ_فاکتور!$N$3:$N$1622,لاگ_فاکتور!$B$3:$B$1622,A57,لاگ_فاکتور!$C$3:$C$1622,B57),0) -> 0 | I57: 0 | J57: 0 | K57: =IFERROR(F57/D57,0) -> 0 | L57: =IFERROR(G57/F57,0) -> 0 | M57: =IFERROR(SUMIFS(لاگ_فاکتور!$L$3:$L$1622,لاگ_فاکتور!$B$3:$B$1622,A57,لاگ_فاکتور!$C$3:$C$1622,B57)/F57,0) -> 0 | N57: 0
A58: 1405/06/22 | B58: 1 | C58: =IFERROR(INDEX(اطلاعات_پرسنل!$D$4:$D$59,MATCH(B58,اطلاعات_پرسنل!$A$4:$A$59,0)),"") -> دریا کریمی | F58: =IFERROR(SUMIFS(لاگ_فاکتور!$V$3:$V$1622,لاگ_فاکتور!$B$3:$B$1622,A58,لاگ_فاکتور!$C$3:$C$1622,B58),0) -> 0 | G58: =IFERROR(SUMIFS(لاگ_فاکتور!$O$3:$O$1622,لاگ_فاکتور!$B$3:$B$1622,A58,لاگ_فاکتور!$C$3:$C$1622,B58),0) -> 0 | H58: =IFERROR(SUMIFS(لاگ_فاکتور!$N$3:$N$1622,لاگ_فاکتور!$B$3:$B$1622,A58,لاگ_فاکتور!$C$3:$C$1622,B58),0) -> 0 | I58: 0 | J58: 0 | K58: =IFERROR(F58/D58,0) -> 0 | L58: =IFERROR(G58/F58,0) -> 0 | M58: =IFERROR(SUMIFS(لاگ_فاکتور!$L$3:$L$1622,لاگ_فاکتور!$B$3:$B$1622,A58,لاگ_فاکتور!$C$3:$C$1622,B58)/F58,0) -> 0 | N58: 0
A59: 1405/06/22 | B59: 2 | C59: =IFERROR(INDEX(اطلاعات_پرسنل!$D$4:$D$59,MATCH(B59,اطلاعات_پرسنل!$A$4:$A$59,0)),"") -> ماحی حمیدپور | F59: =IFERROR(SUMIFS(لاگ_فاکتور!$V$3:$V$1622,لاگ_فاکتور!$B$3:$B$1622,A59,لاگ_فاکتور!$C$3:$C$1622,B59),0) -> 0 | G59: =IFERROR(SUMIFS(لاگ_فاکتور!$O$3:$O$1622,لاگ_فاکتور!$B$3:$B$1622,A59,لاگ_فاکتور!$C$3:$C$1622,B59),0) -> 0 | H59: =IFERROR(SUMIFS(لاگ_فاکتور!$N$3:$N$1622,لاگ_فاکتور!$B$3:$B$1622,A59,لاگ_فاکتور!$C$3:$C$1622,B59),0) -> 0 | I59: 0 | J59: 0 | K59: =IFERROR(F59/D59,0) -> 0 | L59: =IFERROR(G59/F59,0) -> 0 | M59: =IFERROR(SUMIFS(لاگ_فاکتور!$L$3:$L$1622,لاگ_فاکتور!$B$3:$B$1622,A59,لاگ_فاکتور!$C$3:$C$1622,B59)/F59,0) -> 0 | N59: 0
A60: 1405/06/23 | B60: 0 | C60: =IFERROR(INDEX(اطلاعات_پرسنل!$D$4:$D$59,MATCH(B60,اطلاعات_پرسنل!$A$4:$A$59,0)),"") -> فروشگاه | F60: =IFERROR(SUMIFS(لاگ_فاکتور!$V$3:$V$1622,لاگ_فاکتور!$B$3:$B$1622,A60,لاگ_فاکتور!$C$3:$C$1622,B60),0) -> 0 | G60: =IFERROR(SUMIFS(لاگ_فاکتور!$O$3:$O$1622,لاگ_فاکتور!$B$3:$B$1622,A60,لاگ_فاکتور!$C$3:$C$1622,B60),0) -> 0 | H60: =IFERROR(SUMIFS(لاگ_فاکتور!$N$3:$N$1622,لاگ_فاکتور!$B$3:$B$1622,A60,لاگ_فاکتور!$C$3:$C$1622,B60),0) -> 0 | I60: 0 | J60: 0 | K60: =IFERROR(F60/D60,0) -> 0 | L60: =IFERROR(G60/F60,0) -> 0 | M60: =IFERROR(SUMIFS(لاگ_فاکتور!$L$3:$L$1622,لاگ_فاکتور!$B$3:$B$1622,A60,لاگ_فاکتور!$C$3:$C$1622,B60)/F60,0) -> 0 | N60: 0
A61: 1405/06/23 | B61: 1 | C61: =IFERROR(INDEX(اطلاعات_پرسنل!$D$4:$D$59,MATCH(B61,اطلاعات_پرسنل!$A$4:$A$59,0)),"") -> دریا کریمی | F61: =IFERROR(SUMIFS(لاگ_فاکتور!$V$3:$V$1622,لاگ_فاکتور!$B$3:$B$1622,A61,لاگ_فاکتور!$C$3:$C$1622,B61),0) -> 0 | G61: =IFERROR(SUMIFS(لاگ_فاکتور!$O$3:$O$1622,لاگ_فاکتور!$B$3:$B$1622,A61,لاگ_فاکتور!$C$3:$C$1622,B61),0) -> 0 | H61: =IFERROR(SUMIFS(لاگ_فاکتور!$N$3:$N$1622,لاگ_فاکتور!$B$3:$B$1622,A61,لاگ_فاکتور!$C$3:$C$1622,B61),0) -> 0 | I61: 0 | J61: 0 | K61: =IFERROR(F61/D61,0) -> 0 | L61: =IFERROR(G61/F61,0) -> 0 | M61: =IFERROR(SUMIFS(لاگ_فاکتور!$L$3:$L$1622,لاگ_فاکتور!$B$3:$B$1622,A61,لاگ_فاکتور!$C$3:$C$1622,B61)/F61,0) -> 0 | N61: 0
A62: 1405/06/23 | B62: 2 | C62: =IFERROR(INDEX(اطلاعات_پرسنل!$D$4:$D$59,MATCH(B62,اطلاعات_پرسنل!$A$4:$A$59,0)),"") -> ماحی حمیدپور | F62: =IFERROR(SUMIFS(لاگ_فاکتور!$V$3:$V$1622,لاگ_فاکتور!$B$3:$B$1622,A62,لاگ_فاکتور!$C$3:$C$1622,B62),0) -> 0 | G62: =IFERROR(SUMIFS(لاگ_فاکتور!$O$3:$O$1622,لاگ_فاکتور!$B$3:$B$1622,A62,لاگ_فاکتور!$C$3:$C$1622,B62),0) -> 0 | H62: =IFERROR(SUMIFS(لاگ_فاکتور!$N$3:$N$1622,لاگ_فاکتور!$B$3:$B$1622,A62,لاگ_فاکتور!$C$3:$C$1622,B62),0) -> 0 | I62: 0 | J62: 0 | K62: =IFERROR(F62/D62,0) -> 0 | L62: =IFERROR(G62/F62,0) -> 0 | M62: =IFERROR(SUMIFS(لاگ_فاکتور!$L$3:$L$1622,لاگ_فاکتور!$B$3:$B$1622,A62,لاگ_فاکتور!$C$3:$C$1622,B62)/F62,0) -> 0 | N62: 0
A63: 1405/06/24 | B63: 0 | C63: =IFERROR(INDEX(اطلاعات_پرسنل!$D$4:$D$59,MATCH(B63,اطلاعات_پرسنل!$A$4:$A$59,0)),"") -> فروشگاه | F63: =IFERROR(SUMIFS(لاگ_فاکتور!$V$3:$V$1622,لاگ_فاکتور!$B$3:$B$1622,A63,لاگ_فاکتور!$C$3:$C$1622,B63),0) -> 0 | G63: =IFERROR(SUMIFS(لاگ_فاکتور!$O$3:$O$1622,لاگ_فاکتور!$B$3:$B$1622,A63,لاگ_فاکتور!$C$3:$C$1622,B63),0) -> 0 | H63: =IFERROR(SUMIFS(لاگ_فاکتور!$N$3:$N$1622,لاگ_فاکتور!$B$3:$B$1622,A63,لاگ_فاکتور!$C$3:$C$1622,B63),0) -> 0 | I63: 0 | J63: 0 | K63: =IFERROR(F63/D63,0) -> 0 | L63: =IFERROR(G63/F63,0) -> 0 | M63: =IFERROR(SUMIFS(لاگ_فاکتور!$L$3:$L$1622,لاگ_فاکتور!$B$3:$B$1622,A63,لاگ_فاکتور!$C$3:$C$1622,B63)/F63,0) -> 0 | N63: 0
A64: 1405/06/25 | B64: 2 | C64: =IFERROR(INDEX(اطلاعات_پرسنل!$D$4:$D$59,MATCH(B64,اطلاعات_پرسنل!$A$4:$A$59,0)),"") -> ماحی حمیدپور | E64: 2 | F64: =IFERROR(SUMIFS(لاگ_فاکتور!$V$3:$V$1622,لاگ_فاکتور!$B$3:$B$1622,A64,لاگ_فاکتور!$C$3:$C$1622,B64),0) -> 0 | G64: =IFERROR(SUMIFS(لاگ_فاکتور!$O$3:$O$1622,لاگ_فاکتور!$B$3:$B$1622,A64,لاگ_فاکتور!$C$3:$C$1622,B64),0) -> 0 | H64: 1 | I64: 0 | J64: 1 | K64: =IFERROR(F64/D64,0) -> 0 | L64: =IFERROR(G64/F64,0) -> 0 | M64: =IFERROR(SUMIFS(لاگ_فاکتور!$L$3:$L$1622,لاگ_فاکتور!$B$3:$B$1622,A64,لاگ_فاکتور!$C$3:$C$1622,B64)/F64,0) -> 0 | N64: 0
A65: 1405/06/26 | B65: 0 | C65: =IFERROR(INDEX(اطلاعات_پرسنل!$D$4:$D$59,MATCH(B65,اطلاعات_پرسنل!$A$4:$A$59,0)),"") -> فروشگاه | D65: 14 | E65: 6 | F65: =IFERROR(SUMIFS(لاگ_فاکتور!$V$3:$V$1622,لاگ_فاکتور!$B$3:$B$1622,A65,لاگ_فاکتور!$C$3:$C$1622,B65),0) -> 0 | G65: =IFERROR(SUMIFS(لاگ_فاکتور!$O$3:$O$1622,لاگ_فاکتور!$B$3:$B$1622,A65,لاگ_فاکتور!$C$3:$C$1622,B65),0) -> 0 | H65: =IFERROR(SUMIFS(لاگ_فاکتور!$N$3:$N$1622,لاگ_فاکتور!$B$3:$B$1622,A65,لاگ_فاکتور!$C$3:$C$1622,B65),0) -> 0 | I65: 0 | J65: 0 | K65: =IFERROR(F65/D65,0) -> 0 | L65: =IFERROR(G65/F65,0) -> 0 | M65: =IFERROR(SUMIFS(لاگ_فاکتور!$L$3:$L$1622,لاگ_فاکتور!$B$3:$B$1622,A65,لاگ_فاکتور!$C$3:$C$1622,B65)/F65,0) -> 0 | N65: 0 | P65: پرو صندل
A66: 1405/06/24 | B66: 1 | C66: =IFERROR(INDEX(اطلاعات_پرسنل!$D$4:$D$59,MATCH(B66,اطلاعات_پرسنل!$A$4:$A$59,0)),"") -> دریا کریمی | F66: =IFERROR(SUMIFS(لاگ_فاکتور!$V$3:$V$1622,لاگ_فاکتور!$B$3:$B$1622,A66,لاگ_فاکتور!$C$3:$C$1622,B66),0) -> 0 | G66: =IFERROR(SUMIFS(لاگ_فاکتور!$O$3:$O$1622,لاگ_فاکتور!$B$3:$B$1622,A66,لاگ_فاکتور!$C$3:$C$1622,B66),0) -> 0 | H66: =IFERROR(SUMIFS(لاگ_فاکتور!$N$3:$N$1622,لاگ_فاکتور!$B$3:$B$1622,A66,لاگ_فاکتور!$C$3:$C$1622,B66),0) -> 0 | I66: 0 | J66: 0 | K66: =IFERROR(F66/D66,0) -> 0 | L66: =IFERROR(G66/F66,0) -> 0 | M66: =IFERROR(SUMIFS(لاگ_فاکتور!$L$3:$L$1622,لاگ_فاکتور!$B$3:$B$1622,A66,لاگ_فاکتور!$C$3:$C$1622,B66)/F66,0) -> 0 | N66: 0
A67: 1405/06/24 | B67: 2 | C67: =IFERROR(INDEX(اطلاعات_پرسنل!$D$4:$D$59,MATCH(B67,اطلاعات_پرسنل!$A$4:$A$59,0)),"") -> ماحی حمیدپور | F67: =IFERROR(SUMIFS(لاگ_فاکتور!$V$3:$V$1622,لاگ_فاکتور!$B$3:$B$1622,A67,لاگ_فاکتور!$C$3:$C$1622,B67),0) -> 0 | G67: =IFERROR(SUMIFS(لاگ_فاکتور!$O$3:$O$1622,لاگ_فاکتور!$B$3:$B$1622,A67,لاگ_فاکتور!$C$3:$C$1622,B67),0) -> 0 | H67: =IFERROR(SUMIFS(لاگ_فاکتور!$N$3:$N$1622,لاگ_فاکتور!$B$3:$B$1622,A67,لاگ_فاکتور!$C$3:$C$1622,B67),0) -> 0 | I67: 0 | J67: 0 | K67: =IFERROR(F67/D67,0) -> 0 | L67: =IFERROR(G67/F67,0) -> 0 | M67: =IFERROR(SUMIFS(لاگ_فاکتور!$L$3:$L$1622,لاگ_فاکتور!$B$3:$B$1622,A67,لاگ_فاکتور!$C$3:$C$1622,B67)/F67,0) -> 0 | N67: 0
A68: 1405/06/25 | B68: 0 | C68: =IFERROR(INDEX(اطلاعات_پرسنل!$D$4:$D$59,MATCH(B68,اطلاعات_پرسنل!$A$4:$A$59,0)),"") -> فروشگاه | F68: =IFERROR(SUMIFS(لاگ_فاکتور!$V$3:$V$1622,لاگ_فاکتور!$B$3:$B$1622,A68,لاگ_فاکتور!$C$3:$C$1622,B68),0) -> 0 | G68: =IFERROR(SUMIFS(لاگ_فاکتور!$O$3:$O$1622,لاگ_فاکتور!$B$3:$B$1622,A68,لاگ_فاکتور!$C$3:$C$1622,B68),0) -> 0 | H68: =IFERROR(SUMIFS(لاگ_فاکتور!$N$3:$N$1622,لاگ_فاکتور!$B$3:$B$1622,A68,لاگ_فاکتور!$C$3:$C$1622,B68),0) -> 0 | I68: 0 | J68: 0 | K68: =IFERROR(F68/D68,0) -> 0 | L68: =IFERROR(G68/F68,0) -> 0 | M68: =IFERROR(SUMIFS(لاگ_فاکتور!$L$3:$L$1622,لاگ_فاکتور!$B$3:$B$1622,A68,لاگ_فاکتور!$C$3:$C$1622,B68)/F68,0) -> 0 | N68: 0
A69: 1405/06/25 | B69: 1 | C69: =IFERROR(INDEX(اطلاعات_پرسنل!$D$4:$D$59,MATCH(B69,اطلاعات_پرسنل!$A$4:$A$59,0)),"") -> دریا کریمی | F69: =IFERROR(SUMIFS(لاگ_فاکتور!$V$3:$V$1622,لاگ_فاکتور!$B$3:$B$1622,A69,لاگ_فاکتور!$C$3:$C$1622,B69),0) -> 0 | G69: =IFERROR(SUMIFS(لاگ_فاکتور!$O$3:$O$1622,لاگ_فاکتور!$B$3:$B$1622,A69,لاگ_فاکتور!$C$3:$C$1622,B69),0) -> 0 | H69: =IFERROR(SUMIFS(لاگ_فاکتور!$N$3:$N$1622,لاگ_فاکتور!$B$3:$B$1622,A69,لاگ_فاکتور!$C$3:$C$1622,B69),0) -> 0 | I69: 0 | J69: 0 | K69: =IFERROR(F69/D69,0) -> 0 | L69: =IFERROR(G69/F69,0) -> 0 | M69: =IFERROR(SUMIFS(لاگ_فاکتور!$L$3:$L$1622,لاگ_فاکتور!$B$3:$B$1622,A69,لاگ_فاکتور!$C$3:$C$1622,B69)/F69,0) -> 0 | N69: 0
A70: 1405/06/26 | B70: 2 | C70: =IFERROR(INDEX(اطلاعات_پرسنل!$D$4:$D$59,MATCH(B70,اطلاعات_پرسنل!$A$4:$A$59,0)),"") -> ماحی حمیدپور | F70: =IFERROR(SUMIFS(لاگ_فاکتور!$V$3:$V$1622,لاگ_فاکتور!$B$3:$B$1622,A70,لاگ_فاکتور!$C$3:$C$1622,B70),0) -> 0 | G70: =IFERROR(SUMIFS(لاگ_فاکتور!$O$3:$O$1622,لاگ_فاکتور!$B$3:$B$1622,A70,لاگ_فاکتور!$C$3:$C$1622,B70),0) -> 0 | H70: =IFERROR(SUMIFS(لاگ_فاکتور!$N$3:$N$1622,لاگ_فاکتور!$B$3:$B$1622,A70,لاگ_فاکتور!$C$3:$C$1622,B70),0) -> 0 | I70: 0 | J70: 0 | K70: =IFERROR(F70/D70,0) -> 0 | L70: =IFERROR(G70/F70,0) -> 0 | M70: =IFERROR(SUMIFS(لاگ_فاکتور!$L$3:$L$1622,لاگ_فاکتور!$B$3:$B$1622,A70,لاگ_فاکتور!$C$3:$C$1622,B70)/F70,0) -> 0 | N70: 0
A71: 1405/06/26 | B71: 2 | C71: =IFERROR(INDEX(اطلاعات_پرسنل!$D$4:$D$59,MATCH(B71,اطلاعات_پرسنل!$A$4:$A$59,0)),"") -> ماحی حمیدپور | F71: =IFERROR(SUMIFS(لاگ_فاکتور!$V$3:$V$1622,لاگ_فاکتور!$B$3:$B$1622,A71,لاگ_فاکتور!$C$3:$C$1622,B71),0) -> 0 | G71: =IFERROR(SUMIFS(لاگ_فاکتور!$O$3:$O$1622,لاگ_فاکتور!$B$3:$B$1622,A71,لاگ_فاکتور!$C$3:$C$1622,B71),0) -> 0 | H71: =IFERROR(SUMIFS(لاگ_فاکتور!$N$3:$N$1622,لاگ_فاکتور!$B$3:$B$1622,A71,لاگ_فاکتور!$C$3:$C$1622,B71),0) -> 0 | I71: 0 | J71: 0 | K71: =IFERROR(F71/D71,0) -> 0 | L71: =IFERROR(G71/F71,0) -> 0 | M71: =IFERROR(SUMIFS(لاگ_فاکتور!$L$3:$L$1622,لاگ_فاکتور!$B$3:$B$1622,A71,لاگ_فاکتور!$C$3:$C$1622,B71)/F71,0) -> 0 | N71: 0
A72: 1405/06/27 | B72: 1 | C72: =IFERROR(INDEX(اطلاعات_پرسنل!$D$4:$D$59,MATCH(B72,اطلاعات_پرسنل!$A$4:$A$59,0)),"") -> دریا کریمی | F72: =IFERROR(SUMIFS(لاگ_فاکتور!$V$3:$V$1622,لاگ_فاکتور!$B$3:$B$1622,A72,لاگ_فاکتور!$C$3:$C$1622,B72),0) -> 0 | G72: =IFERROR(SUMIFS(لاگ_فاکتور!$O$3:$O$1622,لاگ_فاکتور!$B$3:$B$1622,A72,لاگ_فاکتور!$C$3:$C$1622,B72),0) -> 0 | H72: =IFERROR(SUMIFS(لاگ_فاکتور!$N$3:$N$1622,لاگ_فاکتور!$B$3:$B$1622,A72,لاگ_فاکتور!$C$3:$C$1622,B72),0) -> 0 | I72: 0 | J72: 0 | K72: =IFERROR(F72/D72,0) -> 0 | L72: =IFERROR(G72/F72,0) -> 0 | M72: =IFERROR(SUMIFS(لاگ_فاکتور!$L$3:$L$1622,لاگ_فاکتور!$B$3:$B$1622,A72,لاگ_فاکتور!$C$3:$C$1622,B72)/F72,0) -> 0 | N72: 0
A73: 1405/06/27 | B73: 0 | C73: =IFERROR(INDEX(اطلاعات_پرسنل!$D$4:$D$59,MATCH(B73,اطلاعات_پرسنل!$A$4:$A$59,0)),"") -> فروشگاه | F73: =IFERROR(SUMIFS(لاگ_فاکتور!$V$3:$V$1622,لاگ_فاکتور!$B$3:$B$1622,A73,لاگ_فاکتور!$C$3:$C$1622,B73),0) -> 0 | G73: =IFERROR(SUMIFS(لاگ_فاکتور!$O$3:$O$1622,لاگ_فاکتور!$B$3:$B$1622,A73,لاگ_فاکتور!$C$3:$C$1622,B73),0) -> 0 | H73: =IFERROR(SUMIFS(لاگ_فاکتور!$N$3:$N$1622,لاگ_فاکتور!$B$3:$B$1622,A73,لاگ_فاکتور!$C$3:$C$1622,B73),0) -> 0 | I73: 0 | J73: 0 | K73: =IFERROR(F73/D73,0) -> 0 | L73: =IFERROR(G73/F73,0) -> 0 | M73: =IFERROR(SUMIFS(لاگ_فاکتور!$L$3:$L$1622,لاگ_فاکتور!$B$3:$B$1622,A73,لاگ_فاکتور!$C$3:$C$1622,B73)/F73,0) -> 0 | N73: 0
A74: 1405/06/29 | B74: 1 | C74: =IFERROR(INDEX(اطلاعات_پرسنل!$D$4:$D$59,MATCH(B74,اطلاعات_پرسنل!$A$4:$A$59,0)),"") -> دریا کریمی | F74: =IFERROR(SUMIFS(لاگ_فاکتور!$V$3:$V$1622,لاگ_فاکتور!$B$3:$B$1622,A74,لاگ_فاکتور!$C$3:$C$1622,B74),0) -> 0 | G74: =IFERROR(SUMIFS(لاگ_فاکتور!$O$3:$O$1622,لاگ_فاکتور!$B$3:$B$1622,A74,لاگ_فاکتور!$C$3:$C$1622,B74),0) -> 0 | H74: =IFERROR(SUMIFS(لاگ_فاکتور!$N$3:$N$1622,لاگ_فاکتور!$B$3:$B$1622,A74,لاگ_فاکتور!$C$3:$C$1622,B74),0) -> 0 | I74: 0 | J74: 0 | K74: =IFERROR(F74/D74,0) -> 0 | L74: =IFERROR(G74/F74,0) -> 0 | M74: =IFERROR(SUMIFS(لاگ_فاکتور!$L$3:$L$1622,لاگ_فاکتور!$B$3:$B$1622,A74,لاگ_فاکتور!$C$3:$C$1622,B74)/F74,0) -> 0 | N74: 0
A75: 1405/06/30 | B75: 0 | C75: =IFERROR(INDEX(اطلاعات_پرسنل!$D$4:$D$59,MATCH(B75,اطلاعات_پرسنل!$A$4:$A$59,0)),"") -> فروشگاه | F75: =IFERROR(SUMIFS(لاگ_فاکتور!$V$3:$V$1622,لاگ_فاکتور!$B$3:$B$1622,A75,لاگ_فاکتور!$C$3:$C$1622,B75),0) -> 0 | G75: =IFERROR(SUMIFS(لاگ_فاکتور!$O$3:$O$1622,لاگ_فاکتور!$B$3:$B$1622,A75,لاگ_فاکتور!$C$3:$C$1622,B75),0) -> 0 | H75: =IFERROR(SUMIFS(لاگ_فاکتور!$N$3:$N$1622,لاگ_فاکتور!$B$3:$B$1622,A75,لاگ_فاکتور!$C$3:$C$1622,B75),0) -> 0 | I75: 0 | J75: 0 | K75: =IFERROR(F75/D75,0) -> 0 | L75: =IFERROR(G75/F75,0) -> 0 | M75: =IFERROR(SUMIFS(لاگ_فاکتور!$L$3:$L$1622,لاگ_فاکتور!$B$3:$B$1622,A75,لاگ_فاکتور!$C$3:$C$1622,B75)/F75,0) -> 0 | N75: 0
A76: 1405/06/30 | B76: 1 | C76: =IFERROR(INDEX(اطلاعات_پرسنل!$D$4:$D$59,MATCH(B76,اطلاعات_پرسنل!$A$4:$A$59,0)),"") -> دریا کریمی | F76: =IFERROR(SUMIFS(لاگ_فاکتور!$V$3:$V$1622,لاگ_فاکتور!$B$3:$B$1622,A76,لاگ_فاکتور!$C$3:$C$1622,B76),0) -> 0 | G76: =IFERROR(SUMIFS(لاگ_فاکتور!$O$3:$O$1622,لاگ_فاکتور!$B$3:$B$1622,A76,لاگ_فاکتور!$C$3:$C$1622,B76),0) -> 0 | H76: =IFERROR(SUMIFS(لاگ_فاکتور!$N$3:$N$1622,لاگ_فاکتور!$B$3:$B$1622,A76,لاگ_فاکتور!$C$3:$C$1622,B76),0) -> 0 | I76: 0 | J76: 0 | K76: =IFERROR(F76/D76,0) -> 0 | L76: =IFERROR(G76/F76,0) -> 0 | M76: =IFERROR(SUMIFS(لاگ_فاکتور!$L$3:$L$1622,لاگ_فاکتور!$B$3:$B$1622,A76,لاگ_فاکتور!$C$3:$C$1622,B76)/F76,0) -> 0 | N76: 0
A77: 1405/06/30 | B77: 2 | C77: =IFERROR(INDEX(اطلاعات_پرسنل!$D$4:$D$59,MATCH(B77,اطلاعات_پرسنل!$A$4:$A$59,0)),"") -> ماحی حمیدپور | F77: =IFERROR(SUMIFS(لاگ_فاکتور!$V$3:$V$1622,لاگ_فاکتور!$B$3:$B$1622,A77,لاگ_فاکتور!$C$3:$C$1622,B77),0) -> 0 | G77: =IFERROR(SUMIFS(لاگ_فاکتور!$O$3:$O$1622,لاگ_فاکتور!$B$3:$B$1622,A77,لاگ_فاکتور!$C$3:$C$1622,B77),0) -> 0 | H77: =IFERROR(SUMIFS(لاگ_فاکتور!$N$3:$N$1622,لاگ_فاکتور!$B$3:$B$1622,A77,لاگ_فاکتور!$C$3:$C$1622,B77),0) -> 0 | I77: 0 | J77: 0 | K77: =IFERROR(F77/D77,0) -> 0 | L77: =IFERROR(G77/F77,0) -> 0 | M77: =IFERROR(SUMIFS(لاگ_فاکتور!$L$3:$L$1622,لاگ_فاکتور!$B$3:$B$1622,A77,لاگ_فاکتور!$C$3:$C$1622,B77)/F77,0) -> 0 | N77: 0
... A79: 1405/06/31 | B79: 2 | C79: =IFERROR(INDEX(اطلاعات_پرسنل!$D$4:$D$59,MATCH(B79,اطلاعات_پرسنل!$A$4:$A$59,0)),"") -> ماحی حمیدپور | F79: =IFERROR(SUMIFS(لاگ_فاکتور!$V$3:$V$1622,لاگ_فاکتور!$B$3:$B$1622,A79,لاگ_فاکتور!$C$3:$C$1622,B79),0) -> 0 | G79: =IFERROR(SUMIFS(لاگ_فاکتور!$O$3:$O$1622,لاگ_فاکتور!$B$3:$B$1622,A79,لاگ_فاکتور!$C$3:$C$1622,B79),0) -> 0 | H79: =IFERROR(SUMIFS(لاگ_فاکتور!$N$3:$N$1622,لاگ_فاکتور!$B$3:$B$1622,A79,لاگ_فاکتور!$C$3:$C$1622,B79),0) -> 0 | I79: 0 | J79: 0 | K79: =IFERROR(F79/D79,0) -> 0 | L79: =IFERROR(G79/F79,0) -> 0 | M79: =IFERROR(SUMIFS(لاگ_فاکتور!$L$3:$L$1622,لاگ_فاکتور!$B$3:$B$1622,A79,لاگ_فاکتور!$C$3:$C$1622,B79)/F79,0) -> 0 | N79: 0
B80: 0 | C80: =IFERROR(INDEX(اطلاعات_پرسنل!$D$4:$D$59,MATCH(B80,اطلاعات_پرسنل!$A$4:$A$59,0)),"") -> فروشگاه | F80: =IFERROR(SUMIFS(لاگ_فاکتور!$V$3:$V$1622,لاگ_فاکتور!$B$3:$B$1622,A80,لاگ_فاکتور!$C$3:$C$1622,B80),0) -> 0 | G80: =IFERROR(SUMIFS(لاگ_فاکتور!$O$3:$O$1622,لاگ_فاکتور!$B$3:$B$1622,A80,لاگ_فاکتور!$C$3:$C$1622,B80),0) -> 0 | H80: =IFERROR(SUMIFS(لاگ_فاکتور!$N$3:$N$1622,لاگ_فاکتور!$B$3:$B$1622,A80,لاگ_فاکتور!$C$3:$C$1622,B80),0) -> 0 | I80: 0 | J80: 0 | K80: =IFERROR(F80/D80,0) -> 0 | L80: =IFERROR(G80/F80,0) -> 0 | M80: =IFERROR(SUMIFS(لاگ_فاکتور!$L$3:$L$1622,لاگ_فاکتور!$B$3:$B$1622,A80,لاگ_فاکتور!$C$3:$C$1622,B80)/F80,0) -> 0 | N80: 0
B81: 1 | C81: =IFERROR(INDEX(اطلاعات_پرسنل!$D$4:$D$59,MATCH(B81,اطلاعات_پرسنل!$A$4:$A$59,0)),"") -> دریا کریمی | F81: =IFERROR(SUMIFS(لاگ_فاکتور!$V$3:$V$1622,لاگ_فاکتور!$B$3:$B$1622,A81,لاگ_فاکتور!$C$3:$C$1622,B81),0) -> 0 | G81: =IFERROR(SUMIFS(لاگ_فاکتور!$O$3:$O$1622,لاگ_فاکتور!$B$3:$B$1622,A81,لاگ_فاکتور!$C$3:$C$1622,B81),0) -> 0 | H81: =IFERROR(SUMIFS(لاگ_فاکتور!$N$3:$N$1622,لاگ_فاکتور!$B$3:$B$1622,A81,لاگ_فاکتور!$C$3:$C$1622,B81),0) -> 0 | I81: 0 | J81: 0 | K81: =IFERROR(F81/D81,0) -> 0 | L81: =IFERROR(G81/F81,0) -> 0 | M81: =IFERROR(SUMIFS(لاگ_فاکتور!$L$3:$L$1622,لاگ_فاکتور!$B$3:$B$1622,A81,لاگ_فاکتور!$C$3:$C$1622,B81)/F81,0) -> 0 | N81: 0
B82: 2 | C82: =IFERROR(INDEX(اطلاعات_پرسنل!$D$4:$D$59,MATCH(B82,اطلاعات_پرسنل!$A$4:$A$59,0)),"") -> ماحی حمیدپور | F82: =IFERROR(SUMIFS(لاگ_فاکتور!$V$3:$V$1622,لاگ_فاکتور!$B$3:$B$1622,A82,لاگ_فاکتور!$C$3:$C$1622,B82),0) -> 0 | G82: =IFERROR(SUMIFS(لاگ_فاکتور!$O$3:$O$1622,لاگ_فاکتور!$B$3:$B$1622,A82,لاگ_فاکتور!$C$3:$C$1622,B82),0) -> 0 | H82: =IFERROR(SUMIFS(لاگ_فاکتور!$N$3:$N$1622,لاگ_فاکتور!$B$3:$B$1622,A82,لاگ_فاکتور!$C$3:$C$1622,B82),0) -> 0 | I82: 0 | J82: 0 | K82: =IFERROR(F82/D82,0) -> 0 | L82: =IFERROR(G82/F82,0) -> 0 | M82: =IFERROR(SUMIFS(لاگ_فاکتور!$L$3:$L$1622,لاگ_فاکتور!$B$3:$B$1622,A82,لاگ_فاکتور!$C$3:$C$1622,B82)/F82,0) -> 0 | N82: 0
B83: 0 | C83: =IFERROR(INDEX(اطلاعات_پرسنل!$D$4:$D$59,MATCH(B83,اطلاعات_پرسنل!$A$4:$A$59,0)),"") -> فروشگاه | F83: =IFERROR(SUMIFS(لاگ_فاکتور!$V$3:$V$1622,لاگ_فاکتور!$B$3:$B$1622,A83,لاگ_فاکتور!$C$3:$C$1622,B83),0) -> 0 | G83: =IFERROR(SUMIFS(لاگ_فاکتور!$O$3:$O$1622,لاگ_فاکتور!$B$3:$B$1622,A83,لاگ_فاکتور!$C$3:$C$1622,B83),0) -> 0 | H83: =IFERROR(SUMIFS(لاگ_فاکتور!$N$3:$N$1622,لاگ_فاکتور!$B$3:$B$1622,A83,لاگ_فاکتور!$C$3:$C$1622,B83),0) -> 0 | I83: 0 | J83: 0 | K83: =IFERROR(F83/D83,0) -> 0 | L83: =IFERROR(G83/F83,0) -> 0 | M83: =IFERROR(SUMIFS(لاگ_فاکتور!$L$3:$L$1622,لاگ_فاکتور!$B$3:$B$1622,A83,لاگ_فاکتور!$C$3:$C$1622,B83)/F83,0) -> 0 | N83: 0
B84: 1 | C84: =IFERROR(INDEX(اطلاعات_پرسنل!$D$4:$D$59,MATCH(B84,اطلاعات_پرسنل!$A$4:$A$59,0)),"") -> دریا کریمی | F84: =IFERROR(SUMIFS(لاگ_فاکتور!$V$3:$V$1622,لاگ_فاکتور!$B$3:$B$1622,A84,لاگ_فاکتور!$C$3:$C$1622,B84),0) -> 0 | G84: =IFERROR(SUMIFS(لاگ_فاکتور!$O$3:$O$1622,لاگ_فاکتور!$B$3:$B$1622,A84,لاگ_فاکتور!$C$3:$C$1622,B84),0) -> 0 | H84: =IFERROR(SUMIFS(لاگ_فاکتور!$N$3:$N$1622,لاگ_فاکتور!$B$3:$B$1622,A84,لاگ_فاکتور!$C$3:$C$1622,B84),0) -> 0 | I84: 0 | J84: 0 | K84: =IFERROR(F84/D84,0) -> 0 | L84: =IFERROR(G84/F84,0) -> 0 | M84: =IFERROR(SUMIFS(لاگ_فاکتور!$L$3:$L$1622,لاگ_فاکتور!$B$3:$B$1622,A84,لاگ_فاکتور!$C$3:$C$1622,B84)/F84,0) -> 0 | N84: 0
B85: 2 | C85: =IFERROR(INDEX(اطلاعات_پرسنل!$D$4:$D$59,MATCH(B85,اطلاعات_پرسنل!$A$4:$A$59,0)),"") -> ماحی حمیدپور | F85: =IFERROR(SUMIFS(لاگ_فاکتور!$V$3:$V$1622,لاگ_فاکتور!$B$3:$B$1622,A85,لاگ_فاکتور!$C$3:$C$1622,B85),0) -> 0 | G85: =IFERROR(SUMIFS(لاگ_فاکتور!$O$3:$O$1622,لاگ_فاکتور!$B$3:$B$1622,A85,لاگ_فاکتور!$C$3:$C$1622,B85),0) -> 0 | H85: =IFERROR(SUMIFS(لاگ_فاکتور!$N$3:$N$1622,لاگ_فاکتور!$B$3:$B$1622,A85,لاگ_فاکتور!$C$3:$C$1622,B85),0) -> 0 | I85: 0 | J85: 0 | K85: =IFERROR(F85/D85,0) -> 0 | L85: =IFERROR(G85/F85,0) -> 0 | M85: =IFERROR(SUMIFS(لاگ_فاکتور!$L$3:$L$1622,لاگ_فاکتور!$B$3:$B$1622,A85,لاگ_فاکتور!$C$3:$C$1622,B85)/F85,0) -> 0 | N85: 0
B86: 0 | C86: =IFERROR(INDEX(اطلاعات_پرسنل!$D$4:$D$59,MATCH(B86,اطلاعات_پرسنل!$A$4:$A$59,0)),"") -> فروشگاه | F86: =IFERROR(SUMIFS(لاگ_فاکتور!$V$3:$V$1622,لاگ_فاکتور!$B$3:$B$1622,A86,لاگ_فاکتور!$C$3:$C$1622,B86),0) -> 0 | G86: =IFERROR(SUMIFS(لاگ_فاکتور!$O$3:$O$1622,لاگ_فاکتور!$B$3:$B$1622,A86,لاگ_فاکتور!$C$3:$C$1622,B86),0) -> 0 | H86: =IFERROR(SUMIFS(لاگ_فاکتور!$N$3:$N$1622,لاگ_فاکتور!$B$3:$B$1622,A86,لاگ_فاکتور!$C$3:$C$1622,B86),0) -> 0 | I86: 0 | J86: 0 | K86: =IFERROR(F86/D86,0) -> 0 | L86: =IFERROR(G86/F86,0) -> 0 | M86: =IFERROR(SUMIFS(لاگ_فاکتور!$L$3:$L$1622,لاگ_فاکتور!$B$3:$B$1622,A86,لاگ_فاکتور!$C$3:$C$1622,B86)/F86,0) -> 0 | N86: 0
B87: 1 | C87: =IFERROR(INDEX(اطلاعات_پرسنل!$D$4:$D$59,MATCH(B87,اطلاعات_پرسنل!$A$4:$A$59,0)),"") -> دریا کریمی | F87: =IFERROR(SUMIFS(لاگ_فاکتور!$V$3:$V$1622,لاگ_فاکتور!$B$3:$B$1622,A87,لاگ_فاکتور!$C$3:$C$1622,B87),0) -> 0 | G87: =IFERROR(SUMIFS(لاگ_فاکتور!$O$3:$O$1622,لاگ_فاکتور!$B$3:$B$1622,A87,لاگ_فاکتور!$C$3:$C$1622,B87),0) -> 0 | H87: =IFERROR(SUMIFS(لاگ_فاکتور!$N$3:$N$1622,لاگ_فاکتور!$B$3:$B$1622,A87,لاگ_فاکتور!$C$3:$C$1622,B87),0) -> 0 | I87: 0 | J87: 0 | K87: =IFERROR(F87/D87,0) -> 0 | L87: =IFERROR(G87/F87,0) -> 0 | M87: =IFERROR(SUMIFS(لاگ_فاکتور!$L$3:$L$1622,لاگ_فاکتور!$B$3:$B$1622,A87,لاگ_فاکتور!$C$3:$C$1622,B87)/F87,0) -> 0 | N87: 0
B88: 2 | C88: =IFERROR(INDEX(اطلاعات_پرسنل!$D$4:$D$59,MATCH(B88,اطلاعات_پرسنل!$A$4:$A$59,0)),"") -> ماحی حمیدپور | F88: =IFERROR(SUMIFS(لاگ_فاکتور!$V$3:$V$1622,لاگ_فاکتور!$B$3:$B$1622,A88,لاگ_فاکتور!$C$3:$C$1622,B88),0) -> 0 | G88: =IFERROR(SUMIFS(لاگ_فاکتور!$O$3:$O$1622,لاگ_فاکتور!$B$3:$B$1622,A88,لاگ_فاکتور!$C$3:$C$1622,B88),0) -> 0 | H88: =IFERROR(SUMIFS(لاگ_فاکتور!$N$3:$N$1622,لاگ_فاکتور!$B$3:$B$1622,A88,لاگ_فاکتور!$C$3:$C$1622,B88),0) -> 0 | I88: 0 | J88: 0 | K88: =IFERROR(F88/D88,0) -> 0 | L88: =IFERROR(G88/F88,0) -> 0 | M88: =IFERROR(SUMIFS(لاگ_فاکتور!$L$3:$L$1622,لاگ_فاکتور!$B$3:$B$1622,A88,لاگ_فاکتور!$C$3:$C$1622,B88)/F88,0) -> 0 | N88: 0
B89: 1 | C89: =IFERROR(INDEX(اطلاعات_پرسنل!$D$4:$D$59,MATCH(B89,اطلاعات_پرسنل!$A$4:$A$59,0)),"") -> دریا کریمی | F89: =IFERROR(SUMIFS(لاگ_فاکتور!$V$3:$V$1622,لاگ_فاکتور!$B$3:$B$1622,A89,لاگ_فاکتور!$C$3:$C$1622,B89),0) -> 0 | G89: =IFERROR(SUMIFS(لاگ_فاکتور!$O$3:$O$1622,لاگ_فاکتور!$B$3:$B$1622,A89,لاگ_فاکتور!$C$3:$C$1622,B89),0) -> 0 | H89: =IFERROR(SUMIFS(لاگ_فاکتور!$N$3:$N$1622,لاگ_فاکتور!$B$3:$B$1622,A89,لاگ_فاکتور!$C$3:$C$1622,B89),0) -> 0 | I89: 0 | J89: 0 | K89: =IFERROR(F89/D89,0) -> 0 | L89: =IFERROR(G89/F89,0) -> 0 | M89: =IFERROR(SUMIFS(لاگ_فاکتور!$L$3:$L$1622,لاگ_فاکتور!$B$3:$B$1622,A89,لاگ_فاکتور!$C$3:$C$1622,B89)/F89,0) -> 0 | N89: 0
B90: 2 | C90: =IFERROR(INDEX(اطلاعات_پرسنل!$D$4:$D$59,MATCH(B90,اطلاعات_پرسنل!$A$4:$A$59,0)),"") -> ماحی حمیدپور | F90: =IFERROR(SUMIFS(لاگ_فاکتور!$V$3:$V$1622,لاگ_فاکتور!$B$3:$B$1622,A90,لاگ_فاکتور!$C$3:$C$1622,B90),0) -> 0 | G90: =IFERROR(SUMIFS(لاگ_فاکتور!$O$3:$O$1622,لاگ_فاکتور!$B$3:$B$1622,A90,لاگ_فاکتور!$C$3:$C$1622,B90),0) -> 0 | H90: =IFERROR(SUMIFS(لاگ_فاکتور!$N$3:$N$1622,لاگ_فاکتور!$B$3:$B$1622,A90,لاگ_فاکتور!$C$3:$C$1622,B90),0) -> 0 | I90: 0 | J90: 0 | K90: =IFERROR(F90/D90,0) -> 0 | L90: =IFERROR(G90/F90,0) -> 0 | M90: =IFERROR(SUMIFS(لاگ_فاکتور!$L$3:$L$1622,لاگ_فاکتور!$B$3:$B$1622,A90,لاگ_فاکتور!$C$3:$C$1622,B90)/F90,0) -> 0 | N90: 0
C91: =IFERROR(INDEX(اطلاعات_پرسنل!$D$4:$D$59,MATCH(B91,اطلاعات_پرسنل!$A$4:$A$59,0)),"") -> فروشگاه | F91: =IFERROR(SUMIFS(لاگ_فاکتور!$V$3:$V$1622,لاگ_فاکتور!$B$3:$B$1622,A91,لاگ_فاکتور!$C$3:$C$1622,B91),0) -> 0 | G91: =IFERROR(SUMIFS(لاگ_فاکتور!$O$3:$O$1622,لاگ_فاکتور!$B$3:$B$1622,A91,لاگ_فاکتور!$C$3:$C$1622,B91),0) -> 0 | H91: =IFERROR(SUMIFS(لاگ_فاکتور!$N$3:$N$1622,لاگ_فاکتور!$B$3:$B$1622,A91,لاگ_فاکتور!$C$3:$C$1622,B91),0) -> 0 | I91: 0 | J91: 0 | K91: =IFERROR(F91/D91,0) -> 0 | L91: =IFERROR(G91/F91,0) -> 0 | M91: =IFERROR(SUMIFS(لاگ_فاکتور!$L$3:$L$1622,لاگ_فاکتور!$B$3:$B$1622,A91,لاگ_فاکتور!$C$3:$C$1622,B91)/F91,0) -> 0 | N91: 0
C92: =IFERROR(INDEX(اطلاعات_پرسنل!$D$4:$D$59,MATCH(B92,اطلاعات_پرسنل!$A$4:$A$59,0)),"") -> فروشگاه | F92: =IFERROR(SUMIFS(لاگ_فاکتور!$V$3:$V$1622,لاگ_فاکتور!$B$3:$B$1622,A92,لاگ_فاکتور!$C$3:$C$1622,B92),0) -> 0 | G92: =IFERROR(SUMIFS(لاگ_فاکتور!$O$3:$O$1622,لاگ_فاکتور!$B$3:$B$1622,A92,لاگ_فاکتور!$C$3:$C$1622,B92),0) -> 0 | H92: =IFERROR(SUMIFS(لاگ_فاکتور!$N$3:$N$1622,لاگ_فاکتور!$B$3:$B$1622,A92,لاگ_فاکتور!$C$3:$C$1622,B92),0) -> 0 | I92: 0 | J92: 0 | K92: =IFERROR(F92/D92,0) -> 0 | L92: =IFERROR(G92/F92,0) -> 0 | M92: =IFERROR(SUMIFS(لاگ_فاکتور!$L$3:$L$1622,لاگ_فاکتور!$B$3:$B$1622,A92,لاگ_فاکتور!$C$3:$C$1622,B92)/F92,0) -> 0 | N92: 0
C93: =IFERROR(INDEX(اطلاعات_پرسنل!$D$4:$D$59,MATCH(B93,اطلاعات_پرسنل!$A$4:$A$59,0)),"") -> فروشگاه | F93: =IFERROR(SUMIFS(لاگ_فاکتور!$V$3:$V$1622,لاگ_فاکتور!$B$3:$B$1622,A93,لاگ_فاکتور!$C$3:$C$1622,B93),0) -> 0 | G93: =IFERROR(SUMIFS(لاگ_فاکتور!$O$3:$O$1622,لاگ_فاکتور!$B$3:$B$1622,A93,لاگ_فاکتور!$C$3:$C$1622,B93),0) -> 0 | H93: =IFERROR(SUMIFS(لاگ_فاکتور!$N$3:$N$1622,لاگ_فاکتور!$B$3:$B$1622,A93,لاگ_فاکتور!$C$3:$C$1622,B93),0) -> 0 | I93: 0 | J93: 0 | K93: =IFERROR(F93/D93,0) -> 0 | L93: =IFERROR(G93/F93,0) -> 0 | M93: =IFERROR(SUMIFS(لاگ_فاکتور!$L$3:$L$1622,لاگ_فاکتور!$B$3:$B$1622,A93,لاگ_فاکتور!$C$3:$C$1622,B93)/F93,0) -> 0 | N93: 0
C94: =IFERROR(INDEX(اطلاعات_پرسنل!$D$4:$D$59,MATCH(B94,اطلاعات_پرسنل!$A$4:$A$59,0)),"") -> فروشگاه | F94: =IFERROR(SUMIFS(لاگ_فاکتور!$V$3:$V$1622,لاگ_فاکتور!$B$3:$B$1622,A94,لاگ_فاکتور!$C$3:$C$1622,B94),0) -> 0 | G94: =IFERROR(SUMIFS(لاگ_فاکتور!$O$3:$O$1622,لاگ_فاکتور!$B$3:$B$1622,A94,لاگ_فاکتور!$C$3:$C$1622,B94),0) -> 0 | H94: =IFERROR(SUMIFS(لاگ_فاکتور!$N$3:$N$1622,لاگ_فاکتور!$B$3:$B$1622,A94,لاگ_فاکتور!$C$3:$C$1622,B94),0) -> 0 | I94: 0 | J94: 0 | K94: =IFERROR(F94/D94,0) -> 0 | L94: =IFERROR(G94/F94,0) -> 0 | M94: =IFERROR(SUMIFS(لاگ_فاکتور!$L$3:$L$1622,لاگ_فاکتور!$B$3:$B$1622,A94,لاگ_فاکتور!$C$3:$C$1622,B94)/F94,0) -> 0 | N94: 0
C95: =IFERROR(INDEX(اطلاعات_پرسنل!$D$4:$D$59,MATCH(B95,اطلاعات_پرسنل!$A$4:$A$59,0)),"") -> فروشگاه | F95: =IFERROR(SUMIFS(لاگ_فاکتور!$V$3:$V$1622,لاگ_فاکتور!$B$3:$B$1622,A95,لاگ_فاکتور!$C$3:$C$1622,B95),0) -> 0 | G95: =IFERROR(SUMIFS(لاگ_فاکتور!$O$3:$O$1622,لاگ_فاکتور!$B$3:$B$1622,A95,لاگ_فاکتور!$C$3:$C$1622,B95),0) -> 0 | H95: =IFERROR(SUMIFS(لاگ_فاکتور!$N$3:$N$1622,لاگ_فاکتور!$B$3:$B$1622,A95,لاگ_فاکتور!$C$3:$C$1622,B95),0) -> 0 | I95: 0 | J95: 0 | K95: =IFERROR(F95/D95,0) -> 0 | L95: =IFERROR(G95/F95,0) -> 0 | M95: =IFERROR(SUMIFS(لاگ_فاکتور!$L$3:$L$1622,لاگ_فاکتور!$B$3:$B$1622,A95,لاگ_فاکتور!$C$3:$C$1622,B95)/F95,0) -> 0 | N95: 0
C96: =IFERROR(INDEX(اطلاعات_پرسنل!$D$4:$D$59,MATCH(B96,اطلاعات_پرسنل!$A$4:$A$59,0)),"") -> فروشگاه | F96: =IFERROR(SUMIFS(لاگ_فاکتور!$V$3:$V$1622,لاگ_فاکتور!$B$3:$B$1622,A96,لاگ_فاکتور!$C$3:$C$1622,B96),0) -> 0 | G96: =IFERROR(SUMIFS(لاگ_فاکتور!$O$3:$O$1622,لاگ_فاکتور!$B$3:$B$1622,A96,لاگ_فاکتور!$C$3:$C$1622,B96),0) -> 0 | H96: =IFERROR(SUMIFS(لاگ_فاکتور!$N$3:$N$1622,لاگ_فاکتور!$B$3:$B$1622,A96,لاگ_فاکتور!$C$3:$C$1622,B96),0) -> 0 | I96: 0 | J96: 0 | K96: =IFERROR(F96/D96,0) -> 0 | L96: =IFERROR(G96/F96,0) -> 0 | M96: =IFERROR(SUMIFS(لاگ_فاکتور!$L$3:$L$1622,لاگ_فاکتور!$B$3:$B$1622,A96,لاگ_فاکتور!$C$3:$C$1622,B96)/F96,0) -> 0 | N96: 0
C97: =IFERROR(INDEX(اطلاعات_پرسنل!$D$4:$D$59,MATCH(B97,اطلاعات_پرسنل!$A$4:$A$59,0)),"") -> فروشگاه | F97: =IFERROR(SUMIFS(لاگ_فاکتور!$V$3:$V$1622,لاگ_فاکتور!$B$3:$B$1622,A97,لاگ_فاکتور!$C$3:$C$1622,B97),0) -> 0 | G97: =IFERROR(SUMIFS(لاگ_فاکتور!$O$3:$O$1622,لاگ_فاکتور!$B$3:$B$1622,A97,لاگ_فاکتور!$C$3:$C$1622,B97),0) -> 0 | H97: =IFERROR(SUMIFS(لاگ_فاکتور!$N$3:$N$1622,لاگ_فاکتور!$B$3:$B$1622,A97,لاگ_فاکتور!$C$3:$C$1622,B97),0) -> 0 | I97: 0 | J97: 0 | K97: =IFERROR(F97/D97,0) -> 0 | L97: =IFERROR(G97/F97,0) -> 0 | M97: =IFERROR(SUMIFS(لاگ_فاکتور!$L$3:$L$1622,لاگ_فاکتور!$B$3:$B$1622,A97,لاگ_فاکتور!$C$3:$C$1622,B97)/F97,0) -> 0 | N97: 0
C98: =IFERROR(INDEX(اطلاعات_پرسنل!$D$4:$D$59,MATCH(B98,اطلاعات_پرسنل!$A$4:$A$59,0)),"") -> فروشگاه | F98: =IFERROR(SUMIFS(لاگ_فاکتور!$V$3:$V$1622,لاگ_فاکتور!$B$3:$B$1622,A98,لاگ_فاکتور!$C$3:$C$1622,B98),0) -> 0 | G98: =IFERROR(SUMIFS(لاگ_فاکتور!$O$3:$O$1622,لاگ_فاکتور!$B$3:$B$1622,A98,لاگ_فاکتور!$C$3:$C$1622,B98),0) -> 0 | H98: =IFERROR(SUMIFS(لاگ_فاکتور!$N$3:$N$1622,لاگ_فاکتور!$B$3:$B$1622,A98,لاگ_فاکتور!$C$3:$C$1622,B98),0) -> 0 | I98: 0 | J98: 0 | K98: =IFERROR(F98/D98,0) -> 0 | L98: =IFERROR(G98/F98,0) -> 0 | M98: =IFERROR(SUMIFS(لاگ_فاکتور!$L$3:$L$1622,لاگ_فاکتور!$B$3:$B$1622,A98,لاگ_فاکتور!$C$3:$C$1622,B98)/F98,0) -> 0 | N98: 0
C99: =IFERROR(INDEX(اطلاعات_پرسنل!$D$4:$D$59,MATCH(B99,اطلاعات_پرسنل!$A$4:$A$59,0)),"") -> فروشگاه | F99: =IFERROR(SUMIFS(لاگ_فاکتور!$V$3:$V$1622,لاگ_فاکتور!$B$3:$B$1622,A99,لاگ_فاکتور!$C$3:$C$1622,B99),0) -> 0 | G99: =IFERROR(SUMIFS(لاگ_فاکتور!$O$3:$O$1622,لاگ_فاکتور!$B$3:$B$1622,A99,لاگ_فاکتور!$C$3:$C$1622,B99),0) -> 0 | H99: =IFERROR(SUMIFS(لاگ_فاکتور!$N$3:$N$1622,لاگ_فاکتور!$B$3:$B$1622,A99,لاگ_فاکتور!$C$3:$C$1622,B99),0) -> 0 | I99: 0 | J99: 0 | K99: =IFERROR(F99/D99,0) -> 0 | L99: =IFERROR(G99/F99,0) -> 0 | M99: =IFERROR(SUMIFS(لاگ_فاکتور!$L$3:$L$1622,لاگ_فاکتور!$B$3:$B$1622,A99,لاگ_فاکتور!$C$3:$C$1622,B99)/F99,0) -> 0 | N99: 0
C100: =IFERROR(INDEX(اطلاعات_پرسنل!$D$4:$D$59,MATCH(B100,اطلاعات_پرسنل!$A$4:$A$59,0)),"") -> فروشگاه | F100: =IFERROR(SUMIFS(لاگ_فاکتور!$V$3:$V$1622,لاگ_فاکتور!$B$3:$B$1622,A100,لاگ_فاکتور!$C$3:$C$1622,B100),0) -> 0 | G100: =IFERROR(SUMIFS(لاگ_فاکتور!$O$3:$O$1622,لاگ_فاکتور!$B$3:$B$1622,A100,لاگ_فاکتور!$C$3:$C$1622,B100),0) -> 0 | H100: =IFERROR(SUMIFS(لاگ_فاکتور!$N$3:$N$1622,لاگ_فاکتور!$B$3:$B$1622,A100,لاگ_فاکتور!$C$3:$C$1622,B100),0) -> 0 | I100: 0 | J100: 0 | K100: =IFERROR(F100/D100,0) -> 0 | L100: =IFERROR(G100/F100,0) -> 0 | M100: =IFERROR(SUMIFS(لاگ_فاکتور!$L$3:$L$1622,لاگ_فاکتور!$B$3:$B$1622,A100,لاگ_فاکتور!$C$3:$C$1622,B100)/F100,0) -> 0 | N100: 0
